Workbook

Sheet ReadMeFirst
A1: Read Me First - Documentation for this Excel Workbook
B3: Date | C3: 44718 | D3: 6C
B4: Description | C4: This Excel Workbook holds TrackR Production data on Components, Employees, WholeSale Prices
C5: This Excel Workbook documents the many AS-Is calculations of the Trackr manufacturing process.
C6: This Excel Workbook also holds the additional To-Be Calculation sheets for Team Member - <your name here>
C7: The TrackR Production Data Sheets (B, F, H, J, L) and As-Is Sheets (C, D, E, G, K) were developed thru Team Work
C8: The As-Is sheets (C, D, E, G, K) were duplicated, then modified, to make To-Be Sheets (<sheet codes here>)for one person's work
C9: The As-Is sheets (C, D, E, G, K) were not adjusted in any way during the To-Be phase of this work.
C10: These sheets hold calculation models of the TrackR Production business, and can be used to generate predictions
C11: Many cells in these sheets use values that come from other sheets, thru Vlookup, =<Cell>, or similar functions.
C12: All Core Data Values (walking speed, assembly times, costs, etc.) have Minimum and Maximum values, not just one value
B14: Authors Team
B15: To-Be Sheets Author
B17: Short Forms
A18: 1 | B18: Prodn | C18: Production
A19: 2 | B19: Avg | C19: Average
A20: 3 | B20: Ver | C20: Version
A21: 4 | B21: A Prefix in Tab Names | C21: As-Is
A22: 5 | B22: T Prefix in Tab Names | C22: To-Be
A23: 6 | B23: P&L | C23: Profit and Loss
B25: Below is the list of all the sheets included along with their authors
A27: Code | B27: Tab Name | C27: Full Sheet Name | D27: Authors | E27: Notes
A28: A | B28: ReadMeFirst
A29: B | B29: Components | C29: Components, Pricing, Inventory Location
A30: C | B30: A Picking | C30: Picking Distances, Times, Walking Speeds
A31: D | B31: A Assembly | C31: TrackR Assembly, Responses to Failures, Times, Costs, Summaries | E31: See the videos
A32: E | B32: A P&L | C32: As-Is Profit and Loss
A33: F | B33: Employees | C33: Employees, PayRates, Attitudes
A34: G | B34: A Schedule | C34: As-Is 8 hour Three Table Schedule for 9 Assembly Workers | E34: 10 minutes break every hour, 30 minute lunch
A35: H | B35: WholeSale | C35: TrackR WholeSale Prices for 2016 to 2019
A36: J | B36: DayProdn | C36: Day's Production of TrackR Versions - Data Table
A37: K | B37: VerAvgProdn | C37: Average Daily Production of TrackR versions 2018 Q4 and 2019 Q1 | E37: Pivot Table
A38: L | B38: POs | C38: Purchase Order Data for Components
B40: Assumptions: | C40: (some Assumptions are given at the top of sheets - ie Picking)
A41: 1 | B41: The time period of this project work
B42: Choice 1 | C42: as of now 2021
B43: Choice 2 | C43: as of May 2019
B44: Decision | C44: Choice 2

Sheet Components
A1: All Components, No TrackR Version Totals | K1: All Components, with TrackR Version Totals
H2: Unit Cost | K2: TrackR A | O2: Unit Cost
A3: ID # | B3: Manufacturer | C3: Part Number | D3: Description | E3: TrackR Version | F3: Shelf | G3: Bay | H3: Min | I3: Max | K3: ID # | L3: Part Number | M3: Description | N3: TrackR Version | O3: Min | P3: Max
A4: 1 | B4: Mitchell’s Plastics | C4: MPC432119-2 | D4: Vulcanized Rubber casing | E4: ABC | F4: =VLOOKUP(Table1[[#This Row],[Part Number]],'Shelving Inventory list'!$A$2:$C$72,2,FALSE) -> 10 | G4: =VLOOKUP(Table1[[#This Row],[Part Number]],'Shelving Inventory list'!$A$2:$C$72,3,FALSE) -> C | H4: =MIN(VLOOKUP(C4,POs!$B$2:$E$46,4,FALSE)) -> 6.606 | I4: =(Table1[[#This Row],[Min]]+0.05*Table1[[#This Row],[Min]]) -> 6.9363 | K4: 1 | L4: Mitchell’s Plastics | M4: MPC432119-2 | N4: ABC | O4: =MIN(VLOOKUP(M4,POs!$B$2:$E$46,4,FALSE)) -> 6.606 | P4: =(Table3[[#This Row],[Min]]+0.05*Table3[[#This Row],[Min]]) -> 6.9363
A5: 2 | B5: Mitchell’s Plastics | C5: MPC44422 | D5: Rigid plastic pins | E5: ABC | F5: =VLOOKUP(Table1[[#This Row],[Part Number]],'Shelving Inventory list'!$A$2:$C$72,2,FALSE) -> 10 | G5: =VLOOKUP(Table1[[#This Row],[Part Number]],'Shelving Inventory list'!$A$2:$C$72,3,FALSE) -> E | H5: =MIN(VLOOKUP(C5,POs!$B$2:$E$46,4,FALSE)) -> 0.081 | I5: =(Table1[[#This Row],[Min]]+0.05*Table1[[#This Row],[Min]]) -> 0.08505 | K5: 2 | L5: Mitchell’s Plastics | M5: MPC44422 | N5: ABC | O5: =MIN(VLOOKUP(M5,POs!$B$2:$E$46,4,FALSE)) -> 0.081 | P5: =(Table3[[#This Row],[Min]]+0.05*Table3[[#This Row],[Min]]) -> 0.08505
A6: 3 | B6: American Vanadium | C6: SFLV25 | D6: Slimflex Lithium-Vanadium printed battery | E6: ABC | F6: =VLOOKUP(Table1[[#This Row],[Part Number]],'Shelving Inventory list'!$A$2:$C$72,2,FALSE) -> 2 | G6: =VLOOKUP(Table1[[#This Row],[Part Number]],'Shelving Inventory list'!$A$2:$C$72,3,FALSE) -> A | H6: =MIN(VLOOKUP(C6,POs!$B$2:$E$46,4,FALSE)) -> 17.42 | I6: =(Table1[[#This Row],[Min]]+0.05*Table1[[#This Row],[Min]]) -> 18.291 | K6: 3 | L6: American Vanadium | M6: SFLV25 | N6: ABC | O6: =MIN(VLOOKUP(M6,POs!$B$2:$E$46,4,FALSE)) -> 17.42 | P6: =(Table3[[#This Row],[Min]]+0.05*Table3[[#This Row],[Min]]) -> 18.291
A7: 4 | B7: Foxconn | C7: FnOFI-GN1212 | D7: Main printed circuit board (PCB) | E7: ABC | F7: =VLOOKUP(Table1[[#This Row],[Part Number]],'Shelving Inventory list'!$A$2:$C$72,2,FALSE) -> 4 | G7: =VLOOKUP(Table1[[#This Row],[Part Number]],'Shelving Inventory list'!$A$2:$C$72,3,FALSE) -> D | H7: =MIN(VLOOKUP(C7,POs!$B$2:$E$46,4,FALSE)) -> 14.99 | I7: =(Table1[[#This Row],[Min]]+0.05*Table1[[#This Row],[Min]]) -> 15.7395 | K7: 4 | L7: Foxconn | M7: FnOFI-GN1212 | N7: ABC | O7: =MIN(VLOOKUP(M7,POs!$B$2:$E$46,4,FALSE)) -> 14.99 | P7: =(Table3[[#This Row],[Min]]+0.05*Table3[[#This Row],[Min]]) -> 15.7395
A8: 5 | B8: Qualcomm | C8: BD2098733AAB | D8: Secure housing for orientation equipment | E8: ABC | F8: =VLOOKUP(Table1[[#This Row],[Part Number]],'Shelving Inventory list'!$A$2:$C$72,2,FALSE) -> 5 | G8: =VLOOKUP(Table1[[#This Row],[Part Number]],'Shelving Inventory list'!$A$2:$C$72,3,FALSE) -> E | H8: =MIN(VLOOKUP(C8,POs!$B$2:$E$46,4,FALSE)) -> 4.15 | I8: =(Table1[[#This Row],[Min]]+0.05*Table1[[#This Row],[Min]]) -> 4.3575 | K8: 5 | L8: Qualcomm | M8: BD2098733AAB | N8: ABC | O8: =MIN(VLOOKUP(M8,POs!$B$2:$E$46,4,FALSE)) -> 4.15 | P8: =(Table3[[#This Row],[Min]]+0.05*Table3[[#This Row],[Min]]) -> 4.3575
A9: 6 | B9: Qualcomm | C9: BD20911131BB | D9: Micro-transmitter for LTE communication | E9: ABC | F9: =VLOOKUP(Table1[[#This Row],[Part Number]],'Shelving Inventory list'!$A$2:$C$72,2,FALSE) -> 6 | G9: =VLOOKUP(Table1[[#This Row],[Part Number]],'Shelving Inventory list'!$A$2:$C$72,3,FALSE) -> B | H9: =MIN(VLOOKUP(C9,POs!$B$2:$E$46,4,FALSE)) -> 1.88 | I9: =(Table1[[#This Row],[Min]]+0.05*Table1[[#This Row],[Min]]) -> 1.974 | K9: 6 | L9: Qualcomm | M9: BD20911131BB | N9: ABC | O9: =MIN(VLOOKUP(M9,POs!$B$2:$E$46,4,FALSE)) -> 1.88 | P9: =(Table3[[#This Row],[Min]]+0.05*Table3[[#This Row],[Min]]) -> 1.974
A10: 7 | B10: ST Microelectronics | C10: HG213123-221 | D10: 3-axis digital gyroscope | E10: ABC | F10: =VLOOKUP(Table1[[#This Row],[Part Number]],'Shelving Inventory list'!$A$2:$C$72,2,FALSE) -> 7 | G10: =VLOOKUP(Table1[[#This Row],[Part Number]],'Shelving Inventory list'!$A$2:$C$72,3,FALSE) -> B | H10: =MIN(VLOOKUP(C10,POs!$B$2:$E$46,4,FALSE)) -> 0.57 | I10: =(Table1[[#This Row],[Min]]+0.05*Table1[[#This Row],[Min]]) -> 0.5985 | K10: 7 | L10: ST Microelectronics | M10: HG213123-221 | N10: ABC | O10: =MIN(VLOOKUP(M10,POs!$B$2:$E$46,4,FALSE)) -> 0.57 | P10: =(Table3[[#This Row],[Min]]+0.05*Table3[[#This Row],[Min]]) -> 0.5985
A11: 8 | B11: ST Microelectronics | C11: STMA11233 | D11: 2-axis analogue accelerometer | E11: ABC | F11: =VLOOKUP(Table1[[#This Row],[Part Number]],'Shelving Inventory list'!$A$2:$C$72,2,FALSE) -> 8 | G11: =VLOOKUP(Table1[[#This Row],[Part Number]],'Shelving Inventory list'!$A$2:$C$72,3,FALSE) -> E | H11: =MIN(VLOOKUP(C11,POs!$B$2:$E$46,4,FALSE)) -> 0.31 | I11: =(Table1[[#This Row],[Min]]+0.05*Table1[[#This Row],[Min]]) -> 0.3255 | K11: 8 | L11: ST Microelectronics | M11: STMA11233 | N11: ABC | O11: =MIN(VLOOKUP(M11,POs!$B$2:$E$46,4,FALSE)) -> 0.31 | P11: =(Table3[[#This Row],[Min]]+0.05*Table3[[#This Row],[Min]]) -> 0.3255
A12: 9 | B12: Samsung | C12: SS98AAIS | D12: 18mm x 29mm OLED screen | E12: ABC | F12: =VLOOKUP(Table1[[#This Row],[Part Number]],'Shelving Inventory list'!$A$2:$C$72,2,FALSE) -> 7 | G12: =VLOOKUP(Table1[[#This Row],[Part Number]],'Shelving Inventory list'!$A$2:$C$72,3,FALSE) -> E | H12: =MIN(VLOOKUP(C12,POs!$B$2:$E$46,4,FALSE)) -> 38.15 | I12: =(Table1[[#This Row],[Min]]+0.05*Table1[[#This Row],[Min]]) -> 40.0575 | K12: 9 | L12: Samsung | M12: SS98AAIS | N12: ABC | O12: =MIN(VLOOKUP(M12,POs!$B$2:$E$46,4,FALSE)) -> 38.15 | P12: =(Table3[[#This Row],[Min]]+0.05*Table3[[#This Row],[Min]]) -> 40.0575
A13: 10 | B13: Sandisk | C13: SDMALBB3033G | D13: 2GB FLASH NAND | E13: ABC | F13: =VLOOKUP(Table1[[#This Row],[Part Number]],'Shelving Inventory list'!$A$2:$C$72,2,FALSE) -> 3 | G13: =VLOOKUP(Table1[[#This Row],[Part Number]],'Shelving Inventory list'!$A$2:$C$72,3,FALSE) -> C | H13: =MIN(VLOOKUP(C13,POs!$B$2:$E$46,4,FALSE)) -> 4 | I13: =(Table1[[#This Row],[Min]]+0.05*Table1[[#This Row],[Min]]) -> 4.2 | K13: 10 | L13: Sandisk | M13: SDMALBB3033G | N13: ABC | O13: =MIN(VLOOKUP(M13,POs!$B$2:$E$46,4,FALSE)) -> 4 | P13: =(Table3[[#This Row],[Min]]+0.05*Table3[[#This Row],[Min]]) -> 4.2
A14: 11 | B14: BlueGiga | C14: BLE112 | D14: Bluetooth 4.0 low energy chipset | E14: ABC | F14: =VLOOKUP(Table1[[#This Row],[Part Number]],'Shelving Inventory list'!$A$2:$C$72,2,FALSE) -> 1 | G14: =VLOOKUP(Table1[[#This Row],[Part Number]],'Shelving Inventory list'!$A$2:$C$72,3,FALSE) -> A | H14: =MIN(VLOOKUP(C14,POs!$B$2:$E$46,4,FALSE)) -> 2 | I14: =(Table1[[#This Row],[Min]]+0.05*Table1[[#This Row],[Min]]) -> 2.1 | K14: 11 | L14: BlueGiga | M14: BLE112 | N14: ABC | O14: =MIN(VLOOKUP(M14,POs!$B$2:$E$46,4,FALSE)) -> 2 | P14: =(Table3[[#This Row],[Min]]+0.05*Table3[[#This Row],[Min]]) -> 2.1
A15: 12 | B15: Banda Bracelets (HK) Ltd. | C15: LS1121 | D15: Plastic wrist strap | E15: B | F15: =VLOOKUP(Table1[[#This Row],[Part Number]],'Shelving Inventory list'!$A$2:$C$72,2,FALSE) -> 14 | G15: =VLOOKUP(Table1[[#This Row],[Part Number]],'Shelving Inventory list'!$A$2:$C$72,3,FALSE) -> A | H15: =MIN(VLOOKUP(C15,POs!$B$2:$E$46,4,FALSE)) -> 3 | I15: =(Table1[[#This Row],[Min]]+0.05*Table1[[#This Row],[Min]]) -> 3.15 | K15: 12 | L15: Banda Bracelets (HK) Ltd. | M15: LS1124 | N15: A | O15: =MIN(VLOOKUP(M15,POs!$B$2:$E$46,4,FALSE)) -> 6 | P15: =(Table3[[#This Row],[Min]]+0.05*Table3[[#This Row],[Min]]) -> 6.3
A16: 13 | B16: Banda Bracelets (HK) Ltd. | C16: LS1124 | D16: Leather wrist strap | E16: A | F16: =VLOOKUP(Table1[[#This Row],[Part Number]],'Shelving Inventory list'!$A$2:$C$72,2,FALSE) -> 14 | G16: =VLOOKUP(Table1[[#This Row],[Part Number]],'Shelving Inventory list'!$A$2:$C$72,3,FALSE) -> B | H16: =MIN(VLOOKUP(C16,POs!$B$2:$E$46,4,FALSE)) -> 6 | I16: =(Table1[[#This Row],[Min]]+0.05*Table1[[#This Row],[Min]]) -> 6.3 | K16: 13 | L16: Banda Bracelets (HK) Ltd. | M16: KK433 | N16: A | O16: =MIN(VLOOKUP(M16,POs!$B$2:$E$46,4,FALSE)) -> 3 | P16: =(Table3[[#This Row],[Min]]+0.05*Table3[[#This Row],[Min]]) -> 3.15
A17: 14 | B17: Banda Bracelets (HK) Ltd. | C17: LS1128 | D17: Gold expansion strap | E17: C | F17: =VLOOKUP(Table1[[#This Row],[Part Number]],'Shelving Inventory list'!$A$2:$C$72,2,FALSE) -> 13 | G17: =VLOOKUP(Table1[[#This Row],[Part Number]],'Shelving Inventory list'!$A$2:$C$72,3,FALSE) -> D | H17: =MIN(VLOOKUP(C17,POs!$B$2:$E$46,4,FALSE)) -> 10 | I17: =(Table1[[#This Row],[Min]]+0.05*Table1[[#This Row],[Min]]) -> 10.5 | K17: Total | P17: =SUBTOTAL(109,Table3[Max]) -> 104.11485
A18: 15 | B18: Banda Bracelets (HK) Ltd. | C18: KK425 | D18: Economy TrackR Packaging | E18: B | F18: =VLOOKUP(Table1[[#This Row],[Part Number]],'Shelving Inventory list'!$A$2:$C$72,2,FALSE) -> 14 | G18: =VLOOKUP(Table1[[#This Row],[Part Number]],'Shelving Inventory list'!$A$2:$C$72,3,FALSE) -> A | H18: =MIN(VLOOKUP(C18,POs!$B$2:$E$46,4,FALSE)) -> 2 | I18: =(Table1[[#This Row],[Min]]+0.05*Table1[[#This Row],[Min]]) -> 2.1
A19: 16 | B19: Banda Bracelets (HK) Ltd. | C19: KK433 | D19: Standard TrackR packaging | E19: A | F19: =VLOOKUP(Table1[[#This Row],[Part Number]],'Shelving Inventory list'!$A$2:$C$72,2,FALSE) -> 14 | G19: =VLOOKUP(Table1[[#This Row],[Part Number]],'Shelving Inventory list'!$A$2:$C$72,3,FALSE) -> B | H19: =MIN(VLOOKUP(C19,POs!$B$2:$E$46,4,FALSE)) -> 3 | I19: =(Table1[[#This Row],[Min]]+0.05*Table1[[#This Row],[Min]]) -> 3.15
A20: 17 | B20: Banda Bracelets (HK) Ltd. | C20: KK438 | D20: DeLuxe TrackR packaging | E20: C | F20: =VLOOKUP(Table1[[#This Row],[Part Number]],'Shelving Inventory list'!$A$2:$C$72,2,FALSE) -> 13 | G20: =VLOOKUP(Table1[[#This Row],[Part Number]],'Shelving Inventory list'!$A$2:$C$72,3,FALSE) -> D | H20: =MIN(VLOOKUP(C20,POs!$B$2:$E$46,4,FALSE)) -> 4 | I20: =(Table1[[#This Row],[Min]]+0.05*Table1[[#This Row],[Min]]) -> 4.2
K22: TrackR B | O22: Unit Cost
K23: ID # | L23: Part Number | M23: Description | N23: TrackR Version | O23: Min | P23: Max
A24: Increase max to 5% | K24: 1 | L24: Mitchell’s Plastics | M24: MPC432119-2 | N24: ABC | O24: =MIN(VLOOKUP(M24,POs!$B$1:$E$46,4,FALSE)) -> 6.606 | P24: =(Table4[[#This Row],[Min]]+0.05*Table4[[#This Row],[Min]]) -> 6.9363
K25: 2 | L25: Mitchell’s Plastics | M25: MPC44422 | N25: ABC | O25: =MIN(VLOOKUP(M25,POs!$B$1:$E$46,4,FALSE)) -> 0.081 | P25: =(Table4[[#This Row],[Min]]+0.05*Table4[[#This Row],[Min]]) -> 0.08505
K26: 3 | L26: American Vanadium | M26: SFLV25 | N26: ABC | O26: =MIN(VLOOKUP(M26,POs!$B$1:$E$46,4,FALSE)) -> 17.42 | P26: =(Table4[[#This Row],[Min]]+0.05*Table4[[#This Row],[Min]]) -> 18.291
K27: 4 | L27: Foxconn | M27: FnOFI-GN1212 | N27: ABC | O27: =MIN(VLOOKUP(M27,POs!$B$1:$E$46,4,FALSE)) -> 14.99 | P27: =(Table4[[#This Row],[Min]]+0.05*Table4[[#This Row],[Min]]) -> 15.7395
K28: 5 | L28: Qualcomm | M28: BD2098733AAB | N28: ABC | O28: =MIN(VLOOKUP(M28,POs!$B$1:$E$46,4,FALSE)) -> 4.15 | P28: =(Table4[[#This Row],[Min]]+0.05*Table4[[#This Row],[Min]]) -> 4.3575
K29: 6 | L29: Qualcomm | M29: BD20911131BB | N29: ABC | O29: =MIN(VLOOKUP(M29,POs!$B$1:$E$46,4,FALSE)) -> 1.88 | P29: =(Table4[[#This Row],[Min]]+0.05*Table4[[#This Row],[Min]]) -> 1.974
K30: 7 | L30: ST Microelectronics | M30: HG213123-221 | N30: ABC | O30: =MIN(VLOOKUP(M30,POs!$B$1:$E$46,4,FALSE)) -> 0.57 | P30: =(Table4[[#This Row],[Min]]+0.05*Table4[[#This Row],[Min]]) -> 0.5985
K31: 8 | L31: ST Microelectronics | M31: STMA11233 | N31: ABC | O31: =MIN(VLOOKUP(M31,POs!$B$1:$E$46,4,FALSE)) -> 0.31 | P31: =(Table4[[#This Row],[Min]]+0.05*Table4[[#This Row],[Min]]) -> 0.3255
K32: 9 | L32: Samsung | M32: SS98AAIS | N32: ABC | O32: =MIN(VLOOKUP(M32,POs!$B$1:$E$46,4,FALSE)) -> 38.15 | P32: =(Table4[[#This Row],[Min]]+0.05*Table4[[#This Row],[Min]]) -> 40.0575
K33: 10 | L33: Sandisk | M33: SDMALBB3033G | N33: ABC | O33: =MIN(VLOOKUP(M33,POs!$B$1:$E$46,4,FALSE)) -> 4 | P33: =(Table4[[#This Row],[Min]]+0.05*Table4[[#This Row],[Min]]) -> 4.2
K34: 11 | L34: BlueGiga | M34: BLE112 | N34: ABC | O34: =MIN(VLOOKUP(M34,POs!$B$1:$E$46,4,FALSE)) -> 2 | P34: =(Table4[[#This Row],[Min]]+0.05*Table4[[#This Row],[Min]]) -> 2.1
K35: 12 | L35: Banda Bracelets (HK) Ltd. | M35: LS1121 | N35: B | O35: =MIN(VLOOKUP(M35,POs!$B$1:$E$46,4,FALSE)) -> 3 | P35: =(Table4[[#This Row],[Min]]+0.05*Table4[[#This Row],[Min]]) -> 3.15
K36: 13 | L36: Banda Bracelets (HK) Ltd. | M36: KK425 | N36: B | O36: =MIN(VLOOKUP(M36,POs!$B$1:$E$46,4,FALSE)) -> 2 | P36: =(Table4[[#This Row],[Min]]+0.05*Table4[[#This Row],[Min]]) -> 2.1
K37: Total | P37: =SUBTOTAL(109,Table4[Max]) -> 99.91485
K40: TrackR C | O40: Unit Cost
K41: ID # | L41: Part Number | M41: Description | N41: TrackR Version | O41: Min | P41: Max
K42: 1 | L42: Mitchell’s Plastics | M42: MPC432119-2 | N42: ABC | O42: =MIN(VLOOKUP(M42,POs!$B$2:$E$46,4,FALSE)) -> 6.606 | P42: =(Table5[[#This Row],[Min]]+0.05*Table5[[#This Row],[Min]]) -> 6.9363
K43: 2 | L43: Mitchell’s Plastics | M43: MPC44422 | N43: ABC | O43: =MIN(VLOOKUP(M43,POs!$B$2:$E$46,4,FALSE)) -> 0.081 | P43: =(Table5[[#This Row],[Min]]+0.05*Table5[[#This Row],[Min]]) -> 0.08505
K44: 3 | L44: American Vanadium | M44: SFLV25 | N44: ABC | O44: =MIN(VLOOKUP(M44,POs!$B$2:$E$46,4,FALSE)) -> 17.42 | P44: =(Table5[[#This Row],[Min]]+0.05*Table5[[#This Row],[Min]]) -> 18.291
K45: 4 | L45: Foxconn | M45: FnOFI-GN1212 | N45: ABC | O45: =MIN(VLOOKUP(M45,POs!$B$2:$E$46,4,FALSE)) -> 14.99 | P45: =(Table5[[#This Row],[Min]]+0.05*Table5[[#This Row],[Min]]) -> 15.7395
K46: 5 | L46: Qualcomm | M46: BD2098733AAB | N46: ABC | O46: =MIN(VLOOKUP(M46,POs!$B$2:$E$46,4,FALSE)) -> 4.15 | P46: =(Table5[[#This Row],[Min]]+0.05*Table5[[#This Row],[Min]]) -> 4.3575
K47: 6 | L47: Qualcomm | M47: BD20911131BB | N47: ABC | O47: =MIN(VLOOKUP(M47,POs!$B$2:$E$46,4,FALSE)) -> 1.88 | P47: =(Table5[[#This Row],[Min]]+0.05*Table5[[#This Row],[Min]]) -> 1.974
K48: 7 | L48: ST Microelectronics | M48: HG213123-221 | N48: ABC | O48: =MIN(VLOOKUP(M48,POs!$B$2:$E$46,4,FALSE)) -> 0.57 | P48: =(Table5[[#This Row],[Min]]+0.05*Table5[[#This Row],[Min]]) -> 0.5985
K49: 8 | L49: ST Microelectronics | M49: STMA11233 | N49: ABC | O49: =MIN(VLOOKUP(M49,POs!$B$2:$E$46,4,FALSE)) -> 0.31 | P49: =(Table5[[#This Row],[Min]]+0.05*Table5[[#This Row],[Min]]) -> 0.3255
K50: 9 | L50: Samsung | M50: SS98AAIS | N50: ABC | O50: =MIN(VLOOKUP(M50,POs!$B$2:$E$46,4,FALSE)) -> 38.15 | P50: =(Table5[[#This Row],[Min]]+0.05*Table5[[#This Row],[Min]]) -> 40.0575
K51: 10 | L51: Sandisk | M51: SDMALBB3033G | N51: ABC | O51: =MIN(VLOOKUP(M51,POs!$B$2:$E$46,4,FALSE)) -> 4 | P51: =(Table5[[#This Row],[Min]]+0.05*Table5[[#This Row],[Min]]) -> 4.2
K52: 11 | L52: BlueGiga | M52: BLE112 | N52: ABC | O52: =MIN(VLOOKUP(M52,POs!$B$2:$E$46,4,FALSE)) -> 2 | P52: =(Table5[[#This Row],[Min]]+0.05*Table5[[#This Row],[Min]]) -> 2.1
K53: 12 | L53: Banda Bracelets (HK) Ltd. | M53: LS1128 | N53: C | O53: =MIN(VLOOKUP(M53,POs!$B$2:$E$46,4,FALSE)) -> 10 | P53: =(Table5[[#This Row],[Min]]+0.05*Table5[[#This Row],[Min]]) -> 10.5
K54: 13 | L54: Banda Bracelets (HK) Ltd. | M54: KK438 | N54: C | O54: =MIN(VLOOKUP(M54,POs!$B$2:$E$46,4,FALSE)) -> 4 | P54: =(Table5[[#This Row],[Min]]+0.05*Table5[[#This Row],[Min]]) -> 4.2
K55: Total | P55: =SUBTOTAL(109,Table5[Max]) -> 109.36485

Sheet A Picking
A2: Data Sources
B3: The distance data in this table comes from:
A5: Assumptions | C5: Issue | H5: Options # | I5: Description | L5: Chosen | M5: Notes and Sources of Knowledge
B6: 1 | C6: What is the Slow Walking Speed for Picking? | L6: 1.1 | N6: m/sec | O6: Tired persons walking at the end of the shift
H7: 1 | I7: 1.1 | J7: m/sec | L7: take the standard value from google
H8: 2 | I8: 1.15 | J8: m/sec
H9: 3 | I9: 1.2 | J9: m/sec
B11: 2 | C11: What is the Fast Walking Speed for Picking? | L11: 1.8 | N11: m/sec | O11: Persons walking at the start of the shift
H12: 1 | I12: 1.8 | J12: m/sec | L12: take the standard value from google
H13: 2 | I13: 1.9 | J13: m/sec
H14: 3 | I14: 1.95 | J14: m/sec
B16: 3 | C16: What is the time spent picking up a part from a shelf's bay, after a person has walked and is standing in front of it?
H17: 1 | I17: 8 | J17: seconds
H18: 2 | I18: 10 | J18: seconds
A20: Additional Process Knowledge
B21: 1 | C21: The picking Strategy is: | E21: The parts closer to the production area will be picked up first and then the parts which are far from the production area will be picked up
C22: What is the best way to pick? | E22: Picking up multiple parts at the same time while also making sure no part is dropped or damaged in any way which are closer to the production area and then going for parts which are far .
C23: Would this be the same route used for the entire day by everyone? How boring! | H23: Yes
C24: The OHT VP Production VP tells me that each person decides for themselves how to pick components.
C25: - OHT VP Production, May 16
A27: Calculations for Distance, Min and Max Times to pick One Set of Components in preparation for Assembly of those Components
C29: Component | G29: Distance | H29: - time in seconds - | K29: Cumulative Time (seconds)
B30: Pick Seq | C30: ID | D30: Part # | E30: Shelf | F30: Bay | G30: (Meters) | H30: Slow Walk | I30: Fast Walk | J30: Pick from Shelf | K30: Maximum | L30: Minimum
B31: 4 | C31: 1 | D31: MPC432119-2 | E31: =VLOOKUP(Table6[[#This Row],[Part '#]],Table1[[Part Number]:[Shelf]],4,FALSE) -> 10 | F31: =VLOOKUP(Table6[[#This Row],[Part '#]],Table1[[Part Number]:[Bay]],5,FALSE) -> C | G31: 4.7 | H31: 4.273 | I31: 2.611 | J31: 8 | K31: =Table6[[#This Row],[Slow Walk]]+Table6[[#This Row],[Pick from Shelf]] -> 12.273 | L31: =Table6[[#This Row],[Fast Walk]]+Table6[[#This Row],[Pick from Shelf]] -> 10.611
B32: 5 | C32: 2 | D32: MPC44422 | E32: =VLOOKUP(Table6[[#This Row],[Part '#]],Table1[[Part Number]:[Shelf]],4,FALSE) -> 10 | F32: =VLOOKUP(Table6[[#This Row],[Part '#]],Table1[[Part Number]:[Bay]],5,FALSE) -> E | G32: 4.7 | H32: 4.273 | I32: 2.611 | J32: 8 | K32: =K31+Table6[[#This Row],[Slow Walk]]+Table6[[#This Row],[Pick from Shelf]] -> 24.546 | L32: =L31+Table6[[#This Row],[Fast Walk]]+Table6[[#This Row],[Pick from Shelf]] -> 21.222
B33: 12 | C33: 3 | D33: SFLV25 | E33: =VLOOKUP(Table6[[#This Row],[Part '#]],Table1[[Part Number]:[Shelf]],4,FALSE) -> 2 | F33: =VLOOKUP(Table6[[#This Row],[Part '#]],Table1[[Part Number]:[Bay]],5,FALSE) -> A | G33: 3.69 | H33: 3.355 | I33: 2.05 | J33: 8 | K33: =K32+Table6[[#This Row],[Slow Walk]]+Table6[[#This Row],[Pick from Shelf]] -> 35.901 | L33: =L32+Table6[[#This Row],[Fast Walk]]+Table6[[#This Row],[Pick from Shelf]] -> 31.272
B34: 10 | C34: 4 | D34: FnOFI-GN1212 | E34: =VLOOKUP(Table6[[#This Row],[Part '#]],Table1[[Part Number]:[Shelf]],4,FALSE) -> 4 | F34: =VLOOKUP(Table6[[#This Row],[Part '#]],Table1[[Part Number]:[Bay]],5,FALSE) -> D | G34: 2.18 | H34: 1.982 | I34: 1.211 | J34: 8 | K34: =K33+Table6[[#This Row],[Slow Walk]]+Table6[[#This Row],[Pick from Shelf]] -> 45.883 | L34: =L33+Table6[[#This Row],[Fast Walk]]+Table6[[#This Row],[Pick from Shelf]] -> 40.483
B35: 9 | C35: 5 | D35: BD2098733AAB | E35: =VLOOKUP(Table6[[#This Row],[Part '#]],Table1[[Part Number]:[Shelf]],4,FALSE) -> 5 | F35: =VLOOKUP(Table6[[#This Row],[Part '#]],Table1[[Part Number]:[Bay]],5,FALSE) -> E | G35: 3.23 | H35: 2.936 | I35: 1.794 | J35: 8 | K35: =K34+Table6[[#This Row],[Slow Walk]]+Table6[[#This Row],[Pick from Shelf]] -> 56.819 | L35: =L34+Table6[[#This Row],[Fast Walk]]+Table6[[#This Row],[Pick from Shelf]] -> 50.277
B36: 8 | C36: 6 | D36: BD20911131BB | E36: =VLOOKUP(Table6[[#This Row],[Part '#]],Table1[[Part Number]:[Shelf]],4,FALSE) -> 6 | F36: =VLOOKUP(Table6[[#This Row],[Part '#]],Table1[[Part Number]:[Bay]],5,FALSE) -> B | G36: 2.76 | H36: 2.509 | I36: 1.533 | J36: 8 | K36: =K35+Table6[[#This Row],[Slow Walk]]+Table6[[#This Row],[Pick from Shelf]] -> 67.328 | L36: =L35+Table6[[#This Row],[Fast Walk]]+Table6[[#This Row],[Pick from Shelf]] -> 59.81
B37: 6 | C37: 7 | D37: HG213123-221 | E37: =VLOOKUP(Table6[[#This Row],[Part '#]],Table1[[Part Number]:[Shelf]],4,FALSE) -> 7 | F37: =VLOOKUP(Table6[[#This Row],[Part '#]],Table1[[Part Number]:[Bay]],5,FALSE) -> B | G37: 85.11 | H37: 77.373 | I37: 47.283 | J37: 8 | K37: =K36+Table6[[#This Row],[Slow Walk]]+Table6[[#This Row],[Pick from Shelf]] -> 152.701 | L37: =L36+Table6[[#This Row],[Fast Walk]]+Table6[[#This Row],[Pick from Shelf]] -> 115.093
B38: 3 | C38: 8 | D38: STMA11233 | E38: =VLOOKUP(Table6[[#This Row],[Part '#]],Table1[[Part Number]:[Shelf]],4,FALSE) -> 8 | F38: =VLOOKUP(Table6[[#This Row],[Part '#]],Table1[[Part Number]:[Bay]],5,FALSE) -> E | G38: 7.45 | H38: 6.773 | I38: 4.139 | J38: 8 | K38: =K37+Table6[[#This Row],[Slow Walk]]+Table6[[#This Row],[Pick from Shelf]] -> 167.474 | L38: =L37+Table6[[#This Row],[Fast Walk]]+Table6[[#This Row],[Pick from Shelf]] -> 127.232
B39: 7 | C39: 9 | D39: SS98AAIS | E39: =VLOOKUP(Table6[[#This Row],[Part '#]],Table1[[Part Number]:[Shelf]],4,FALSE) -> 7 | F39: =VLOOKUP(Table6[[#This Row],[Part '#]],Table1[[Part Number]:[Bay]],5,FALSE) -> E | G39: 85.11 | H39: 77.373 | I39: 47.283 | J39: 8 | K39: =K38+Table6[[#This Row],[Slow Walk]]+Table6[[#This Row],[Pick from Shelf]] -> 252.847 | L39: =L38+Table6[[#This Row],[Fast Walk]]+Table6[[#This Row],[Pick from Shelf]] -> 182.515
B40: 11 | C40: 10 | D40: SDMALBB3033G | E40: =VLOOKUP(Table6[[#This Row],[Part '#]],Table1[[Part Number]:[Shelf]],4,FALSE) -> 3 | F40: =VLOOKUP(Table6[[#This Row],[Part '#]],Table1[[Part Number]:[Bay]],5,FALSE) -> C | G40: 4.26 | H40: 3.873 | I40: 2.367 | J40: 8 | K40: =K39+Table6[[#This Row],[Slow Walk]]+Table6[[#This Row],[Pick from Shelf]] -> 264.72 | L40: =L39+Table6[[#This Row],[Fast Walk]]+Table6[[#This Row],[Pick from Shelf]] -> 192.882
B41: 13 | C41: 11 | D41: BLE112 | E41: =VLOOKUP(Table6[[#This Row],[Part '#]],Table1[[Part Number]:[Shelf]],4,FALSE) -> 1 | F41: =VLOOKUP(Table6[[#This Row],[Part '#]],Table1[[Part Number]:[Bay]],5,FALSE) -> A | G41: 4.33 | H41: 3.936 | I41: 2.406 | J41: 8 | K41: =K40+Table6[[#This Row],[Slow Walk]]+Table6[[#This Row],[Pick from Shelf]] -> 276.656 | L41: =L40+Table6[[#This Row],[Fast Walk]]+Table6[[#This Row],[Pick from Shelf]] -> 203.288
B42: 1 | C42: 12 | D42: LS1121 | E42: =VLOOKUP(Table6[[#This Row],[Part '#]],Table1[[Part Number]:[Shelf]],4,FALSE) -> 14 | F42: =VLOOKUP(Table6[[#This Row],[Part '#]],Table1[[Part Number]:[Bay]],5,FALSE) -> A | G42: 25.47 | H42: 23.155 | I42: 14.15 | J42: 8 | K42: =K41+Table6[[#This Row],[Slow Walk]]+Table6[[#This Row],[Pick from Shelf]] -> 307.811 | L42: =L41+Table6[[#This Row],[Fast Walk]]+Table6[[#This Row],[Pick from Shelf]] -> 225.438
B43: 2 | C43: 13 | D43: KK433 | E43: =VLOOKUP(Table6[[#This Row],[Part '#]],Table1[[Part Number]:[Shelf]],4,FALSE) -> 14 | F43: =VLOOKUP(Table6[[#This Row],[Part '#]],Table1[[Part Number]:[Bay]],5,FALSE) -> B | G43: 25.47 | H43: 23.155 | I43: 14.15 | J43: 8 | K43: =K42+Table6[[#This Row],[Slow Walk]]+Table6[[#This Row],[Pick from Shelf]] -> 338.966 | L43: =L42+Table6[[#This Row],[Fast Walk]]+Table6[[#This Row],[Pick from Shelf]] -> 247.588
B51: Total Minimum Walking and Picking Time | E51: =MIN(L31:L43) -> 10.611
B52: Total Maximum Walking and Picking Time | E52: =MAX(K31:K43) -> 338.966

Sheet T Picking
A2: Data Sources
B3: The distance data in this table comes from:
A5: Assumptions | C5: Issue | H5: Options # | I5: Description | L5: Chosen | M5: Notes and Sources of Knowledge
B6: 1 | C6: What is the Slow Walking Speed for Picking? | L6: 1.1 | N6: m/sec | O6: Tired persons walking at the end of the shift
H7: 1 | I7: 1.1 | J7: m/sec | L7: take the standard value from google
H8: 2 | I8: 1.15 | J8: m/sec
H9: 3 | I9: 1.2 | J9: m/sec
B11: 2 | C11: What is the Fast Walking Speed for Picking? | L11: 1.8 | N11: m/sec | O11: Persons walking at the start of the shift
H12: 1 | I12: 1.8 | J12: m/sec | L12: take the standard value from google
H13: 2 | I13: 1.9 | J13: m/sec
H14: 3 | I14: 1.95 | J14: m/sec
B16: 3 | C16: What is the time spent picking up a part from a shelf's bay, after a person has walked and is standing in front of it?
H17: 1 | I17: 8 | J17: seconds
H18: 2 | I18: 10 | J18: seconds
A20: Additional Process Knowledge
B21: 1 | C21: The picking Strategy is: | E21: The parts closer to the production area will be picked up first and then the parts which are far from the production area will be picked up
C22: What is the best way to pick? | E22: Picking up multiple parts at the same time while also making sure no part is dropped or damaged in any way which are closer to the production area and then going for parts which are far .
C23: Would this be the same route used for the entire day by everyone? How boring! | H23: Yes
C24: The OHT VP Production VP tells me that each person decides for themselves how to pick components.
C25: - OHT VP Production, May 16
A27: Calculations for Distance, Min and Max Times to pick One Set of Components in preparation for Assembly of those Components
C29: Component | G29: Distance | H29: - time in seconds - | K29: Cumulative Time (seconds)
B30: Pick Seq | C30: ID | D30: Part # | E30: Shelf | F30: Bay | G30: (Meters) | H30: Slow Walk | I30: Fast Walk | J30: Pick from Shelf | K30: Maximum | L30: Minimum
B31: 12 | C31: 1 | D31: MPC432119-2 | E31: =VLOOKUP(Table616[[#This Row],[Part '#]],Table1[[Part Number]:[Shelf]],4,FALSE) -> 10 | F31: =VLOOKUP(Table616[[#This Row],[Part '#]],Table1[[Part Number]:[Bay]],5,FALSE) -> C | G31: 2.6 | H31: =G31/1.1 -> 2.3636364 | I31: =Table616[[#This Row],[(Meters)]]/1.8 -> 1.4444444 | J31: 8 | K31: =Table616[[#This Row],[Slow Walk]]+Table616[[#This Row],[Pick from Shelf]] -> 10.363636 | L31: =Table616[[#This Row],[Fast Walk]]+Table616[[#This Row],[Pick from Shelf]] -> 9.4444444
B32: 13 | C32: 2 | D32: MPC44422 | E32: =VLOOKUP(Table616[[#This Row],[Part '#]],Table1[[Part Number]:[Shelf]],4,FALSE) -> 10 | F32: =VLOOKUP(Table616[[#This Row],[Part '#]],Table1[[Part Number]:[Bay]],5,FALSE) -> E | G32: 2.6 | H32: =G32/1.1 -> 2.3636364 | I32: =Table616[[#This Row],[(Meters)]]/1.8 -> 1.4444444 | J32: 8 | K32: =H32+J32+K31 -> 20.727273 | L32: =I32+J32+L31 -> 18.888889
B33: 2 | C33: 3 | D33: SFLV25 | E33: =VLOOKUP(Table616[[#This Row],[Part '#]],Table1[[Part Number]:[Shelf]],4,FALSE) -> 2 | F33: =VLOOKUP(Table616[[#This Row],[Part '#]],Table1[[Part Number]:[Bay]],5,FALSE) -> A | G33: 2.1 | H33: =G33/1.1 -> 1.9090909 | I33: =Table616[[#This Row],[(Meters)]]/1.8 -> 1.1666667 | J33: 8 | K33: =H33+J33+K32 -> 30.636364 | L33: =I33+J33+L32 -> 28.055556
B34: 7 | C34: 4 | D34: FnOFI-GN1212 | E34: =VLOOKUP(Table616[[#This Row],[Part '#]],Table1[[Part Number]:[Shelf]],4,FALSE) -> 4 | F34: =VLOOKUP(Table616[[#This Row],[Part '#]],Table1[[Part Number]:[Bay]],5,FALSE) -> D | G34: 0.6 | H34: =G34/1.1 -> 0.54545455 | I34: =Table616[[#This Row],[(Meters)]]/1.8 -> 0.33333333 | J34: 8 | K34: =H34+J34+K33 -> 39.181818 | L34: =I34+J34+L33 -> 36.388889
B35: 6 | C35: 5 | D35: BD2098733AAB | E35: =VLOOKUP(Table616[[#This Row],[Part '#]],Table1[[Part Number]:[Shelf]],4,FALSE) -> 5 | F35: =VLOOKUP(Table616[[#This Row],[Part '#]],Table1[[Part Number]:[Bay]],5,FALSE) -> E | G35: 2.3 | H35: =G35/1.1 -> 2.0909091 | I35: =Table616[[#This Row],[(Meters)]]/1.8 -> 1.2777778 | J35: 8 | K35: =H35+J35+K34 -> 49.272727 | L35: =I35+J35+L34 -> 45.666667
B36: 10 | C36: 6 | D36: BD20911131BB | E36: =VLOOKUP(Table616[[#This Row],[Part '#]],Table1[[Part Number]:[Shelf]],4,FALSE) -> 6 | F36: =VLOOKUP(Table616[[#This Row],[Part '#]],Table1[[Part Number]:[Bay]],5,FALSE) -> B | G36: 0.5 | H36: =G36/1.1 -> 0.45454545 | I36: =Table616[[#This Row],[(Meters)]]/1.8 -> 0.27777778 | J36: 8 | K36: =H36+J36+K35 -> 57.727273 | L36: =I36+J36+L35 -> 53.944444
B37: 8 | C37: 7 | D37: HG213123-221 | E37: =VLOOKUP(Table616[[#This Row],[Part '#]],Table1[[Part Number]:[Shelf]],4,FALSE) -> 7 | F37: =VLOOKUP(Table616[[#This Row],[Part '#]],Table1[[Part Number]:[Bay]],5,FALSE) -> B | G37: 8.1 | H37: =G37/1.1 -> 7.3636364 | I37: =Table616[[#This Row],[(Meters)]]/1.8 -> 4.5 | J37: 8 | K37: =H37+J37+K36 -> 73.090909 | L37: =I37+J37+L36 -> 66.444444
B38: 11 | C38: 8 | D38: STMA11233 | E38: =VLOOKUP(Table616[[#This Row],[Part '#]],Table1[[Part Number]:[Shelf]],4,FALSE) -> 8 | F38: =VLOOKUP(Table616[[#This Row],[Part '#]],Table1[[Part Number]:[Bay]],5,FALSE) -> E | G38: 18.2 | H38: =G38/1.1 -> 16.545455 | I38: =Table616[[#This Row],[(Meters)]]/1.8 -> 10.111111 | J38: 8 | K38: =H38+J38+K37 -> 97.636364 | L38: =I38+J38+L37 -> 84.555556
B39: 9 | C39: 9 | D39: SS98AAIS | E39: =VLOOKUP(Table616[[#This Row],[Part '#]],Table1[[Part Number]:[Shelf]],4,FALSE) -> 7 | F39: =VLOOKUP(Table616[[#This Row],[Part '#]],Table1[[Part Number]:[Bay]],5,FALSE) -> E | G39: 4.1 | H39: =G39/1.1 -> 3.7272727 | I39: =Table616[[#This Row],[(Meters)]]/1.8 -> 2.2777778 | J39: 8 | K39: =H39+J39+K38 -> 109.36364 | L39: =I39+J39+L38 -> 94.833333
B40: 3 | C40: 10 | D40: SDMALBB3033G | E40: =VLOOKUP(Table616[[#This Row],[Part '#]],Table1[[Part Number]:[Shelf]],4,FALSE) -> 3 | F40: =VLOOKUP(Table616[[#This Row],[Part '#]],Table1[[Part Number]:[Bay]],5,FALSE) -> C | G40: 1.3 | H40: =G40/1.1 -> 1.1818182 | I40: =Table616[[#This Row],[(Meters)]]/1.8 -> 0.72222222 | J40: 8 | K40: =H40+J40+K39 -> 118.54545 | L40: =I40+J40+L39 -> 103.55556
B41: 1 | C41: 11 | D41: BLE112 | E41: =VLOOKUP(Table616[[#This Row],[Part '#]],Table1[[Part Number]:[Shelf]],4,FALSE) -> 1 | F41: =VLOOKUP(Table616[[#This Row],[Part '#]],Table1[[Part Number]:[Bay]],5,FALSE) -> A | G41: 5.9 | H41: =G41/1.1 -> 5.3636364 | I41: =Table616[[#This Row],[(Meters)]]/1.8 -> 3.2777778 | J41: 8 | K41: =H41+J41+K40 -> 131.90909 | L41: =I41+J41+L40 -> 114.83333
B42: 4 | C42: 12 | D42: LS1121 | E42: =VLOOKUP(Table616[[#This Row],[Part '#]],Table1[[Part Number]:[Shelf]],4,FALSE) -> 14 | F42: =VLOOKUP(Table616[[#This Row],[Part '#]],Table1[[Part Number]:[Bay]],5,FALSE) -> A | G42: 3 | H42: =G42/1.1 -> 2.7272727 | I42: =Table616[[#This Row],[(Meters)]]/1.8 -> 1.6666667 | J42: 8 | K42: =H42+J42+K41 -> 142.63636 | L42: =I42+J42+L41 -> 124.5
B43: 5 | C43: 13 | D43: KK433 | E43: =VLOOKUP(Table616[[#This Row],[Part '#]],Table1[[Part Number]:[Shelf]],4,FALSE) -> 14 | F43: =VLOOKUP(Table616[[#This Row],[Part '#]],Table1[[Part Number]:[Bay]],5,FALSE) -> B | G43: 3 | H43: =G43/1.1 -> 2.7272727 | I43: =Table616[[#This Row],[(Meters)]]/1.8 -> 1.6666667 | J43: 8 | K43: =H43+J43+K42 -> 153.36364 | L43: =I43+J43+L42 -> 134.16667
B51: Total Minimum Walking and Picking Time | E51: =MAX(L31:L43) -> 134.16667
B52: Total Maximum Walking and Picking Time | E52: =MAX(K31:K43) -> 153.36364

Sheet A Assembly
A2: Labour Costing
B3: Type | C3: Worker Type | D3: Cost Per Hour | E3: Per Second
B4: Min | C4: Team Member | D4: =VLOOKUP(C4,Employees!$B$21:$C$33,2,FALSE) -> 22 | E4: 0.0061
B5: Max | C5: Team Lead | D5: =VLOOKUP(C5,Employees!$B$21:$C$33,2,FALSE) -> 26 | E5: 0.0072
A7: Assumptions | C7: Issue | D7: Options # | E7: Description | H7: Chosen | I7: Notes and Sources of Knowledge
B8: 1 | C8: What is the Walking Speed for Assemblers? | H8: Average | J8: m/sec | K8: (This is used in the Responses to Failed tests)
D9: 1 | E9: Slow Walking Speed from Picking | H9: 1.18 | I9: Average of speeds from Picking Sheet | J9: m/sec
D10: 2 | E10: Fast Walking Speed from Picking | H10: 1.75 | I10: Average of speeds from Picking Sheet | J10: m/sec
D11: 3 | E11: Average of the Fast and Slow | H11: 1.47 | J11: m/sec
B13: 2 | C13: Who does the final shipping of the packaged TrackR's? | H13: =E14 -> Maintenance Workers
D14: 1 | E14: Maintenance Workers
D15: 2 | E15: Assembly Workers
D16: 3 | E16: Someone else?
B18: 3 | C18: Who keeps the replacement parts shelf stocked? | H18: =E19 -> Maintenance Workers
D19: 1 | E19: Maintenance Workers
D20: 2 | E20: Assembly Workers
D21: 3 | E21: Someone else?
B23: 4
A27: Additional Process Knowledge
C28: Tug Test Process | D28: The assembly worker grasps the recently soldered part with a special pair of forceps, and pulls with the required amount of force, and no more.
D29: Newly trained assembly workers tend to fail more tug tests, because they pull with too much force. - Comment from Production Lead Hand - May 17th
A31: Common Calculation Factors
B32: 1 | C32: Time to record a failed test for QC | E32: sec | F32: (This is done into either a log book or a computer screen on the Return Goods Shelf)
B33: 2 | C33: Distance from Assembly Table to Return Goods Shelf | H33: meters
B34: 3 | C34: Distance from Return Goods to Replacement Parts | H34: meters
B35: 4 | C35: Distance from Return Goods Shelf to Assembly Table | H35: meters
A37: Assembly Steps - Master List | D37: Picking is not included in this list, and does not need to be included in this list.
B38: Step # | C38: Task | D38: Column1 | E38: Duration(sec) | F38: Total Time | G38: Labour Task Cost (min) | H38: Labour Task Cost (Max) | I38: Labour Cost Total to Task(min) | J38: Labour Cost Total to Task (Max) | K38: Componenent ID# | L38: Component Cost (Min) | M38: Component Cost (Max) | N38: All Total Cost to Task(Min) | O38: All Total Cost to Task (Max) | P38: Failure % | Q38: Action if Test Failed | R38: Additional Time (sec) | S38: More Labour Cost (Min) | T38: More Labour Cost (Max) | U38: Extra Component Cost (Min) | V38: Extra Component Cost (Max) | W38: Total Time to Task with 1 fail and Good Repeat | X38: All Total Cost to Task (Min) | Y38: All Total Cost to Task (max)2 | Z38: Reliability | AA38: Reliability to Task
B39: 1 | C39: Unbox MPC432119-2 | E39: 14 | F39: 14 | G39: =E39*$E$4 -> 0.0854 | H39: =E39*$E$5 -> 0.1008 | I39: =G39 -> 0.0854 | J39: =H39 -> 0.1008 | K39: 1 | L39: =VLOOKUP($K39,Components!$A$3:$I$23,8,FALSE) -> 6.606 | M39: =VLOOKUP($K39,Components!$A$3:$I$23,9,FALSE) -> 6.9363 | N39: =L39+G39 -> 6.6914 | O39: =M39+H39 -> 7.0371 | W39: =F39 -> 14 | X39: =SUM(G39,L39,S39,U39) -> 6.6914 | Y39: =SUM(H39,M39,T39,V39) -> 7.0371 | Z39: 1 | AA39: =Z39 -> 1
B40: 2 | C40: Inspect MPC432119-2 Test A | E40: 5 | F40: =F39+E40 -> 19 | G40: =E40*$E$4 -> 0.0305 | H40: =E40*$E$5 -> 0.036 | I40: =I39+G40 -> 0.1159 | J40: =J39+H40 -> 0.1368 | N40: =N39+L40+G40 -> 6.7219 | O40: =O39+M40+H40 -> 7.0731 | P40: 2 | Q40: Redo Test A | R40: =F83 -> 45.673469 | S40: =$R40*$E$4 -> 0.27860816 | T40: =$R40*$E$5 -> 0.32884898 | U40: =L77 -> 6.606 | V40: =M77 -> 6.9363 | W40: =W39+E40+R40 -> 64.673469 | X40: =SUM(X39,G40,L40,S40,U40) -> 13.606508 | Y40: =SUM(Y39,H40,M40,T40,V40) -> 14.338249 | Z40: =1-P40/100 -> 0.98 | AA40: =Z40*AA39 -> 0.98
B41: 3 | C41: MPC44422 is slid into LS1121 | E41: 3 | F41: =F40+E41 -> 22 | G41: =E41*$E$4 -> 0.0183 | H41: =E41*$E$5 -> 0.0216 | I41: =I40+G41 -> 0.1342 | J41: =J40+H41 -> 0.1584 | K41: 2 | L41: =VLOOKUP($K41,Components!$A$3:$I$23,8,FALSE) -> 0.081 | M41: =VLOOKUP($K41,Components!$A$3:$I$23,9,FALSE) -> 0.08505 | N41: =N40+L41+G41 -> 6.8212 | O41: =O40+M41+H41 -> 7.17975 | W41: =W40+E41+R41 -> 67.673469 | X41: =SUM(X40,G41,L41,S41,U41) -> 13.705808 | Y41: =SUM(Y40,H41,M41,T41,V41) -> 14.444899 | Z41: =1-P41/100 -> 1 | AA41: =Z41*AA40 -> 0.98
B42: 4 | C42: Connect LS112 to MPC432119-2 | E42: 7 | F42: =F41+E42 -> 29 | G42: =E42*$E$4 -> 0.0427 | H42: =E42*$E$5 -> 0.0504 | I42: =I41+G42 -> 0.1769 | J42: =J41+H42 -> 0.2088 | K42: 12 | L42: =VLOOKUP($K42,Components!$A$3:$I$23,8,FALSE) -> 3 | M42: =VLOOKUP($K42,Components!$A$3:$I$23,9,FALSE) -> 3.15 | N42: =N41+L42+G42 -> 9.8639 | O42: =O41+M42+H42 -> 10.38015 | W42: =W41+E42+R42 -> 74.673469 | X42: =SUM(X41,G42,L42,S42,U42) -> 16.748508 | Y42: =SUM(Y41,H42,M42,T42,V42) -> 17.645299 | Z42: =1-P42/100 -> 1 | AA42: =Z42*AA41 -> 0.98
B43: 5 | C43: Tug Test B | E43: 2 | F43: =F42+E43 -> 31 | G43: =E43*$E$4 -> 0.0122 | H43: =E43*$E$5 -> 0.0144 | I43: =I42+G43 -> 0.1891 | J43: =J42+H43 -> 0.2232 | N43: =N42+L43+G43 -> 9.8761 | O43: =O42+M43+H43 -> 10.39455 | P43: 5.2 | Q43: Redo Test B | R43: =F94 -> 36.673469 | S43: =$R43*$E$4 -> 0.22370816 | T43: =$R43*$E$5 -> 0.26404898 | U43: =SUM(L87:L94) -> 3.081 | V43: =SUM(M87:M94) -> 3.23505 | W43: =W42+E43+R43 -> 113.34694 | X43: =SUM(X42,G43,L43,S43,U43) -> 20.065416 | Y43: =SUM(Y42,H43,M43,T43,V43) -> 21.158798 | Z43: =1-P43/100 -> 0.948 | AA43: =Z43*AA42 -> 0.92904
B44: 6 | C44: Place SDMALBB3033G on FnOFI-GN1212 | E44: 6.6 | F44: =F43+E44 -> 37.6 | G44: =E44*$E$4 -> 0.04026 | H44: =E44*$E$5 -> 0.04752 | I44: =I43+G44 -> 0.22936 | J44: =J43+H44 -> 0.27072 | K44: 10 | L44: =VLOOKUP($K44,Components!$A$3:$I$23,8,FALSE) -> 4 | M44: =VLOOKUP($K44,Components!$A$3:$I$23,9,FALSE) -> 4.2 | N44: =N43+L44+G44 -> 13.91636 | O44: =O43+M44+H44 -> 14.64207 | W44: =W43+E44+R44 -> 119.94694 | X44: =SUM(X43,G44,L44,S44,U44) -> 24.105676 | Y44: =SUM(Y43,H44,M44,T44,V44) -> 25.406318 | Z44: =1-P44/100 -> 1 | AA44: =Z44*AA43 -> 0.92904
B45: 7 | C45: Solder FnOFI-GN1212 to SDMALBB3033G | E45: 20 | F45: =F44+E45 -> 57.6 | G45: =E45*$E$4 -> 0.122 | H45: =E45*$E$5 -> 0.144 | I45: =I44+G45 -> 0.35136 | J45: =J44+H45 -> 0.41472 | K45: 4 | L45: =VLOOKUP($K45,Components!$A$3:$I$23,8,FALSE) -> 14.99 | M45: =VLOOKUP($K45,Components!$A$3:$I$23,9,FALSE) -> 15.7395 | N45: =N44+L45+G45 -> 29.02836 | O45: =O44+M45+H45 -> 30.52557 | W45: =W44+E45+R45 -> 139.94694 | X45: =SUM(X44,G45,L45,S45,U45) -> 39.217676 | Y45: =SUM(Y44,H45,M45,T45,V45) -> 41.289818 | Z45: =1-P45/100 -> 1 | AA45: =Z45*AA44 -> 0.92904
B46: 8 | C46: Visual Examination Test C | E46: 30 | F46: =F45+E46 -> 87.6 | G46: =E46*$E$4 -> 0.183 | H46: =E46*$E$5 -> 0.216 | I46: =I45+G46 -> 0.53436 | J46: =J45+H46 -> 0.63072 | N46: =N45+L46+G46 -> 29.21136 | O46: =O45+M46+H46 -> 30.74157 | P46: 2 | Q46: Redo Test C | R46: =F102 -> 37.6 | S46: =$R46*$E$4 -> 0.22936 | T46: =$R46*$E$5 -> 0.27072 | U46: =SUM(L100:L102) -> 18.99 | V46: =SUM(M100:M102) -> 19.9395 | W46: =W45+E46+R46 -> 207.54694 | X46: =SUM(X45,G46,L46,S46,U46) -> 58.620036 | Y46: =SUM(Y45,H46,M46,T46,V46) -> 61.716038 | Z46: =1-P46/100 -> 0.98 | AA46: =Z46*AA45 -> 0.9104592
B47: 9 | C47: Clamp LS112 | E47: 24 | F47: =F46+E47 -> 111.6 | G47: =E47*$E$4 -> 0.1464 | H47: =E47*$E$5 -> 0.1728 | I47: =I46+G47 -> 0.68076 | J47: =J46+H47 -> 0.80352 | N47: =N46+L47+G47 -> 29.35776 | O47: =O46+M47+H47 -> 30.91437 | W47: =W46+E47+R47 -> 231.54694 | X47: =SUM(X46,G47,L47,S47,U47) -> 58.766436 | Y47: =SUM(Y46,H47,M47,T47,V47) -> 61.888838 | Z47: =1-P47/100 -> 1 | AA47: =Z47*AA46 -> 0.9104592
B48: 10 | C48: Solder HG213123-221 to BD2098733AAB | E48: 12 | F48: =F47+E48 -> 123.6 | G48: =E48*$E$4 -> 0.0732 | H48: =E48*$E$5 -> 0.0864 | I48: =I47+G48 -> 0.75396 | J48: =J47+H48 -> 0.88992 | K48: 7 | L48: =VLOOKUP($K48,Components!$A$3:$I$23,8,FALSE) -> 0.57 | M48: =VLOOKUP($K48,Components!$A$3:$I$23,9,FALSE) -> 0.5985 | N48: =N47+L48+G48 -> 30.00096 | O48: =O47+M48+H48 -> 31.59927 | W48: =W47+E48+R48 -> 243.54694 | X48: =SUM(X47,G48,L48,S48,U48) -> 59.409636 | Y48: =SUM(Y47,H48,M48,T48,V48) -> 62.573738 | Z48: =1-P48/100 -> 1 | AA48: =Z48*AA47 -> 0.9104592
B49: 11 | C49: Wait to Ensure bond | E49: 6 | F49: =F48+E49 -> 129.6 | G49: =E49*$E$4 -> 0.0366 | H49: =E49*$E$5 -> 0.0432 | I49: =I48+G49 -> 0.79056 | J49: =J48+H49 -> 0.93312 | N49: =N48+L49+G49 -> 30.03756 | O49: =O48+M49+H49 -> 31.64247 | W49: =W48+E49+R49 -> 249.54694 | X49: =SUM(X48,G49,L49,S49,U49) -> 59.446236 | Y49: =SUM(Y48,H49,M49,T49,V49) -> 62.616938 | Z49: =1-P49/100 -> 1 | AA49: =Z49*AA48 -> 0.9104592
B50: 12 | C50: Tug Test D | E50: 2 | F50: =F49+E50 -> 131.6 | G50: =E50*$E$4 -> 0.0122 | H50: =E50*$E$5 -> 0.0144 | I50: =I49+G50 -> 0.80276 | J50: =J49+H50 -> 0.94752 | N50: =N49+L50+G50 -> 30.04976 | O50: =O49+M50+H50 -> 31.65687 | P50: 7.5 | Q50: Redo Test D | R50: =F115 -> 58.673469 | S50: =$R50*$E$4 -> 0.35790816 | T50: =$R50*$E$5 -> 0.42244898 | U50: =SUM(L107:L115) -> 0.57 | V50: =SUM(M107:M115) -> 0.5985 | W50: =W49+E50+R50 -> 310.22041 | X50: =SUM(X49,G50,L50,S50,U50) -> 60.386344 | Y50: =SUM(Y49,H50,M50,T50,V50) -> 63.652287 | Z50: =1-P50/100 -> 0.925 | AA50: =Z50*AA49 -> 0.84217476
B51: 13 | C51: Solder BD2098733AAB on FnOFI-GN1212 | E51: 4.4 | F51: =F50+E51 -> 136 | G51: =E51*$E$4 -> 0.02684 | H51: =E51*$E$5 -> 0.03168 | I51: =I50+G51 -> 0.8296 | J51: =J50+H51 -> 0.9792 | K51: 5 | L51: =VLOOKUP($K51,Components!$A$3:$I$23,8,FALSE) -> 4.15 | M51: =VLOOKUP($K51,Components!$A$3:$I$23,9,FALSE) -> 4.3575 | N51: =N50+L51+G51 -> 34.2266 | O51: =O50+M51+H51 -> 36.04605 | W51: =W50+E51+R51 -> 314.62041 | X51: =SUM(X50,G51,L51,S51,U51) -> 64.563184 | Y51: =SUM(Y50,H51,M51,T51,V51) -> 68.041467 | Z51: =1-P51/100 -> 1 | AA51: =Z51*AA50 -> 0.84217476
B52: 14 | C52: Wait to Ensure bond | E52: 6 | F52: =F51+E52 -> 142 | G52: =E52*$E$4 -> 0.0366 | H52: =E52*$E$5 -> 0.0432 | I52: =I51+G52 -> 0.8662 | J52: =J51+H52 -> 1.0224 | N52: =N51+L52+G52 -> 34.2632 | O52: =O51+M52+H52 -> 36.08925 | W52: =W51+E52+R52 -> 320.62041 | X52: =SUM(X51,G52,L52,S52,U52) -> 64.599784 | Y52: =SUM(Y51,H52,M52,T52,V52) -> 68.084667 | Z52: =1-P52/100 -> 1 | AA52: =Z52*AA51 -> 0.84217476
B53: 15 | C53: Tug Test E | E53: 2 | F53: =F52+E53 -> 144 | G53: =E53*$E$4 -> 0.0122 | H53: =E53*$E$5 -> 0.0144 | I53: =I52+G53 -> 0.8784 | J53: =J52+H53 -> 1.0368 | N53: =N52+L53+G53 -> 34.2754 | O53: =O52+M53+H53 -> 36.10365 | P53: 0 | Q53: Redo Test E | R53: =F128 -> 51.073469 | S53: =$R53*$E$4 -> 0.31154816 | T53: =$R53*$E$5 -> 0.36772898 | U53: =SUM(L120:L128) -> 4.15 | V53: 4.15 | W53: =W52+E53+R53 -> 373.69388 | X53: =SUM(X52,G53,L53,S53,U53) -> 69.073533 | Y53: =SUM(Y52,H53,M53,T53,V53) -> 72.616796 | Z53: =1-P53/100 -> 1 | AA53: =Z53*AA52 -> 0.84217476
B54: 16 | C54: Solder STMA11233 to HG213123-221 | E54: 8.8 | F54: =F53+E54 -> 152.8 | G54: =E54*$E$4 -> 0.05368 | H54: =E54*$E$5 -> 0.06336 | I54: =I53+G54 -> 0.93208 | J54: =J53+H54 -> 1.10016 | K54: 8 | L54: =VLOOKUP($K54,Components!$A$3:$I$23,8,FALSE) -> 0.31 | M54: =VLOOKUP($K54,Components!$A$3:$I$23,9,FALSE) -> 0.3255 | N54: =N53+L54+G54 -> 34.63908 | O54: =O53+M54+H54 -> 36.49251 | W54: =W53+E54+R54 -> 382.49388 | X54: =SUM(X53,G54,L54,S54,U54) -> 69.437213 | Y54: =SUM(Y53,H54,M54,T54,V54) -> 73.005656 | Z54: =1-P54/100 -> 1 | AA54: =Z54*AA53 -> 0.84217476
B55: 17 | C55: Wait to Ensure bond | E55: 6 | F55: =F54+E55 -> 158.8 | G55: =E55*$E$4 -> 0.0366 | H55: =E55*$E$5 -> 0.0432 | I55: =I54+G55 -> 0.96868 | J55: =J54+H55 -> 1.14336 | N55: =N54+L55+G55 -> 34.67568 | O55: =O54+M55+H55 -> 36.53571 | W55: =W54+E55+R55 -> 388.49388 | X55: =SUM(X54,G55,L55,S55,U55) -> 69.473813 | Y55: =SUM(Y54,H55,M55,T55,V55) -> 73.048856 | Z55: =1-P55/100 -> 1 | AA55: =Z55*AA54 -> 0.84217476
B56: 18 | C56: Tug Test F | E56: 2 | F56: =F55+E56 -> 160.8 | G56: =E56*$E$4 -> 0.0122 | H56: =E56*$E$5 -> 0.0144 | I56: =I55+G56 -> 0.98088 | J56: =J55+H56 -> 1.15776 | N56: =N55+L56+G56 -> 34.68788 | O56: =O55+M56+H56 -> 36.55011 | W56: =W55+E56+R56 -> 390.49388 | X56: =SUM(X55,G56,L56,S56,U56) -> 69.486013 | Y56: =SUM(Y55,H56,M56,T56,V56) -> 73.063256 | Z56: =1-P56/100 -> 1 | AA56: =Z56*AA55 -> 0.84217476
B57: 19 | C57: Slide BLE112 on FnOFI-GN1212 | E57: 1.2 | F57: =F56+E57 -> 162 | G57: =E57*$E$4 -> 0.00732 | H57: =E57*$E$5 -> 0.00864 | I57: =I56+G57 -> 0.9882 | J57: =J56+H57 -> 1.1664 | K57: 11 | L57: =VLOOKUP($K57,Components!$A$3:$I$23,8,FALSE) -> 2 | M57: =VLOOKUP($K57,Components!$A$3:$I$23,9,FALSE) -> 2.1 | N57: =N56+L57+G57 -> 36.6952 | O57: =O56+M57+H57 -> 38.65875 | P57: 0 | Q57: Redo Test F | R57: =F141 -> 55.473469 | S57: =$R57*$E$4 -> 0.33838816 | T57: =$R57*$E$5 -> 0.39940898 | U57: =SUM(L133:L141) -> 0.31 | V57: =SUM(M133:M141) -> 0.3255 | W57: =W56+E57+R57 -> 447.16735 | X57: =SUM(X56,G57,L57,S57,U57) -> 72.141721 | Y57: =SUM(Y56,H57,M57,T57,V57) -> 75.896805 | Z57: =1-P57/100 -> 1 | AA57: =Z57*AA56 -> 0.84217476
B58: 20 | C58: Slide BD20911131BB on FnOFI-GN1212 | E58: 1.2 | F58: =F57+E58 -> 163.2 | G58: =E58*$E$4 -> 0.00732 | H58: =E58*$E$5 -> 0.00864 | I58: =I57+G58 -> 0.99552 | J58: =J57+H58 -> 1.17504 | K58: 6 | L58: =VLOOKUP($K58,Components!$A$3:$I$23,8,FALSE) -> 1.88 | M58: =VLOOKUP($K58,Components!$A$3:$I$23,9,FALSE) -> 1.974 | N58: =N57+L58+G58 -> 38.58252 | O58: =O57+M58+H58 -> 40.64139 | W58: =W57+E58+R58 -> 448.36735 | X58: =SUM(X57,G58,L58,S58,U58) -> 74.029041 | Y58: =SUM(Y57,H58,M58,T58,V58) -> 77.879445 | Z58: =1-P58/100 -> 1 | AA58: =Z58*AA57 -> 0.84217476
B59: 21 | C59: Place SFLV25 | E59: 12 | F59: =F58+E59 -> 175.2 | G59: =E59*$E$4 -> 0.0732 | H59: =E59*$E$5 -> 0.0864 | I59: =I58+G59 -> 1.06872 | J59: =J58+H59 -> 1.26144 | K59: 3 | L59: =VLOOKUP($K59,Components!$A$3:$I$23,8,FALSE) -> 17.42 | M59: =VLOOKUP($K59,Components!$A$3:$I$23,9,FALSE) -> 18.291 | N59: =N58+L59+G59 -> 56.07572 | O59: =O58+M59+H59 -> 59.01879 | W59: =W58+E59+R59 -> 460.36735 | X59: =SUM(X58,G59,L59,S59,U59) -> 91.522241 | Y59: =SUM(Y58,H59,M59,T59,V59) -> 96.256845 | Z59: =1-P59/100 -> 1 | AA59: =Z59*AA58 -> 0.84217476
B60: 22 | C60: SFLV25 is OK - Test G | E60: 5 | F60: =F59+E60 -> 180.2 | G60: =E60*$E$4 -> 0.0305 | H60: =E60*$E$5 -> 0.036 | I60: =I59+G60 -> 1.09922 | J60: =J59+H60 -> 1.29744 | N60: =N59+L60+G60 -> 56.10622 | O60: =O59+M60+H60 -> 59.05479 | W60: =W59+E60+R60 -> 465.36735 | X60: =SUM(X59,G60,L60,S60,U60) -> 91.552741 | Y60: =SUM(Y59,H60,M60,T60,V60) -> 96.292845 | Z60: =1-P60/100 -> 1 | AA60: =Z60*AA59 -> 0.84217476
B61: 23 | C61: Slid SS98AAIS into MPC432119-2 | E61: 8 | F61: =F60+E61 -> 188.2 | G61: =E61*$E$4 -> 0.0488 | H61: =E61*$E$5 -> 0.0576 | I61: =I60+G61 -> 1.14802 | J61: =J60+H61 -> 1.35504 | K61: 9 | L61: =VLOOKUP($K61,Components!$A$3:$I$23,8,FALSE) -> 38.15 | M61: =VLOOKUP($K61,Components!$A$3:$I$23,9,FALSE) -> 40.0575 | N61: =N60+L61+G61 -> 94.30502 | O61: =O60+M61+H61 -> 99.16989 | P61: 3 | Q61: Redo Test G | R61: 0 | S61: 0 | T61: 0 | U61: 0 | V61: 0 | W61: =W60+E61+R61 -> 473.36735 | X61: =SUM(X60,G61,L61,S61,U61) -> 129.75154 | Y61: =SUM(Y60,H61,M61,T61,V61) -> 136.40794 | Z61: =1-P61/100 -> 0.97 | AA61: =Z61*AA60 -> 0.81690952
B62: 24 | C62: Remove TrackR from Clamp | E62: 13.3 | F62: =F61+E62 -> 201.5 | G62: =E62*$E$4 -> 0.08113 | H62: =E62*$E$5 -> 0.09576 | I62: =I61+G62 -> 1.22915 | J62: =J61+H62 -> 1.4508 | N62: =N61+L62+G62 -> 94.38615 | O62: =O61+M62+H62 -> 99.26565 | W62: =W61+E62+R62 -> 486.66735 | X62: =SUM(X61,G62,L62,S62,U62) -> 129.83267 | Y62: =SUM(Y61,H62,M62,T62,V62) -> 136.5037 | Z62: =1-P62/100 -> 1 | AA62: =Z62*AA61 -> 0.81690952
B63: 24 | C63: Chemical Weld Assmbly | E63: 5 | F63: =F62+E63 -> 206.5 | G63: =E63*$E$4 -> 0.0305 | H63: =E63*$E$5 -> 0.036 | I63: =I62+G63 -> 1.25965 | J63: =J62+H63 -> 1.4868 | N63: =N62+L63+G63 -> 94.41665 | O63: =O62+M63+H63 -> 99.30165 | W63: =W62+E63+R63 -> 491.66735 | X63: =SUM(X62,G63,L63,S63,U63) -> 129.86317 | Y63: =SUM(Y62,H63,M63,T63,V63) -> 136.5397 | Z63: =1-P63/100 -> 1 | AA63: =Z63*AA62 -> 0.81690952
B64: 25 | C64: Heat Test H | E64: 10 | F64: =F63+E64 -> 216.5 | G64: =E64*$E$4 -> 0.061 | H64: =E64*$E$5 -> 0.072 | I64: =I63+G64 -> 1.32065 | J64: =J63+H64 -> 1.5588 | N64: =N63+L64+G64 -> 94.47765 | O64: =O63+M64+H64 -> 99.37365 | P64: 9.5 | Q64: Redo Test H | R64: 0 | S64: 0 | T64: 0 | U64: 0 | V64: 0 | W64: =W63+E64+R64 -> 501.66735 | X64: =SUM(X63,G64,L64,S64,U64) -> 129.92417 | Y64: =SUM(Y63,H64,M64,T64,V64) -> 136.6117 | Z64: =1-P64/100 -> 0.905 | AA64: =Z64*AA63 -> 0.73930311
B65: 25 | C65: Move to Testing PC | E65: 15 | F65: =F64+E65 -> 231.5 | G65: =E65*$E$4 -> 0.0915 | H65: =E65*$E$5 -> 0.108 | I65: =I64+G65 -> 1.41215 | J65: =J64+H65 -> 1.6668 | N65: =N64+L65+G65 -> 94.56915 | O65: =O64+M65+H65 -> 99.48165 | W65: =W64+E65+R65 -> 516.66735 | X65: =SUM(X64,G65,L65,S65,U65) -> 130.01567 | Y65: =SUM(Y64,H65,M65,T65,V65) -> 136.7197 | Z65: =1-P65/100 -> 1 | AA65: =Z65*AA64 -> 0.73930311
B66: 26 | C66: Turn on TrackR | E66: 3 | F66: =F65+E66 -> 234.5 | G66: =E66*$E$4 -> 0.0183 | H66: =E66*$E$5 -> 0.0216 | I66: =I65+G66 -> 1.43045 | J66: =J65+H66 -> 1.6884 | N66: =N65+L66+G66 -> 94.58745 | O66: =O65+M66+H66 -> 99.50325 | W66: =W65+E66+R66 -> 519.66735 | X66: =SUM(X65,G66,L66,S66,U66) -> 130.03397 | Y66: =SUM(Y65,H66,M66,T66,V66) -> 136.7413 | Z66: =1-P66/100 -> 1 | AA66: =Z66*AA65 -> 0.73930311
B67: 27 | C67: Wait for Radio Connectivity/ Sync - Test J | E67: 40 | F67: =F66+E67 -> 274.5 | G67: =E67*$E$4 -> 0.244 | H67: =E67*$E$5 -> 0.288 | I67: =I66+G67 -> 1.67445 | J67: =J66+H67 -> 1.9764 | N67: =N66+L67+G67 -> 94.83145 | O67: =O66+M67+H67 -> 99.79125 | P67: 2 | Q67: Redo Test J | R67: 0 | S67: 0 | T67: 0 | U67: 0 | V67: 0 | W67: =W66+E67+R67 -> 559.66735 | X67: =SUM(X66,G67,L67,S67,U67) -> 130.27797 | Y67: =SUM(Y66,H67,M67,T67,V67) -> 137.0293 | Z67: =1-P67/100 -> 0.98 | AA67: =Z67*AA66 -> 0.72451705
B68: 28 | C68: Put TrackR into Version Packaging | E68: 19 | F68: =F67+E68 -> 293.5 | G68: =E68*$E$4 -> 0.1159 | H68: =E68*$E$5 -> 0.1368 | I68: =I67+G68 -> 1.79035 | J68: =J67+H68 -> 2.1132 | N68: =N67+L68+G68 -> 94.94735 | O68: =O67+M68+H68 -> 99.92805 | W68: =W67+E68+R68 -> 578.66735 | X68: =SUM(X67,G68,L68,S68,U68) -> 130.39387 | Y68: =SUM(Y67,H68,M68,T68,V68) -> 137.1661 | Z68: =1-P68/100 -> 1 | AA68: =Z68*AA67 -> 0.72451705
B69: 29 | C69: Place Packed TrackR on Conveyor | E69: 2 | F69: =F68+E69 -> 295.5 | G69: =E69*$E$4 -> 0.0122 | H69: =E69*$E$5 -> 0.0144 | I69: =I68+G69 -> 1.80255 | J69: =J68+H69 -> 2.1276 | N69: =N68+L69+G69 -> 94.95955 | O69: =O68+M69+H69 -> 99.94245 | W69: =W68+E69+R69 -> 580.66735 | X69: =SUM(X68,G69,L69,S69,U69) -> 130.40607 | Y69: =SUM(Y68,H69,M69,T69,V69) -> 137.1805 | Z69: =1-P69/100 -> 1 | AA69: =Z69*AA68 -> 0.72451705
A71: Responses to Failed Tests
B73: Response A
B74: ReDo A | C74: If Test A Fails - Get another MPC4321119-2 from the shelf, and inspect it. Assume that the replacement part is OK.
B75: Step # | C75: Task | D75: Distance (m) | E75: Duration(sec) | F75: Total Time | G75: Labour Task Cost (min) | H75: Labour Task Cost (Max) | I75: Labour Cost Total to Task(min) | J75: Labour Cost Total to Task (Max) | K75: Componenent ID# | L75: Component Cost (Min) | M75: Component Cost (Max) | N75: All Total Cost to Task(Min) | O75: All Total Cost to Task (Max)
B76: 1 | C76: Walk to Return Goods Shelf | D76: 5.37 | E76: =D76/$H$11 -> 3.6530612 | F76: =E76 -> 3.6530612 | G76: =E76*$E$4 -> 0.022283673 | H76: =E76*$E$5 -> 0.026302041 | I76: =G76 -> 0.022283673 | J76: =H76 -> 0.026302041 | N76: =L76+G76 -> 0.022283673 | O76: =M76+H76 -> 0.026302041
B77: 2 | C77: Put down the Failed Part | E77: 2 | F77: =F76+E77 -> 5.6530612 | G77: =E77*$E$4 -> 0.0122 | H77: =E77*$E$5 -> 0.0144 | I77: =I76+G77 -> 0.034483673 | J77: =J76+H77 -> 0.040702041 | K77: 1 | L77: =VLOOKUP($K77,Components!$A$3:$I$23,8,FALSE) -> 6.606 | M77: =VLOOKUP($K77,Components!$A$3:$I$23,9,FALSE) -> 6.9363 | N77: =N76+L77+G77 -> 6.6404837 | O77: =O76+M77+H77 -> 6.977002
B78: 3 | C78: Record the failure | E78: 8 | F78: =F77+E78 -> 13.653061 | G78: =E78*$E$4 -> 0.0488 | H78: =E78*$E$5 -> 0.0576 | I78: =I77+G78 -> 0.083283673 | J78: =J77+H78 -> 0.098302041 | N78: =N77+L78+G78 -> 6.6892837 | O78: =O77+M78+H78 -> 7.034602
B79: 4 | C79: Walk to the Replacement Parts Shelf | D79: 8.06 | E79: =D79/$H$11 -> 5.4829932 | F79: =F78+E79 -> 19.136054 | G79: =E79*$E$4 -> 0.033446259 | H79: =E79*$E$5 -> 0.039477551 | I79: =I78+G79 -> 0.11672993 | J79: =J78+H79 -> 0.13777959 | N79: =N78+L79+G79 -> 6.7227299 | O79: =O78+M79+H79 -> 7.0740796
B80: 5 | C80: Pick Up the Replacement Part | E80: 3 | F80: =F79+E80 -> 22.136054 | G80: =E80*$E$4 -> 0.0183 | H80: =E80*$E$5 -> 0.0216 | I80: =I79+G80 -> 0.13502993 | J80: =J79+H80 -> 0.15937959 | N80: =N79+L80+G80 -> 6.7410299 | O80: =O79+M80+H80 -> 7.0956796
B81: 6 | C81: Walk back to the Assembly Table | D81: 6.67 | E81: =D81/$H$11 -> 4.537415 | F81: =F80+E81 -> 26.673469 | G81: =E81*$E$4 -> 0.027678231 | H81: =E81*$E$5 -> 0.032669388 | I81: =I80+G81 -> 0.16270816 | J81: =J80+H81 -> 0.19204898 | N81: =N80+L81+G81 -> 6.7687082 | O81: =O80+M81+H81 -> 7.128349
B82: 2 | C82: Unbox MPC432119-2 | E82: 14 | F82: =F81+E82 -> 40.673469 | G82: =E82*$E$4 -> 0.0854 | H82: =E82*$E$5 -> 0.1008 | I82: =I81+G82 -> 0.24810816 | J82: =J81+H82 -> 0.29284898 | N82: =N81+L82+G82 -> 6.8541082 | O82: =O81+M82+H82 -> 7.229149
B83: 3 | C83: Inspect MPC432119-2 | E83: 5 | F83: =F82+E83 -> 45.673469 | G83: =E83*$E$4 -> 0.0305 | H83: =E83*$E$5 -> 0.036 | I83: =I82+G83 -> 0.27860816 | J83: =J82+H83 -> 0.32884898 | N83: =N82+L83+G83 -> 6.8846082 | O83: =O82+M83+H83 -> 7.265149
B85: ReDo B | C85: If Test B Fails - Detach MPC44422, get another LS112 from the shelf, and repeat the assembly steps
B86: Step # | C86: Task | D86: Distance (m) | E86: Duration(sec) | F86: Total Time | G86: Labour Task Cost (min) | H86: Labour Task Cost (Max) | I86: Labour Cost Total to Task(min) | J86: Labour Cost Total to Task (Max) | K86: Componenent ID# | L86: Component Cost (Min) | M86: Component Cost (Max) | N86: All Total Cost to Task(Min) | O86: All Total Cost to Task (Max)
B87: 1 | C87: Walk to Return Goods Shelf | D87: 5.37 | E87: =D87/$H$11 -> 3.6530612 | F87: =E87 -> 3.6530612 | G87: =E87*$E$4 -> 0.022283673 | H87: =E87*$E$5 -> 0.026302041 | I87: =G87 -> 0.022283673 | J87: =H87 -> 0.026302041 | N87: =L87+G87 -> 0.022283673 | O87: =M87+H87 -> 0.026302041
B88: 2 | C88: Put down the Failed Part | E88: 2 | F88: =F87+E88 -> 5.6530612 | G88: =E88*$E$4 -> 0.0122 | H88: =E88*$E$5 -> 0.0144 | I88: =I87+G88 -> 0.034483673 | J88: =J87+H88 -> 0.040702041 | N88: =N87+L88+G88 -> 0.034483673 | O88: =O87+M88+H88 -> 0.040702041
B89: 3 | C89: Record the failure | E89: 8 | F89: =F88+E89 -> 13.653061 | G89: =E89*$E$4 -> 0.0488 | H89: =E89*$E$5 -> 0.0576 | I89: =I88+G89 -> 0.083283673 | J89: =J88+H89 -> 0.098302041 | K89: 2 | L89: =VLOOKUP($K89,Components!$A$3:$I$23,8,FALSE) -> 0.081 | M89: =VLOOKUP($K89,Components!$A$3:$I$23,9,FALSE) -> 0.08505 | N89: =N88+L89+G89 -> 0.16428367 | O89: =O88+M89+H89 -> 0.18335204
B90: 4 | C90: Walk to the Replacement Parts Shelf | D90: 8.06 | E90: =D90/$H$11 -> 5.4829932 | F90: =F89+E90 -> 19.136054 | G90: =E90*$E$4 -> 0.033446259 | H90: =E90*$E$5 -> 0.039477551 | I90: =I89+G90 -> 0.11672993 | J90: =J89+H90 -> 0.13777959 | N90: =N89+L90+G90 -> 0.19772993 | O90: =O89+M90+H90 -> 0.22282959
B91: 5 | C91: Pick Up the Replacement Part | E91: 3 | F91: =F90+E91 -> 22.136054 | G91: =E91*$E$4 -> 0.0183 | H91: =E91*$E$5 -> 0.0216 | I91: =I90+G91 -> 0.13502993 | J91: =J90+H91 -> 0.15937959 | K91: 12 | L91: =VLOOKUP($K91,Components!$A$3:$I$23,8,FALSE) -> 3 | M91: =VLOOKUP($K91,Components!$A$3:$I$23,9,FALSE) -> 3.15 | N91: =N90+L91+G91 -> 3.2160299 | O91: =O90+M91+H91 -> 3.3944296
B92: 6 | C92: Walk back to the Assembly Table | D92: 6.67 | E92: =D92/$H$11 -> 4.537415 | F92: =F91+E92 -> 26.673469 | G92: =E92*$E$4 -> 0.027678231 | H92: =E92*$E$5 -> 0.032669388 | I92: =I91+G92 -> 0.16270816 | J92: =J91+H92 -> 0.19204898 | N92: =N91+L92+G92 -> 3.2437082 | O92: =O91+M92+H92 -> 3.427099
B93: 3 | C93: MPC44422 is slid into LS1121 | E93: 3 | F93: =F92+E93 -> 29.673469 | G93: =E93*$E$4 -> 0.0183 | H93: =E93*$E$5 -> 0.0216 | I93: =I92+G93 -> 0.18100816 | J93: =J92+H93 -> 0.21364898 | N93: =N92+L93+G93 -> 3.2620082 | O93: =O92+M93+H93 -> 3.448699
B94: 4 | C94: Connect LS1121 to MPC432119-2 | E94: 7 | F94: =F93+E94 -> 36.673469 | G94: =E94*$E$4 -> 0.0427 | H94: =E94*$E$5 -> 0.0504 | I94: =I93+G94 -> 0.22370816 | J94: =J93+H94 -> 0.26404898 | N94: =N93+L94+G94 -> 3.3047082 | O94: =O93+M94+H94 -> 3.499099
B97: ReDo C
B98: Response C | C98: If Test C Fails - Board must be cleaned of old solder and soldered again properly
B99: Step # | C99: Task | D99: Distance (m) | E99: Duration(sec) | F99: Total Time | G99: Labour Task Cost (min) | H99: Labour Task Cost (Max) | I99: Labour Cost Total to Task(min) | J99: Labour Cost Total to Task (Max) | K99: Componenent ID# | L99: Component Cost (Min) | M99: Component Cost (Max) | N99: All Total Cost to Task(Min) | O99: All Total Cost to Task (Max)
B100: 1 | C100: Clean old solder on board | E100: 11 | F100: =E100 -> 11 | G100: =E100*$E$4 -> 0.0671 | H100: =E100*$E$5 -> 0.0792 | I100: =G100 -> 0.0671 | J100: =H100 -> 0.0792 | N100: =L100+G100 -> 0.0671 | O100: =M100+H100 -> 0.0792
B101: 6 | C101: Place SDMALBB3033G on FnOFI-GN1212 | E101: 6.6 | F101: =F100+E101 -> 17.6 | G101: =E101*$E$4 -> 0.04026 | H101: =E101*$E$5 -> 0.04752 | I101: =I100+G101 -> 0.10736 | J101: =J100+H101 -> 0.12672 | K101: 10 | L101: =VLOOKUP($K101,Components!$A$3:$I$23,8,FALSE) -> 4 | M101: =VLOOKUP($K101,Components!$A$3:$I$23,9,FALSE) -> 4.2 | N101: =N100+L101+G101 -> 4.10736 | O101: =O100+M101+H101 -> 4.32672
B102: 7 | C102: Solder FnOFI-GN1212 to SDMALBB3033G | E102: 20 | F102: =F101+E102 -> 37.6 | G102: =E102*$E$4 -> 0.122 | H102: =E102*$E$5 -> 0.144 | I102: =I101+G102 -> 0.22936 | J102: =J101+H102 -> 0.27072 | K102: 4 | L102: =VLOOKUP($K102,Components!$A$3:$I$23,8,FALSE) -> 14.99 | M102: =VLOOKUP($K102,Components!$A$3:$I$23,9,FALSE) -> 15.7395 | N102: =N101+L102+G102 -> 19.21936 | O102: =O101+M102+H102 -> 20.21022
B104: ReDo D
B105: Response D | C105: If Test D Fails - Dispose Component HG213123-221 and record as porduct waste
B106: Step # | C106: Task | D106: Distance (m) | E106: Duration(sec) | F106: Total Time | G106: Labour Task Cost (min) | H106: Labour Task Cost (Max) | I106: Labour Cost Total to Task(min) | J106: Labour Cost Total to Task (Max) | K106: Componenent ID# | L106: Component Cost (Min) | M106: Component Cost (Max) | N106: All Total Cost to Task(Min) | O106: All Total Cost to Task (Max)
B107: 1 | C107: Walk to Return Goods Shelf | D107: 5.37 | E107: =D107/$H$11 -> 3.6530612 | F107: =E107 -> 3.6530612 | G107: =E107*$E$4 -> 0.022283673 | H107: =E107*$E$5 -> 0.026302041 | I107: =G107 -> 0.022283673 | J107: =H107 -> 0.026302041 | N107: =L107+G107 -> 0.022283673 | O107: =M107+H107 -> 0.026302041
B108: 2 | C108: Put down the Failed Part | E108: 2 | F108: =F107+E108 -> 5.6530612 | G108: =E108*$E$4 -> 0.0122 | H108: =E108*$E$5 -> 0.0144 | I108: =I107+G108 -> 0.034483673 | J108: =J107+H108 -> 0.040702041 | N108: =N107+L108+G108 -> 0.034483673 | O108: =O107+M108+H108 -> 0.040702041
B109: 3 | C109: Record the failure | E109: 8 | F109: =F108+E109 -> 13.653061 | G109: =E109*$E$4 -> 0.0488 | H109: =E109*$E$5 -> 0.0576 | I109: =I108+G109 -> 0.083283673 | J109: =J108+H109 -> 0.098302041 | K109: 7 | L109: =VLOOKUP($K109,Components!$A$3:$I$23,8,FALSE) -> 0.57 | M109: =VLOOKUP($K109,Components!$A$3:$I$23,9,FALSE) -> 0.5985 | N109: =N108+L109+G109 -> 0.65328367 | O109: =O108+M109+H109 -> 0.69680204
B110: 4 | C110: Walk to the Replacement Parts Shelf | D110: 8.06 | E110: =D110/$H$11 -> 5.4829932 | F110: =F109+E110 -> 19.136054 | G110: =E110*$E$4 -> 0.033446259 | H110: =E110*$E$5 -> 0.039477551 | I110: =I109+G110 -> 0.11672993 | J110: =J109+H110 -> 0.13777959 | N110: =N109+L110+G110 -> 0.68672993 | O110: =O109+M110+H110 -> 0.73627959
B111: 5 | C111: Pick Up the Replacement Part | E111: 3 | F111: =F110+E111 -> 22.136054 | G111: =E111*$E$4 -> 0.0183 | H111: =E111*$E$5 -> 0.0216 | I111: =I110+G111 -> 0.13502993 | J111: =J110+H111 -> 0.15937959 | N111: =N110+L111+G111 -> 0.70502993 | O111: =O110+M111+H111 -> 0.75787959
B112: 6 | C112: Walk back to the Assembly Table | D112: 6.67 | E112: =D112/$H$11 -> 4.537415 | F112: =F111+E112 -> 26.673469 | G112: =E112*$E$4 -> 0.027678231 | H112: =E112*$E$5 -> 0.032669388 | I112: =I111+G112 -> 0.16270816 | J112: =J111+H112 -> 0.19204898 | N112: =N111+L112+G112 -> 0.73270816 | O112: =O111+M112+H112 -> 0.79054898
B113: 7 | C113: Clean-up | E113: 14 | F113: =F112+E113 -> 40.673469 | G113: =E113*$E$4 -> 0.0854 | H113: =E113*$E$5 -> 0.1008 | I113: =I112+G113 -> 0.24810816 | J113: =J112+H113 -> 0.29284898 | N113: =N112+L113+G113 -> 0.81810816 | O113: =O112+M113+H113 -> 0.89134898
B114: 10 | C114: Solder HG213123-221 to BD2098733AAB | E114: 12 | F114: =F113+E114 -> 52.673469 | G114: =E114*$E$4 -> 0.0732 | H114: =E114*$E$5 -> 0.0864 | I114: =I113+G114 -> 0.32130816 | J114: =J113+H114 -> 0.37924898 | N114: =N113+L114+G114 -> 0.89130816 | O114: =O113+M114+H114 -> 0.97774898
B115: 11 | C115: Wait to Ensure bond | E115: 6 | F115: =F114+E115 -> 58.673469 | G115: =E115*$E$4 -> 0.0366 | H115: =E115*$E$5 -> 0.0432 | I115: =I114+G115 -> 0.35790816 | J115: =J114+H115 -> 0.42244898 | N115: =N114+L115+G115 -> 0.92790816 | O115: =O114+M115+H115 -> 1.020949
B117: ReDO E
...

Sheet T Assembly
A2: Labour Costing
B3: Type | C3: Worker Type | D3: Cost Per Hour | E3: Per Second
B4: Min | C4: Team Member | D4: =VLOOKUP(C4,Employees!$B$21:$C$33,2,FALSE) -> 22 | E4: 0.0061
B5: Max | C5: Team Lead | D5: =VLOOKUP(C5,Employees!$B$21:$C$33,2,FALSE) -> 26 | E5: 0.0072
A7: Assumptions | C7: Issue | D7: Options # | E7: Description | H7: Chosen | I7: Notes and Sources of Knowledge
B8: 1 | C8: What is the Walking Speed for Assemblers? | H8: Average | J8: m/sec | K8: (This is used in the Responses to Failed tests)
D9: 1 | E9: Slow Walking Speed from Picking | H9: 1.1 | I9: Average of speeds from Picking Sheet | J9: m/sec
D10: 2 | E10: Fast Walking Speed from Picking | H10: 1.8 | I10: Average of speeds from Picking Sheet | J10: m/sec
D11: 3 | E11: Average of the Fast and Slow | H11: 2 | J11: m/sec
B13: 2 | C13: Who does the final shipping of the packaged TrackR's? | H13: =E14 -> Maintenance Workers
D14: 1 | E14: Maintenance Workers
D15: 2 | E15: Assembly Workers
D16: 3 | E16: Someone else?
B18: 3 | C18: Who keeps the replacement parts shelf stocked? | H18: =E19 -> Maintenance Workers
D19: 1 | E19: Maintenance Workers
D20: 2 | E20: Assembly Workers
D21: 3 | E21: Someone else?
B23: 4
A27: Additional Process Knowledge
C28: Tug Test Process | D28: The assembly worker grasps the recently soldered part with a special pair of forceps, and pulls with the required amount of force, and no more.
D29: Newly trained assembly workers tend to fail more tug tests, because they pull with too much force. - Comment from Production Lead Hand - May 17th
A31: Common Calculation Factors
B32: 1 | C32: Time to record a failed test for QC | E32: sec | F32: (This is done into either a log book or a computer screen on the Return Goods Shelf)
B33: 2 | C33: Distance from Assembly Table to Return Goods Shelf | G33: 7.9 | H33: meters
B34: 3 | C34: Distance from Return Goods to Replacement Parts | G34: 9.6 | H34: meters
B35: 4 | C35: Distance from Return Goods Shelf to Assembly Table | G35: 7.9 | H35: meters
A37: Assembly Steps - Master List | D37: Picking is not included in this list, and does not need to be included in this list.
B38: Step # | C38: Task | D38: Column1 | E38: Duration(sec) | F38: Total Time | G38: Labour Task Cost (min) | H38: Labour Task Cost (Max) | I38: Labour Cost Total to Task(min) | J38: Labour Cost Total to Task (Max) | K38: Componenent ID# | L38: Component Cost (Min) | M38: Component Cost (Max) | N38: All Total Cost to Task(Min) | O38: All Total Cost to Task (Max) | P38: Failure % | Q38: Action if Test Failed | R38: Additional Time (sec) | S38: More Labour Cost (Min) | T38: More Labour Cost (Max) | U38: Extra Component Cost (Min) | V38: Extra Component Cost (Max) | W38: Total Time to Task with 1 fail and Good Repeat | X38: All Total Cost to Task (Min) | Y38: All Total Cost to Task (max)2 | Z38: Reliability | AA38: Reliability to Task
B39: 1 | C39: Unbox MPC432119-2 | D39: 1 | E39: 14 | F39: 14 | G39: =E39*$E$4 -> 0.0854 | H39: =E39*$E$5 -> 0.1008 | I39: =G39 -> 0.0854 | J39: =H39 -> 0.1008 | K39: 1 | L39: =VLOOKUP($K39,Components!$A$3:$I$23,8,FALSE) -> 6.606 | M39: =VLOOKUP($K39,Components!$A$3:$I$23,9,FALSE) -> 6.9363 | N39: =L39+G39 -> 6.6914 | O39: =M39+H39 -> 7.0371 | W39: =F39 -> 14 | X39: =SUM(G39,L39,S39,U39) -> 6.6914 | Y39: =SUM(H39,M39,T39,V39) -> 7.0371 | Z39: 1 | AA39: =Z39 -> 1
B40: 2 | C40: Inspect MPC432119-2 Test A | D40: 1 | E40: 5 | F40: =F39+E40 -> 19 | G40: =E40*$E$4 -> 0.0305 | H40: =E40*$E$5 -> 0.036 | I40: =I39+G40 -> 0.1159 | J40: =J39+H40 -> 0.1368 | N40: =N39+L40+G40 -> 6.7219 | O40: =O39+M40+H40 -> 7.0731 | P40: 2 | Q40: Redo Test A | R40: =F83 -> 44.7 | S40: =$R40*$E$4 -> 0.27267 | T40: =$R40*$E$5 -> 0.32184 | U40: =L77 -> 6.606 | V40: =M77 -> 6.9363 | W40: =W39+E40+R40 -> 63.7 | X40: =SUM(X39,G40,L40,S40,U40) -> 13.60057 | Y40: =SUM(Y39,H40,M40,T40,V40) -> 14.33124 | Z40: =1-P40/100 -> 0.98 | AA40: =Z40*AA39 -> 0.98
B41: 3 | C41: MPC44422 is slid into LS1121 | D41: 2 | E41: 3 | F41: =F40+E41 -> 22 | G41: =E41*$E$4 -> 0.0183 | H41: =E41*$E$5 -> 0.0216 | I41: =I40+G41 -> 0.1342 | J41: =J40+H41 -> 0.1584 | K41: 2 | L41: =VLOOKUP($K41,Components!$A$3:$I$23,8,FALSE) -> 0.081 | M41: =VLOOKUP($K41,Components!$A$3:$I$23,9,FALSE) -> 0.08505 | N41: =N40+L41+G41 -> 6.8212 | O41: =O40+M41+H41 -> 7.17975 | W41: =W40+E41+R41 -> 66.7 | X41: =SUM(X40,G41,L41,S41,U41) -> 13.69987 | Y41: =SUM(Y40,H41,M41,T41,V41) -> 14.43789 | Z41: =1-P41/100 -> 1 | AA41: =Z41*AA40 -> 0.98
B42: 4 | C42: Connect LS112 to MPC432119-2 | D42: 2 | E42: 7 | F42: =F41+E42 -> 29 | G42: =E42*$E$4 -> 0.0427 | H42: =E42*$E$5 -> 0.0504 | I42: =I41+G42 -> 0.1769 | J42: =J41+H42 -> 0.2088 | K42: 12 | L42: =VLOOKUP($K42,Components!$A$3:$I$23,8,FALSE) -> 3 | M42: =VLOOKUP($K42,Components!$A$3:$I$23,9,FALSE) -> 3.15 | N42: =N41+L42+G42 -> 9.8639 | O42: =O41+M42+H42 -> 10.38015 | W42: =W41+E42+R42 -> 73.7 | X42: =SUM(X41,G42,L42,S42,U42) -> 16.74257 | Y42: =SUM(Y41,H42,M42,T42,V42) -> 17.63829 | Z42: =1-P42/100 -> 1 | AA42: =Z42*AA41 -> 0.98
B43: 5 | C43: Tug Test B | D43: 3 | E43: 2 | F43: =F42+E43 -> 31 | G43: =E43*$E$4 -> 0.0122 | H43: =E43*$E$5 -> 0.0144 | I43: =I42+G43 -> 0.1891 | J43: =J42+H43 -> 0.2232 | N43: =N42+L43+G43 -> 9.8761 | O43: =O42+M43+H43 -> 10.39455 | P43: 5.2 | Q43: Redo Test B | R43: =F94 -> 35.7 | S43: =$R43*$E$4 -> 0.21777 | T43: =$R43*$E$5 -> 0.25704 | U43: =SUM(L87:L94) -> 3.081 | V43: =SUM(M87:M94) -> 3.23505 | W43: =W42+E43+R43 -> 111.4 | X43: =SUM(X42,G43,L43,S43,U43) -> 20.05354 | Y43: =SUM(Y42,H43,M43,T43,V43) -> 21.14478 | Z43: =1-P43/100 -> 0.948 | AA43: =Z43*AA42 -> 0.92904
B44: 6 | C44: Place SDMALBB3033G on FnOFI-GN1212 | D44: 1 | E44: 6.6 | F44: =F43+E44 -> 37.6 | G44: =E44*$E$4 -> 0.04026 | H44: =E44*$E$5 -> 0.04752 | I44: =I43+G44 -> 0.22936 | J44: =J43+H44 -> 0.27072 | K44: 10 | L44: =VLOOKUP($K44,Components!$A$3:$I$23,8,FALSE) -> 4 | M44: =VLOOKUP($K44,Components!$A$3:$I$23,9,FALSE) -> 4.2 | N44: =N43+L44+G44 -> 13.91636 | O44: =O43+M44+H44 -> 14.64207 | W44: =W43+E44+R44 -> 118 | X44: =SUM(X43,G44,L44,S44,U44) -> 24.0938 | Y44: =SUM(Y43,H44,M44,T44,V44) -> 25.3923 | Z44: =1-P44/100 -> 1 | AA44: =Z44*AA43 -> 0.92904
B45: 7 | C45: Solder FnOFI-GN1212 to SDMALBB3033G | D45: 2 | E45: 20 | F45: =F44+E45 -> 57.6 | G45: =E45*$E$4 -> 0.122 | H45: =E45*$E$5 -> 0.144 | I45: =I44+G45 -> 0.35136 | J45: =J44+H45 -> 0.41472 | K45: 4 | L45: =VLOOKUP($K45,Components!$A$3:$I$23,8,FALSE) -> 14.99 | M45: =VLOOKUP($K45,Components!$A$3:$I$23,9,FALSE) -> 15.7395 | N45: =N44+L45+G45 -> 29.02836 | O45: =O44+M45+H45 -> 30.52557 | W45: =W44+E45+R45 -> 138 | X45: =SUM(X44,G45,L45,S45,U45) -> 39.2058 | Y45: =SUM(Y44,H45,M45,T45,V45) -> 41.2758 | Z45: =1-P45/100 -> 1 | AA45: =Z45*AA44 -> 0.92904
B46: 8 | C46: Visual Examination Test C | D46: 3 | E46: 30 | F46: =F45+E46 -> 87.6 | G46: =E46*$E$4 -> 0.183 | H46: =E46*$E$5 -> 0.216 | I46: =I45+G46 -> 0.53436 | J46: =J45+H46 -> 0.63072 | N46: =N45+L46+G46 -> 29.21136 | O46: =O45+M46+H46 -> 30.74157 | P46: 2 | Q46: Redo Test C | R46: =F102 -> 37.6 | S46: =$R46*$E$4 -> 0.22936 | T46: =$R46*$E$5 -> 0.27072 | U46: =SUM(L100:L102) -> 18.99 | V46: =SUM(M100:M102) -> 19.9395 | W46: =W45+E46+R46 -> 205.6 | X46: =SUM(X45,G46,L46,S46,U46) -> 58.60816 | Y46: =SUM(Y45,H46,M46,T46,V46) -> 61.70202 | Z46: =1-P46/100 -> 0.98 | AA46: =Z46*AA45 -> 0.9104592
B47: 9 | C47: Clamp LS112 | D47: 4 | E47: 24 | F47: =F46+E47 -> 111.6 | G47: =E47*$E$4 -> 0.1464 | H47: =E47*$E$5 -> 0.1728 | I47: =I46+G47 -> 0.68076 | J47: =J46+H47 -> 0.80352 | N47: =N46+L47+G47 -> 29.35776 | O47: =O46+M47+H47 -> 30.91437 | W47: =W46+E47+R47 -> 229.6 | X47: =SUM(X46,G47,L47,S47,U47) -> 58.75456 | Y47: =SUM(Y46,H47,M47,T47,V47) -> 61.87482 | Z47: =1-P47/100 -> 1 | AA47: =Z47*AA46 -> 0.9104592
B48: 10 | C48: Solder HG213123-221 to BD2098733AAB | D48: 4 | E48: 12 | F48: =F47+E48 -> 123.6 | G48: =E48*$E$4 -> 0.0732 | H48: =E48*$E$5 -> 0.0864 | I48: =I47+G48 -> 0.75396 | J48: =J47+H48 -> 0.88992 | K48: 7 | L48: =VLOOKUP($K48,Components!$A$3:$I$23,8,FALSE) -> 0.57 | M48: =VLOOKUP($K48,Components!$A$3:$I$23,9,FALSE) -> 0.5985 | N48: =N47+L48+G48 -> 30.00096 | O48: =O47+M48+H48 -> 31.59927 | W48: =W47+E48+R48 -> 241.6 | X48: =SUM(X47,G48,L48,S48,U48) -> 59.39776 | Y48: =SUM(Y47,H48,M48,T48,V48) -> 62.55972 | Z48: =1-P48/100 -> 1 | AA48: =Z48*AA47 -> 0.9104592
B49: 11 | C49: Wait to Ensure bond | D49: 4 | E49: 6 | F49: =F48+E49 -> 129.6 | G49: =E49*$E$4 -> 0.0366 | H49: =E49*$E$5 -> 0.0432 | I49: =I48+G49 -> 0.79056 | J49: =J48+H49 -> 0.93312 | N49: =N48+L49+G49 -> 30.03756 | O49: =O48+M49+H49 -> 31.64247 | W49: =W48+E49+R49 -> 247.6 | X49: =SUM(X48,G49,L49,S49,U49) -> 59.43436 | Y49: =SUM(Y48,H49,M49,T49,V49) -> 62.60292 | Z49: =1-P49/100 -> 1 | AA49: =Z49*AA48 -> 0.9104592
B50: 12 | C50: Tug Test D | D50: 3 | E50: 2 | F50: =F49+E50 -> 131.6 | G50: =E50*$E$4 -> 0.0122 | H50: =E50*$E$5 -> 0.0144 | I50: =I49+G50 -> 0.80276 | J50: =J49+H50 -> 0.94752 | N50: =N49+L50+G50 -> 30.04976 | O50: =O49+M50+H50 -> 31.65687 | P50: 7.5 | Q50: Redo Test D | R50: =F115 -> 57.7 | S50: =$R50*$E$4 -> 0.35197 | T50: =$R50*$E$5 -> 0.41544 | U50: =SUM(L107:L115) -> 0.57 | V50: =SUM(M107:M115) -> 0.5985 | W50: =W49+E50+R50 -> 307.3 | X50: =SUM(X49,G50,L50,S50,U50) -> 60.36853 | Y50: =SUM(Y49,H50,M50,T50,V50) -> 63.63126 | Z50: =1-P50/100 -> 0.925 | AA50: =Z50*AA49 -> 0.84217476
B51: 13 | C51: Solder BD2098733AAB on FnOFI-GN1212 | D51: 2 | E51: 0 | F51: =F50+E51 -> 131.6 | G51: =E51*$E$4 -> 0 | H51: =E51*$E$5 -> 0 | I51: =I50+G51 -> 0.80276 | J51: =J50+H51 -> 0.94752 | K51: 5 | L51: =VLOOKUP($K51,Components!$A$3:$I$23,8,FALSE) -> 4.15 | M51: =VLOOKUP($K51,Components!$A$3:$I$23,9,FALSE) -> 4.3575 | N51: =N50+L51+G51 -> 34.19976 | O51: =O50+M51+H51 -> 36.01437 | W51: =W50+E51+R51 -> 307.3 | X51: =SUM(X50,G51,L51,S51,U51) -> 64.51853 | Y51: =SUM(Y50,H51,M51,T51,V51) -> 67.98876 | Z51: =1-P51/100 -> 1 | AA51: =Z51*AA50 -> 0.84217476
B52: 14 | C52: Wait to Ensure bond | D52: 1 | E52: 0 | F52: =F51+E52 -> 131.6 | G52: =E52*$E$4 -> 0 | H52: =E52*$E$5 -> 0 | I52: =I51+G52 -> 0.80276 | J52: =J51+H52 -> 0.94752 | N52: =N51+L52+G52 -> 34.19976 | O52: =O51+M52+H52 -> 36.01437 | W52: =W51+E52+R52 -> 307.3 | X52: =SUM(X51,G52,L52,S52,U52) -> 64.51853 | Y52: =SUM(Y51,H52,M52,T52,V52) -> 67.98876 | Z52: =1-P52/100 -> 1 | AA52: =Z52*AA51 -> 0.84217476
B53: 15 | C53: Tug Test E | D53: 1.2 | E53: 0 | F53: =F52+E53 -> 131.6 | G53: =E53*$E$4 -> 0 | H53: =E53*$E$5 -> 0 | I53: =I52+G53 -> 0.80276 | J53: =J52+H53 -> 0.94752 | N53: =N52+L53+G53 -> 34.19976 | O53: =O52+M53+H53 -> 36.01437 | P53: 0 | Q53: Redo Test E | R53: =F128 -> 50.1 | S53: =$R53*$E$4 -> 0.30561 | T53: =$R53*$E$5 -> 0.36072 | U53: =SUM(L120:L128) -> 4.15 | V53: 4.15 | W53: =W52+E53+R53 -> 357.4 | X53: =SUM(X52,G53,L53,S53,U53) -> 68.97414 | Y53: =SUM(Y52,H53,M53,T53,V53) -> 72.49948 | Z53: =1-P53/100 -> 1 | AA53: =Z53*AA52 -> 0.84217476
B54: 16 | C54: Solder STMA11233 to HG213123-221 | D54: 2 | E54: 0 | F54: =F53+E54 -> 131.6 | G54: =E54*$E$4 -> 0 | H54: =E54*$E$5 -> 0 | I54: =I53+G54 -> 0.80276 | J54: =J53+H54 -> 0.94752 | K54: 8 | L54: =VLOOKUP($K54,Components!$A$3:$I$23,8,FALSE) -> 0.31 | M54: =VLOOKUP($K54,Components!$A$3:$I$23,9,FALSE) -> 0.3255 | N54: =N53+L54+G54 -> 34.50976 | O54: =O53+M54+H54 -> 36.33987 | W54: =W53+E54+R54 -> 357.4 | X54: =SUM(X53,G54,L54,S54,U54) -> 69.28414 | Y54: =SUM(Y53,H54,M54,T54,V54) -> 72.82498 | Z54: =1-P54/100 -> 1 | AA54: =Z54*AA53 -> 0.84217476
B55: 17 | C55: Wait to Ensure bond | D55: 2 | E55: 0 | F55: =F54+E55 -> 131.6 | G55: =E55*$E$4 -> 0 | H55: =E55*$E$5 -> 0 | I55: =I54+G55 -> 0.80276 | J55: =J54+H55 -> 0.94752 | N55: =N54+L55+G55 -> 34.50976 | O55: =O54+M55+H55 -> 36.33987 | W55: =W54+E55+R55 -> 357.4 | X55: =SUM(X54,G55,L55,S55,U55) -> 69.28414 | Y55: =SUM(Y54,H55,M55,T55,V55) -> 72.82498 | Z55: =1-P55/100 -> 1 | AA55: =Z55*AA54 -> 0.84217476
B56: 18 | C56: Tug Test F | D56: 0 | E56: 1.2 | F56: =F55+E56 -> 132.8 | G56: =E56*$E$4 -> 0.00732 | H56: =E56*$E$5 -> 0.00864 | I56: =I55+G56 -> 0.81008 | J56: =J55+H56 -> 0.95616 | N56: =N55+L56+G56 -> 34.51708 | O56: =O55+M56+H56 -> 36.34851 | W56: =W55+E56+R56 -> 358.6 | X56: =SUM(X55,G56,L56,S56,U56) -> 69.29146 | Y56: =SUM(Y55,H56,M56,T56,V56) -> 72.83362 | Z56: =1-P56/100 -> 1 | AA56: =Z56*AA55 -> 0.84217476
B57: 19 | C57: Slide BLE112 on FnOFI-GN1212 | D57: 4 | E57: 1.2 | F57: =F56+E57 -> 134 | G57: =E57*$E$4 -> 0.00732 | H57: =E57*$E$5 -> 0.00864 | I57: =I56+G57 -> 0.8174 | J57: =J56+H57 -> 0.9648 | K57: 11 | L57: =VLOOKUP($K57,Components!$A$3:$I$23,8,FALSE) -> 2 | M57: =VLOOKUP($K57,Components!$A$3:$I$23,9,FALSE) -> 2.1 | N57: =N56+L57+G57 -> 36.5244 | O57: =O56+M57+H57 -> 38.45715 | P57: 0 | Q57: Redo Test F | R57: =F141 -> 54.5 | S57: =$R57*$E$4 -> 0.33245 | T57: =$R57*$E$5 -> 0.3924 | U57: =SUM(L133:L141) -> 0.31 | V57: =SUM(M133:M141) -> 0.3255 | W57: =W56+E57+R57 -> 414.3 | X57: =SUM(X56,G57,L57,S57,U57) -> 71.94123 | Y57: =SUM(Y56,H57,M57,T57,V57) -> 75.66016 | Z57: =1-P57/100 -> 1 | AA57: =Z57*AA56 -> 0.84217476
B58: 20 | C58: Slide BD20911131BB on FnOFI-GN1212 | D58: 1 | E58: 1.2 | F58: =F57+E58 -> 135.2 | G58: =E58*$E$4 -> 0.00732 | H58: =E58*$E$5 -> 0.00864 | I58: =I57+G58 -> 0.82472 | J58: =J57+H58 -> 0.97344 | K58: 6 | L58: =VLOOKUP($K58,Components!$A$3:$I$23,8,FALSE) -> 1.88 | M58: =VLOOKUP($K58,Components!$A$3:$I$23,9,FALSE) -> 1.974 | N58: =N57+L58+G58 -> 38.41172 | O58: =O57+M58+H58 -> 40.43979 | W58: =W57+E58+R58 -> 415.5 | X58: =SUM(X57,G58,L58,S58,U58) -> 73.82855 | Y58: =SUM(Y57,H58,M58,T58,V58) -> 77.6428 | Z58: =1-P58/100 -> 1 | AA58: =Z58*AA57 -> 0.84217476
B59: 21 | C59: Place SFLV25 | D59: 2 | E59: 12 | F59: =F58+E59 -> 147.2 | G59: =E59*$E$4 -> 0.0732 | H59: =E59*$E$5 -> 0.0864 | I59: =I58+G59 -> 0.89792 | J59: =J58+H59 -> 1.05984 | K59: 3 | L59: =VLOOKUP($K59,Components!$A$3:$I$23,8,FALSE) -> 17.42 | M59: =VLOOKUP($K59,Components!$A$3:$I$23,9,FALSE) -> 18.291 | N59: =N58+L59+G59 -> 55.90492 | O59: =O58+M59+H59 -> 58.81719 | W59: =W58+E59+R59 -> 427.5 | X59: =SUM(X58,G59,L59,S59,U59) -> 91.32175 | Y59: =SUM(Y58,H59,M59,T59,V59) -> 96.0202 | Z59: =1-P59/100 -> 1 | AA59: =Z59*AA58 -> 0.84217476
B60: 22 | C60: SFLV25 is OK - Test G | D60: 3 | E60: 5 | F60: =F59+E60 -> 152.2 | G60: =E60*$E$4 -> 0.0305 | H60: =E60*$E$5 -> 0.036 | I60: =I59+G60 -> 0.92842 | J60: =J59+H60 -> 1.09584 | N60: =N59+L60+G60 -> 55.93542 | O60: =O59+M60+H60 -> 58.85319 | W60: =W59+E60+R60 -> 432.5 | X60: =SUM(X59,G60,L60,S60,U60) -> 91.35225 | Y60: =SUM(Y59,H60,M60,T60,V60) -> 96.0562 | Z60: =1-P60/100 -> 1 | AA60: =Z60*AA59 -> 0.84217476
B61: 23 | C61: Slid SS98AAIS into MPC432119-2 | D61: 4 | E61: 8 | F61: =F60+E61 -> 160.2 | G61: =E61*$E$4 -> 0.0488 | H61: =E61*$E$5 -> 0.0576 | I61: =I60+G61 -> 0.97722 | J61: =J60+H61 -> 1.15344 | K61: 9 | L61: =VLOOKUP($K61,Components!$A$3:$I$23,8,FALSE) -> 38.15 | M61: =VLOOKUP($K61,Components!$A$3:$I$23,9,FALSE) -> 40.0575 | N61: =N60+L61+G61 -> 94.13422 | O61: =O60+M61+H61 -> 98.96829 | P61: 3 | Q61: Redo Test G | R61: 0 | S61: 0 | T61: 0 | U61: 0 | V61: 0 | W61: =W60+E61+R61 -> 440.5 | X61: =SUM(X60,G61,L61,S61,U61) -> 129.55105 | Y61: =SUM(Y60,H61,M61,T61,V61) -> 136.1713 | Z61: =1-P61/100 -> 0.97 | AA61: =Z61*AA60 -> 0.81690952
B62: 24 | C62: Remove TrackR from Clamp | D62: 3 | E62: 13.3 | F62: =F61+E62 -> 173.5 | G62: =E62*$E$4 -> 0.08113 | H62: =E62*$E$5 -> 0.09576 | I62: =I61+G62 -> 1.05835 | J62: =J61+H62 -> 1.2492 | N62: =N61+L62+G62 -> 94.21535 | O62: =O61+M62+H62 -> 99.06405 | W62: =W61+E62+R62 -> 453.8 | X62: =SUM(X61,G62,L62,S62,U62) -> 129.63218 | Y62: =SUM(Y61,H62,M62,T62,V62) -> 136.26706 | Z62: =1-P62/100 -> 1 | AA62: =Z62*AA61 -> 0.81690952
B63: 24 | C63: Chemical Weld Assmbly | D63: 2 | E63: 5 | F63: =F62+E63 -> 178.5 | G63: =E63*$E$4 -> 0.0305 | H63: =E63*$E$5 -> 0.036 | I63: =I62+G63 -> 1.08885 | J63: =J62+H63 -> 1.2852 | N63: =N62+L63+G63 -> 94.24585 | O63: =O62+M63+H63 -> 99.10005 | W63: =W62+E63+R63 -> 458.8 | X63: =SUM(X62,G63,L63,S63,U63) -> 129.66268 | Y63: =SUM(Y62,H63,M63,T63,V63) -> 136.30306 | Z63: =1-P63/100 -> 1 | AA63: =Z63*AA62 -> 0.81690952
B64: 25 | C64: Heat Test H | D64: 1 | E64: 10 | F64: =F63+E64 -> 188.5 | G64: =E64*$E$4 -> 0.061 | H64: =E64*$E$5 -> 0.072 | I64: =I63+G64 -> 1.14985 | J64: =J63+H64 -> 1.3572 | N64: =N63+L64+G64 -> 94.30685 | O64: =O63+M64+H64 -> 99.17205 | P64: 9.5 | Q64: Redo Test H | R64: 0 | S64: 0 | T64: 0 | U64: 0 | V64: 0 | W64: =W63+E64+R64 -> 468.8 | X64: =SUM(X63,G64,L64,S64,U64) -> 129.72368 | Y64: =SUM(Y63,H64,M64,T64,V64) -> 136.37506 | Z64: =1-P64/100 -> 0.905 | AA64: =Z64*AA63 -> 0.73930311
B65: 25 | C65: Move to Testing PC | D65: 3 | E65: 15 | F65: =F64+E65 -> 203.5 | G65: =E65*$E$4 -> 0.0915 | H65: =E65*$E$5 -> 0.108 | I65: =I64+G65 -> 1.24135 | J65: =J64+H65 -> 1.4652 | N65: =N64+L65+G65 -> 94.39835 | O65: =O64+M65+H65 -> 99.28005 | W65: =W64+E65+R65 -> 483.8 | X65: =SUM(X64,G65,L65,S65,U65) -> 129.81518 | Y65: =SUM(Y64,H65,M65,T65,V65) -> 136.48306 | Z65: =1-P65/100 -> 1 | AA65: =Z65*AA64 -> 0.73930311
B66: 26 | C66: Turn on TrackR | D66: 2 | E66: 3 | F66: =F65+E66 -> 206.5 | G66: =E66*$E$4 -> 0.0183 | H66: =E66*$E$5 -> 0.0216 | I66: =I65+G66 -> 1.25965 | J66: =J65+H66 -> 1.4868 | N66: =N65+L66+G66 -> 94.41665 | O66: =O65+M66+H66 -> 99.30165 | W66: =W65+E66+R66 -> 486.8 | X66: =SUM(X65,G66,L66,S66,U66) -> 129.83348 | Y66: =SUM(Y65,H66,M66,T66,V66) -> 136.50466 | Z66: =1-P66/100 -> 1 | AA66: =Z66*AA65 -> 0.73930311
B67: 27 | C67: Wait for Radio Connectivity/ Sync - Test J | D67: 1 | E67: 40 | F67: =F66+E67 -> 246.5 | G67: =E67*$E$4 -> 0.244 | H67: =E67*$E$5 -> 0.288 | I67: =I66+G67 -> 1.50365 | J67: =J66+H67 -> 1.7748 | N67: =N66+L67+G67 -> 94.66065 | O67: =O66+M67+H67 -> 99.58965 | P67: 2 | Q67: Redo Test J | R67: 0 | S67: 0 | T67: 0 | U67: 0 | V67: 0 | W67: =W66+E67+R67 -> 526.8 | X67: =SUM(X66,G67,L67,S67,U67) -> 130.07748 | Y67: =SUM(Y66,H67,M67,T67,V67) -> 136.79266 | Z67: =1-P67/100 -> 0.98 | AA67: =Z67*AA66 -> 0.72451705
B68: 28 | C68: Put TrackR into Version Packaging | D68: 4 | E68: 19 | F68: =F67+E68 -> 265.5 | G68: =E68*$E$4 -> 0.1159 | H68: =E68*$E$5 -> 0.1368 | I68: =I67+G68 -> 1.61955 | J68: =J67+H68 -> 1.9116 | N68: =N67+L68+G68 -> 94.77655 | O68: =O67+M68+H68 -> 99.72645 | W68: =W67+E68+R68 -> 545.8 | X68: =SUM(X67,G68,L68,S68,U68) -> 130.19338 | Y68: =SUM(Y67,H68,M68,T68,V68) -> 136.92946 | Z68: =1-P68/100 -> 1 | AA68: =Z68*AA67 -> 0.72451705
B69: 29 | C69: Place Packed TrackR on Conveyor | D69: 2 | E69: 2 | F69: =F68+E69 -> 267.5 | G69: =E69*$E$4 -> 0.0122 | H69: =E69*$E$5 -> 0.0144 | I69: =I68+G69 -> 1.63175 | J69: =J68+H69 -> 1.926 | N69: =N68+L69+G69 -> 94.78875 | O69: =O68+M69+H69 -> 99.74085 | W69: =W68+E69+R69 -> 547.8 | X69: =SUM(X68,G69,L69,S69,U69) -> 130.20558 | Y69: =SUM(Y68,H69,M69,T69,V69) -> 136.94386 | Z69: =1-P69/100 -> 1 | AA69: =Z69*AA68 -> 0.72451705
A71: Responses to Failed Tests
B73: Response A
B74: ReDo A | C74: If Test A Fails - Get another MPC4321119-2 from the shelf, and inspect it. Assume that the replacement part is OK.
B75: Step # | C75: Task | D75: Distance (m) | E75: Duration(sec) | F75: Total Time | G75: Labour Task Cost (min) | H75: Labour Task Cost (Max) | I75: Labour Cost Total to Task(min) | J75: Labour Cost Total to Task (Max) | K75: Componenent ID# | L75: Component Cost (Min) | M75: Component Cost (Max) | N75: All Total Cost to Task(Min) | O75: All Total Cost to Task (Max)
B76: 1 | C76: Walk to Return Goods Shelf | D76: 7.9 | E76: =D76/$H$11 -> 3.95 | F76: =E76 -> 3.95 | G76: =E76*$E$4 -> 0.024095 | H76: =E76*$E$5 -> 0.02844 | I76: =G76 -> 0.024095 | J76: =H76 -> 0.02844 | N76: =L76+G76 -> 0.024095 | O76: =M76+H76 -> 0.02844
B77: 2 | C77: Put down the Failed Part | E77: 2 | F77: =F76+E77 -> 5.95 | G77: =E77*$E$4 -> 0.0122 | H77: =E77*$E$5 -> 0.0144 | I77: =I76+G77 -> 0.036295 | J77: =J76+H77 -> 0.04284 | K77: 1 | L77: =VLOOKUP($K77,Components!$A$3:$I$23,8,FALSE) -> 6.606 | M77: =VLOOKUP($K77,Components!$A$3:$I$23,9,FALSE) -> 6.9363 | N77: =N76+L77+G77 -> 6.642295 | O77: =O76+M77+H77 -> 6.97914
B78: 3 | C78: Record the failure | E78: 8 | F78: =F77+E78 -> 13.95 | G78: =E78*$E$4 -> 0.0488 | H78: =E78*$E$5 -> 0.0576 | I78: =I77+G78 -> 0.085095 | J78: =J77+H78 -> 0.10044 | N78: =N77+L78+G78 -> 6.691095 | O78: =O77+M78+H78 -> 7.03674
B79: 4 | C79: Walk to the Replacement Parts Shelf | D79: 9.6 | E79: =D79/$H$11 -> 4.8 | F79: =F78+E79 -> 18.75 | G79: =E79*$E$4 -> 0.02928 | H79: =E79*$E$5 -> 0.03456 | I79: =I78+G79 -> 0.114375 | J79: =J78+H79 -> 0.135 | N79: =N78+L79+G79 -> 6.720375 | O79: =O78+M79+H79 -> 7.0713
B80: 5 | C80: Pick Up the Replacement Part | E80: 3 | F80: =F79+E80 -> 21.75 | G80: =E80*$E$4 -> 0.0183 | H80: =E80*$E$5 -> 0.0216 | I80: =I79+G80 -> 0.132675 | J80: =J79+H80 -> 0.1566 | N80: =N79+L80+G80 -> 6.738675 | O80: =O79+M80+H80 -> 7.0929
B81: 6 | C81: Walk back to the Assembly Table | D81: 7.9 | E81: =D81/$H$11 -> 3.95 | F81: =F80+E81 -> 25.7 | G81: =E81*$E$4 -> 0.024095 | H81: =E81*$E$5 -> 0.02844 | I81: =I80+G81 -> 0.15677 | J81: =J80+H81 -> 0.18504 | N81: =N80+L81+G81 -> 6.76277 | O81: =O80+M81+H81 -> 7.12134
B82: 2 | C82: Unbox MPC432119-2 | E82: 14 | F82: =F81+E82 -> 39.7 | G82: =E82*$E$4 -> 0.0854 | H82: =E82*$E$5 -> 0.1008 | I82: =I81+G82 -> 0.24217 | J82: =J81+H82 -> 0.28584 | N82: =N81+L82+G82 -> 6.84817 | O82: =O81+M82+H82 -> 7.22214
B83: 3 | C83: Inspect MPC432119-2 | E83: 5 | F83: =F82+E83 -> 44.7 | G83: =E83*$E$4 -> 0.0305 | H83: =E83*$E$5 -> 0.036 | I83: =I82+G83 -> 0.27267 | J83: =J82+H83 -> 0.32184 | N83: =N82+L83+G83 -> 6.87867 | O83: =O82+M83+H83 -> 7.25814
B85: ReDo B | C85: If Test B Fails - Detach MPC44422, get another LS112 from the shelf, and repeat the assembly steps
B86: Step # | C86: Task | D86: Distance (m) | E86: Duration(sec) | F86: Total Time | G86: Labour Task Cost (min) | H86: Labour Task Cost (Max) | I86: Labour Cost Total to Task(min) | J86: Labour Cost Total to Task (Max) | K86: Componenent ID# | L86: Component Cost (Min) | M86: Component Cost (Max) | N86: All Total Cost to Task(Min) | O86: All Total Cost to Task (Max)
B87: 1 | C87: Walk to Return Goods Shelf | D87: 7.9 | E87: =D87/$H$11 -> 3.95 | F87: =E87 -> 3.95 | G87: =E87*$E$4 -> 0.024095 | H87: =E87*$E$5 -> 0.02844 | I87: =G87 -> 0.024095 | J87: =H87 -> 0.02844 | N87: =L87+G87 -> 0.024095 | O87: =M87+H87 -> 0.02844
B88: 2 | C88: Put down the Failed Part | E88: 2 | F88: =F87+E88 -> 5.95 | G88: =E88*$E$4 -> 0.0122 | H88: =E88*$E$5 -> 0.0144 | I88: =I87+G88 -> 0.036295 | J88: =J87+H88 -> 0.04284 | N88: =N87+L88+G88 -> 0.036295 | O88: =O87+M88+H88 -> 0.04284
B89: 3 | C89: Record the failure | E89: 8 | F89: =F88+E89 -> 13.95 | G89: =E89*$E$4 -> 0.0488 | H89: =E89*$E$5 -> 0.0576 | I89: =I88+G89 -> 0.085095 | J89: =J88+H89 -> 0.10044 | K89: 2 | L89: =VLOOKUP($K89,Components!$A$3:$I$23,8,FALSE) -> 0.081 | M89: =VLOOKUP($K89,Components!$A$3:$I$23,9,FALSE) -> 0.08505 | N89: =N88+L89+G89 -> 0.166095 | O89: =O88+M89+H89 -> 0.18549
B90: 4 | C90: Walk to the Replacement Parts Shelf | D90: 9.6 | E90: =D90/$H$11 -> 4.8 | F90: =F89+E90 -> 18.75 | G90: =E90*$E$4 -> 0.02928 | H90: =E90*$E$5 -> 0.03456 | I90: =I89+G90 -> 0.114375 | J90: =J89+H90 -> 0.135 | N90: =N89+L90+G90 -> 0.195375 | O90: =O89+M90+H90 -> 0.22005
B91: 5 | C91: Pick Up the Replacement Part | E91: 3 | F91: =F90+E91 -> 21.75 | G91: =E91*$E$4 -> 0.0183 | H91: =E91*$E$5 -> 0.0216 | I91: =I90+G91 -> 0.132675 | J91: =J90+H91 -> 0.1566 | K91: 12 | L91: =VLOOKUP($K91,Components!$A$3:$I$23,8,FALSE) -> 3 | M91: =VLOOKUP($K91,Components!$A$3:$I$23,9,FALSE) -> 3.15 | N91: =N90+L91+G91 -> 3.213675 | O91: =O90+M91+H91 -> 3.39165
B92: 6 | C92: Walk back to the Assembly Table | D92: 7.9 | E92: =D92/$H$11 -> 3.95 | F92: =F91+E92 -> 25.7 | G92: =E92*$E$4 -> 0.024095 | H92: =E92*$E$5 -> 0.02844 | I92: =I91+G92 -> 0.15677 | J92: =J91+H92 -> 0.18504 | N92: =N91+L92+G92 -> 3.23777 | O92: =O91+M92+H92 -> 3.42009
B93: 3 | C93: MPC44422 is slid into LS1121 | E93: 3 | F93: =F92+E93 -> 28.7 | G93: =E93*$E$4 -> 0.0183 | H93: =E93*$E$5 -> 0.0216 | I93: =I92+G93 -> 0.17507 | J93: =J92+H93 -> 0.20664 | N93: =N92+L93+G93 -> 3.25607 | O93: =O92+M93+H93 -> 3.44169
B94: 4 | C94: Connect LS1121 to MPC432119-2 | E94: 7 | F94: =F93+E94 -> 35.7 | G94: =E94*$E$4 -> 0.0427 | H94: =E94*$E$5 -> 0.0504 | I94: =I93+G94 -> 0.21777 | J94: =J93+H94 -> 0.25704 | N94: =N93+L94+G94 -> 3.29877 | O94: =O93+M94+H94 -> 3.49209
B97: ReDo C
B98: Response C | C98: If Test C Fails - Board must be cleaned of old solder and soldered again properly
B99: Step # | C99: Task | D99: Distance (m) | E99: Duration(sec) | F99: Total Time | G99: Labour Task Cost (min) | H99: Labour Task Cost (Max) | I99: Labour Cost Total to Task(min) | J99: Labour Cost Total to Task (Max) | K99: Componenent ID# | L99: Component Cost (Min) | M99: Component Cost (Max) | N99: All Total Cost to Task(Min) | O99: All Total Cost to Task (Max)
B100: 1 | C100: Clean old solder on board | E100: 11 | F100: =E100 -> 11 | G100: =E100*$E$4 -> 0.0671 | H100: =E100*$E$5 -> 0.0792 | I100: =G100 -> 0.0671 | J100: =H100 -> 0.0792 | N100: =L100+G100 -> 0.0671 | O100: =M100+H100 -> 0.0792
B101: 6 | C101: Place SDMALBB3033G on FnOFI-GN1212 | E101: 6.6 | F101: =F100+E101 -> 17.6 | G101: =E101*$E$4 -> 0.04026 | H101: =E101*$E$5 -> 0.04752 | I101: =I100+G101 -> 0.10736 | J101: =J100+H101 -> 0.12672 | K101: 10 | L101: =VLOOKUP($K101,Components!$A$3:$I$23,8,FALSE) -> 4 | M101: =VLOOKUP($K101,Components!$A$3:$I$23,9,FALSE) -> 4.2 | N101: =N100+L101+G101 -> 4.10736 | O101: =O100+M101+H101 -> 4.32672
B102: 7 | C102: Solder FnOFI-GN1212 to SDMALBB3033G | E102: 20 | F102: =F101+E102 -> 37.6 | G102: =E102*$E$4 -> 0.122 | H102: =E102*$E$5 -> 0.144 | I102: =I101+G102 -> 0.22936 | J102: =J101+H102 -> 0.27072 | K102: 4 | L102: =VLOOKUP($K102,Components!$A$3:$I$23,8,FALSE) -> 14.99 | M102: =VLOOKUP($K102,Components!$A$3:$I$23,9,FALSE) -> 15.7395 | N102: =N101+L102+G102 -> 19.21936 | O102: =O101+M102+H102 -> 20.21022
B104: ReDo D
B105: Response D | C105: If Test D Fails - Dispose Component HG213123-221 and record as porduct waste
B106: Step # | C106: Task | D106: Distance (m) | E106: Duration(sec) | F106: Total Time | G106: Labour Task Cost (min) | H106: Labour Task Cost (Max) | I106: Labour Cost Total to Task(min) | J106: Labour Cost Total to Task (Max) | K106: Componenent ID# | L106: Component Cost (Min) | M106: Component Cost (Max) | N106: All Total Cost to Task(Min) | O106: All Total Cost to Task (Max)
B107: 1 | C107: Walk to Return Goods Shelf | D107: 7.9 | E107: =D107/$H$11 -> 3.95 | F107: =E107 -> 3.95 | G107: =E107*$E$4 -> 0.024095 | H107: =E107*$E$5 -> 0.02844 | I107: =G107 -> 0.024095 | J107: =H107 -> 0.02844 | N107: =L107+G107 -> 0.024095 | O107: =M107+H107 -> 0.02844
B108: 2 | C108: Put down the Failed Part | E108: 2 | F108: =F107+E108 -> 5.95 | G108: =E108*$E$4 -> 0.0122 | H108: =E108*$E$5 -> 0.0144 | I108: =I107+G108 -> 0.036295 | J108: =J107+H108 -> 0.04284 | N108: =N107+L108+G108 -> 0.036295 | O108: =O107+M108+H108 -> 0.04284
B109: 3 | C109: Record the failure | E109: 8 | F109: =F108+E109 -> 13.95 | G109: =E109*$E$4 -> 0.0488 | H109: =E109*$E$5 -> 0.0576 | I109: =I108+G109 -> 0.085095 | J109: =J108+H109 -> 0.10044 | K109: 7 | L109: =VLOOKUP($K109,Components!$A$3:$I$23,8,FALSE) -> 0.57 | M109: =VLOOKUP($K109,Components!$A$3:$I$23,9,FALSE) -> 0.5985 | N109: =N108+L109+G109 -> 0.655095 | O109: =O108+M109+H109 -> 0.69894
B110: 4 | C110: Walk to the Replacement Parts Shelf | D110: 9.6 | E110: =D110/$H$11 -> 4.8 | F110: =F109+E110 -> 18.75 | G110: =E110*$E$4 -> 0.02928 | H110: =E110*$E$5 -> 0.03456 | I110: =I109+G110 -> 0.114375 | J110: =J109+H110 -> 0.135 | N110: =N109+L110+G110 -> 0.684375 | O110: =O109+M110+H110 -> 0.7335
B111: 5 | C111: Pick Up the Replacement Part | E111: 3 | F111: =F110+E111 -> 21.75 | G111: =E111*$E$4 -> 0.0183 | H111: =E111*$E$5 -> 0.0216 | I111: =I110+G111 -> 0.132675 | J111: =J110+H111 -> 0.1566 | N111: =N110+L111+G111 -> 0.702675 | O111: =O110+M111+H111 -> 0.7551
B112: 6 | C112: Walk back to the Assembly Table | D112: 7.9 | E112: =D112/$H$11 -> 3.95 | F112: =F111+E112 -> 25.7 | G112: =E112*$E$4 -> 0.024095 | H112: =E112*$E$5 -> 0.02844 | I112: =I111+G112 -> 0.15677 | J112: =J111+H112 -> 0.18504 | N112: =N111+L112+G112 -> 0.72677 | O112: =O111+M112+H112 -> 0.78354
B113: 7 | C113: Clean-up | E113: 14 | F113: =F112+E113 -> 39.7 | G113: =E113*$E$4 -> 0.0854 | H113: =E113*$E$5 -> 0.1008 | I113: =I112+G113 -> 0.24217 | J113: =J112+H113 -> 0.28584 | N113: =N112+L113+G113 -> 0.81217 | O113: =O112+M113+H113 -> 0.88434
B114: 10 | C114: Solder HG213123-221 to BD2098733AAB | E114: 12 | F114: =F113+E114 -> 51.7 | G114: =E114*$E$4 -> 0.0732 | H114: =E114*$E$5 -> 0.0864 | I114: =I113+G114 -> 0.31537 | J114: =J113+H114 -> 0.37224 | N114: =N113+L114+G114 -> 0.88537 | O114: =O113+M114+H114 -> 0.97074
B115: 11 | C115: Wait to Ensure bond | E115: 6 | F115: =F114+E115 -> 57.7 | G115: =E115*$E$4 -> 0.0366 | H115: =E115*$E$5 -> 0.0432 | I115: =I114+G115 -> 0.35197 | J115: =J114+H115 -> 0.41544 | N115: =N114+L115+G115 -> 0.92197 | O115: =O114+M115+H115 -> 1.01394
B117: ReDO E
...

Sheet A P&L
A1: As-Is Profit And loss
A3: Assumptions | C3: Issue | D3: Options # | E3: Description | H3: Chosen | I3: Notes and Sources of Knowledge
B4: 1 | C4: Is the Final Testing time included in the Assembly time (Calc Factor 1) for this model? | H4: No | I4: Directed by the Senior BA
C5: *** Final Testing is Done at the 4th Assembly Table *** | D5: 1 | E5: Yes
D6: 2 | E6: No
B8: 2 | C8: Should the production limit per day be built into this Calculation Model? | H8: No | I8: Directed by the Senior BA
C9: ** See point 1 in Additional Process Knowledge *** | D9: 1 | E9: Yes
D10: 2 | E10: No
B12: 3 | C12: Are shipping costs included in this model? | H12: No | I12: Shipping is Paid back by the TrackR Buyer
D13: 1 | E13: Yes
D14: 2 | E14: No
A16: Additional Process Knowledge
B17: 1 | C17: Current policy - Daily Limit of TrackR Production
C18: OHT will not build more TrackR's that it can sell in one day. In fact, it doesn't build a TRackR until it has an order for that TrackR.
C19: So, when enough TrackR's are built to meet orders, then production stops.
C20: Source - OHT Production VP - May 16
B22: 2 | C22: Current Policy - Picking of Components, and then Assembly
C23: Each Assembly worker - Lead Hand or not - walks and picks the needed components for one TrackR,
C24: and then, when an Assembly Table is available, steps to the assembly table
C25: and proceeds to perform all necessary actions and tests to asemble a Good TrackR.
C26: Source - OHT Production VP - May 16
B28: 3 | C28: All 3 Assembly Tables must be used continually until the daily limit is met
C29: So, often persons are standing still, with their picked components, waiting for an assembly table.
C30: Source - OHT Production VP - May 16
A33: Common Calculation Factors
B34: 1 | C34: Average Time for one worker to assemble and test one TrackR | D34: =(('A Assembly'!W69+'A Assembly'!F69)/2)/60 -> 7.3013946 | E34: Minutes
B35: 2 | C35: Average Time for one worker to pick one set of TrackR components, for one version | D35: =(('A Picking'!K43+'A Picking'!L43)/2)/60 -> 4.88795 | E35: Minutes
B36: 3 | C36: Hours of shift per day | D36: 7.5 | E36: Hours
B37: 4 | C37: Number of Assembly Tables in Use | D37: 3 | E37: Tables
B38: 5 | C38: Number of Shifts Per Day | D38: 2 | E38: Shifts
B39: 6 | C39: Failure Rate of Final Test | D39: ='A Assembly'!P67/100 -> 0.02
B40: 7 | C40: Failure Rate of Heat Test | D40: ='A Assembly'!P64/100 -> 0.095
B41: 8 | C41: Marketing Cost per TrackR (income for the Marketing Group) | D41: 10
A43: TrackR Production - Profit and Loss Estimate Model
B45: Gross Income Per Average Day
C46: Productive Work Time per hour (1 - Maintenance Time) | D46: 1 | E46: Hours
C47: Hours shift per day | D47: =D36 -> 7.5 | E47: Hours
C49: TrackRs made per hour Per Table | D49: =D46/(D34/60) -> 8.2176082 | E49: TrackRs per Hour
C50: TrackRs made per Table Per Shift | D50: =D49*D47 -> 61.632062 | E50: TrackRs per Shift
C51: ="TrackRs made by "&D37&" tables Per Shift" -> TrackRs made by 3 tables Per Shift | D51: =D50*D37 -> 184.89619 | E51: TrackR
C52: ="TrackRs per day in "&D38&" shifts" -> TrackRs per day in 2 shifts | D52: =D51*D38 -> 369.79237 | E52: TrackR
C53: Defective Rate (failing either the final or Heat tests) | D53: =D39+D40+D42 -> 0.115
C54: Good TrackRs built per day | D54: =D52*(1-D53) -> 327.26625 | E54: TrackR
C56: Gross Profit (Good TrackR's * WholeSale Price) per Day
C57: is not calculated, because of the need to calculate for 3 versions
D59: TrackR A | E59: TrackR B | F59: TrackR C
C60: Wholesale price of TrackR for 2019 Qtr 1 | D60: =GETPIVOTDATA("WholeSalePrice",WholeSale!$A$8,"ProductCode","Trackr A") -> 140 | E60: =GETPIVOTDATA("WholeSalePrice",WholeSale!$A$8,"ProductCode","Trackr B") -> 115 | F60: =GETPIVOTDATA("WholeSalePrice",WholeSale!$A$8,"ProductCode","Trackr C") -> 155
C61: Component Cost of One TrackR | D61: =Table3[[#Totals],[Max]] -> 104.11485 | E61: =Table4[[#Totals],[Max]] -> 99.91485 | F61: =Table5[[#Totals],[Max]] -> 109.36485
C62: Marketing Cost | D62: =D41 -> 10 | E62: =D62 -> 10 | F62: =E62 -> 10 | I62: 126 days in 6 months
C63: Daily TrackR Built for 2018 Qtr 4 and 2019 Qtr 1 | D63: =(GETPIVOTDATA("Quantity",DayProdn!$A$8,"ProductCode","Trackr A")+GETPIVOTDATA("Quantity",DayProdn!$D$8,"ProductCode","Trackr A"))/126 -> 65.785714 | E63: =(GETPIVOTDATA("Quantity",DayProdn!$A$8,"ProductCode","Trackr B")+GETPIVOTDATA("Quantity",DayProdn!$D$8,"ProductCode","Trackr B"))/126 -> 59.452381 | F63: =(GETPIVOTDATA("Quantity",DayProdn!$A$8,"ProductCode","Trackr C")+GETPIVOTDATA("Quantity",DayProdn!$D$8,"ProductCode","Trackr C"))/126 -> 55.18254
C64: Percentage of TrackR Version Built per Day | D64: =D63/SUM($D$63:$F$63) -> 0.36462411 | E64: =E63/SUM($D$63:$F$63) -> 0.32952096 | F64: =F63/SUM($D$63:$F$63) -> 0.30585492
C65: Profit Per Good TrackR | D65: =D60-(D61+D62) -> 25.88515 | E65: =E60-(E61+E62) -> 5.08515 | F65: =F60-(F61+F62) -> 35.63515
B67: Net Income Per Average Day
C68: Net Profit per TrackR Version for "Good TrackRs Built Per Day" | D68: =D65*D64*$D54 -> 3088.8534 | E68: =E65*E64*$D54 -> 548.38811 | F68: =F65*F64*$D54 -> 3566.9357
C69: ( Net Profit = Gross Profit - Component Costs - Marketing Costs )
C71: Less: Component Costs of Failed TRackR's that were built | D71: =D61*(D52-D54)*D64 -> 1614.41 | E71: =E61*(D52-D54)*E64 -> 1400.1316 | F71: =F61*(D52-D54)*F64 -> 1422.4894
C73: Total Net Profit for Good TrackR's of 3 Versions per Day | D73: =SUM(D68:F68)-SUM(D71:F71) -> 2767.1462
B75: Direct Labour Costs Per Day | D75: Payrate | F75: Number of Staff
C76: Team Member | D76: =Employees!C22 -> 22 | E76: per hour | F76: =VLOOKUP(C76,Employees!$A$5:$B$14,2,FALSE) -> 12
C77: Team Lead | D77: =Employees!C21 -> 26 | E77: per hour | F77: =VLOOKUP(C77,Employees!$A$5:$B$14,2,FALSE) -> 6
C78: Maintenance | D78: =Employees!C23 -> 26 | E78: per hour | F78: =VLOOKUP(C78,Employees!$A$5:$B$14,2,FALSE) -> 6
C80: Payroll Burden | D80: 0.2
C82: Total Direct Labour Cost Per Day | D82: =(D76*F76+D77*F77+D78*F78)*D36*(1+D80) -> 5184
B84: InDirect Labour Costs Per Day - For both TrackR and Medical Imaging | I84: ** This should be hidden **
C85: Role | D85: Amount per hour | E85: Number of workers | F85: Hours per day | I85: Indirect labour expense for one day
C86: Team Lead | D86: 0 | E86: =VLOOKUP(C86,Employees!$A$5:$B$14,2,FALSE) -> 6 | F86: 8 | I86: =D86*E86*F86 -> 0
C87: Shift / Maintenance Manager | D87: =VLOOKUP(C87,Employees!$B$21:$C$33,2,FALSE) -> 30 | E87: =VLOOKUP(C87,Employees!$A$5:$B$14,2,FALSE) -> 3 | F87: 8 | I87: =D87*E87*F87 -> 720
C88: QC Staff | D88: =VLOOKUP(C88,Employees!$B$21:$C$33,2,FALSE) -> 26 | E88: =VLOOKUP(C88,Employees!$A$5:$B$14,2,FALSE) -> 3 | F88: 8 | I88: =D88*E88*F88 -> 624
C89: Product and Process Designers | D89: =VLOOKUP(C89,Employees!$B$21:$C$33,2,FALSE) -> 30 | E89: =VLOOKUP(C89,Employees!$A$5:$B$14,2,FALSE) -> 2 | F89: 8 | I89: =D89*E89*F89 -> 480
C90: Purchasing Agents | D90: =VLOOKUP(C90,Employees!$B$21:$C$33,2,FALSE) -> 23.08 | E90: =VLOOKUP(C90,Employees!$A$5:$B$14,2,FALSE) -> 2 | F90: 8 | I90: =D90*E90*F90 -> 369.28
C91: Shipper / Receivers | D91: =VLOOKUP(C91,Employees!$B$21:$C$33,2,FALSE) -> 26 | E91: =VLOOKUP(C91,Employees!$A$5:$B$14,2,FALSE) -> 2 | F91: 8 | I91: =D91*E91*F91 -> 416
C92: Human Resources | D92: =VLOOKUP(C92,Employees!$B$21:$C$33,2,FALSE) -> 21.54 | E92: =VLOOKUP(C92,Employees!$A$5:$B$14,2,FALSE) -> 3 | F92: 8 | I92: =D92*E92*F92 -> 516.96
C93: Production VP / Plant Manager | D93: =VLOOKUP(C93,Employees!$B$21:$C$33,2,FALSE) -> 30.77 | E93: =VLOOKUP(C93,Employees!$A$5:$B$14,2,FALSE) -> 1 | F93: 8 | I93: =D93*E93*F93 -> 246.16
I94: =SUM(I86:I93) -> 3372.4
C95: TrackR Share of Indirect Labour Costs Per Day | D95: 0.5
C97: Total InDirect Labour Cost Per Day | D97: =D95*I94 -> 1686.2
B99: Other Expenses
C100: Plant Operational Expenses (Electricity, Water, Insurance, etc) | D100: 42 | E100: per Hour
C101: for TrackR | D101: 24 | E101: Hours per Working Day
B103: Summary for 1 Day and Profit / Loss Calculations
C104: Net Income | D104: =D73 -> 2767.1462
C105: Direct Labour | D105: =-D82 -> -5184
C106: Indirect Labout | D106: =-D97 -> -1686.2
C107: Other Expenses | D107: =-(D100*D101) -> -1008
C109: One Day Profit / Loss | D109: =SUM(D104:D108) -> -5111.0538

Sheet T P&L
A1: As-Is Profit And loss
A3: Assumptions | C3: Issue | D3: Options # | E3: Description | H3: Chosen | I3: Notes and Sources of Knowledge
B4: 1 | C4: Is the Final Testing time included in the Assembly time (Calc Factor 1) for this model? | H4: No | I4: Directed by the Senior BA
C5: *** Final Testing is Done at the 4th Assembly Table *** | D5: 1 | E5: Yes
D6: 2 | E6: No
B8: 2 | C8: Should the production limit per day be built into this Calculation Model? | H8: No | I8: Directed by the Senior BA
C9: ** See point 1 in Additional Process Knowledge *** | D9: 1 | E9: Yes
D10: 2 | E10: No
B12: 3 | C12: Are shipping costs included in this model? | H12: No | I12: Shipping is Paid back by the TrackR Buyer
D13: 1 | E13: Yes
D14: 2 | E14: No
A16: Additional Process Knowledge
B17: 1 | C17: Current policy - Daily Limit of TrackR Production
C18: OHT will not build more TrackR's that it can sell in one day. In fact, it doesn't build a TRackR until it has an order for that TrackR.
C19: So, when enough TrackR's are built to meet orders, then production stops.
C20: Source - OHT Production VP - May 16
B22: 2 | C22: Current Policy - Picking of Components, and then Assembly
C23: Each Assembly worker - Lead Hand or not - walks and picks the needed components for one TrackR,
C24: and then, when an Assembly Table is available, steps to the assembly table
C25: and proceeds to perform all necessary actions and tests to asemble a Good TrackR.
C26: Source - OHT Production VP - May 16
B28: 3 | C28: All 3 Assembly Tables must be used continually until the daily limit is met
C29: So, often persons are standing still, with their picked components, waiting for an assembly table.
C30: Source - OHT Production VP - May 16
A33: Common Calculation Factors
B34: 1 | C34: Average Time for one worker to assemble and test one TrackR | D34: =(('T Assembly'!W69+'T Assembly'!F69)/2)/60 -> 6.7941667 | E34: Minutes
B35: 2 | C35: Average Time for one worker to pick one set of TrackR components, for one version | D35: =(('T Picking'!K43+'T Picking'!L43)/2)/60 -> 2.3960859 | E35: Minutes
B36: 3 | C36: Hours of shift per day | D36: 4 | E36: Hours
B37: 4 | C37: Number of Assembly Tables in Use | D37: 3 | E37: Tables
B38: 5 | C38: Number of Shifts Per Day | D38: 2 | E38: Shifts
B39: 6 | C39: Failure Rate of Final Test | D39: ='A Assembly'!P67/100 -> 0.02
B40: 7 | C40: Failure Rate of Heat Test | D40: ='A Assembly'!P64/100 -> 0.095
B41: 8 | C41: Marketing Cost per TrackR (income for the Marketing Group) | D41: 10
A43: TrackR Production - Profit and Loss Estimate Model
B45: Gross Income Per Average Day
C46: Productive Work Time per hour (1 - Maintenance Time) | D46: 1 | E46: Hours
C47: Hours shift per day | D47: =D36 -> 4 | E47: Hours
C49: TrackRs made per hour Per Table | D49: =D46/(D34/60) -> 8.8311051 | E49: TrackRs per Hour
C50: TrackRs made per Table Per Shift | D50: =D49*D47 -> 35.32442 | E50: TrackRs per Shift
C51: ="TrackRs made by "&D37&" tables Per Shift" -> TrackRs made by 3 tables Per Shift | D51: =D50*D37 -> 105.97326 | E51: TrackR
C52: ="TrackRs per day in "&D38&" shifts" -> TrackRs per day in 2 shifts | D52: =D51*D38 -> 211.94652 | E52: TrackR
C53: Defective Rate (failing either the final or Heat tests) | D53: =D39+D40+D42 -> 0.115
C54: Good TrackRs built per day | D54: =D52*(1-D53) -> 187.57267 | E54: TrackR
C56: Gross Profit (Good TrackR's * WholeSale Price) per Day
C57: is not calculated, because of the need to calculate for 3 versions
D59: TrackR A | E59: TrackR B | F59: TrackR C
C60: Wholesale price of TrackR for 2019 Qtr 1 | D60: =GETPIVOTDATA("WholeSalePrice",WholeSale!$A$8,"ProductCode","Trackr A") -> 140 | E60: =GETPIVOTDATA("WholeSalePrice",WholeSale!$A$8,"ProductCode","Trackr B") -> 115 | F60: =GETPIVOTDATA("WholeSalePrice",WholeSale!$A$8,"ProductCode","Trackr C") -> 155
C61: Component Cost of One TrackR | D61: =Table3[[#Totals],[Max]] -> 104.11485 | E61: =Table4[[#Totals],[Max]] -> 99.91485 | F61: =Table5[[#Totals],[Max]] -> 109.36485
C62: Marketing Cost | D62: =D41 -> 10 | E62: =D62 -> 10 | F62: =E62 -> 10 | I62: 126 days in 6 months
C63: Daily TrackR Built for 2018 Qtr 4 and 2019 Qtr 1 | D63: =(GETPIVOTDATA("Quantity",DayProdn!$A$8,"ProductCode","Trackr A")+GETPIVOTDATA("Quantity",DayProdn!$D$8,"ProductCode","Trackr A"))/126 -> 65.785714 | E63: =(GETPIVOTDATA("Quantity",DayProdn!$A$8,"ProductCode","Trackr B")+GETPIVOTDATA("Quantity",DayProdn!$D$8,"ProductCode","Trackr B"))/126 -> 59.452381 | F63: =(GETPIVOTDATA("Quantity",DayProdn!$A$8,"ProductCode","Trackr C")+GETPIVOTDATA("Quantity",DayProdn!$D$8,"ProductCode","Trackr C"))/126 -> 55.18254
C64: Percentage of TrackR Version Built per Day | D64: =D63/SUM($D$63:$F$63) -> 0.36462411 | E64: =E63/SUM($D$63:$F$63) -> 0.32952096 | F64: =F63/SUM($D$63:$F$63) -> 0.30585492
C65: Profit Per Good TrackR | D65: =D60-(D61+D62) -> 25.88515 | E65: =E60-(E61+E62) -> 5.08515 | F65: =F60-(F61+F62) -> 35.63515
B67: Net Income Per Average Day
C68: Net Profit per TrackR Version for "Good TrackRs Built Per Day" | D68: =D65*D64*$D54 -> 1770.3765 | E68: =E65*E64*$D54 -> 314.30868 | F68: =F65*F64*$D54 -> 2044.3895
C69: ( Net Profit = Gross Profit - Component Costs - Marketing Costs )
C71: Less: Component Costs of Failed TRackR's that were built | D71: =D61*(D52-D54)*D64 -> 925.29923 | E71: =E61*(D52-D54)*E64 -> 802.48555 | F71: =F61*(D52-D54)*F64 -> 815.29987
C73: Total Net Profit for Good TrackR's of 3 Versions per Day | D73: =SUM(D68:F68)-SUM(D71:F71) -> 1585.99
B75: Direct Labour Costs Per Day | D75: Payrate | F75: Number of Staff
C76: Team Member | D76: =Employees!C22 -> 22 | E76: per hour | F76: =VLOOKUP(C76,Employees!$A$5:$B$14,2,FALSE) -> 12
C77: Team Lead | D77: =Employees!C21 -> 26 | E77: per hour | F77: =VLOOKUP(C77,Employees!$A$5:$B$14,2,FALSE) -> 6
C78: Maintenance | D78: =Employees!C23 -> 26 | E78: per hour | F78: =VLOOKUP(C78,Employees!$A$5:$B$14,2,FALSE) -> 6
C80: Payroll Burden | D80: 0.2
C82: Total Direct Labour Cost Per Day | D82: =(D76*F76+D77*F77+D78*F78)*D36*(1+D80) -> 2764.8
B84: InDirect Labour Costs Per Day - For both TrackR and Medical Imaging | I84: ** This should be hidden **
C85: Role | D85: Amount per hour | E85: Number of workers | F85: Hours per day | I85: Indirect labour expense for one day
C86: Team Lead | D86: 0 | E86: =VLOOKUP(C86,Employees!$A$5:$B$14,2,FALSE) -> 6 | F86: 8 | I86: =D86*E86*F86 -> 0
C87: Shift / Maintenance Manager | D87: =VLOOKUP(C87,Employees!$B$21:$C$33,2,FALSE) -> 30 | E87: =VLOOKUP(C87,Employees!$A$5:$B$14,2,FALSE) -> 3 | F87: 8 | I87: =D87*E87*F87 -> 720
C88: QC Staff | D88: =VLOOKUP(C88,Employees!$B$21:$C$33,2,FALSE) -> 26 | E88: =VLOOKUP(C88,Employees!$A$5:$B$14,2,FALSE) -> 3 | F88: 8 | I88: =D88*E88*F88 -> 624
C89: Product and Process Designers | D89: =VLOOKUP(C89,Employees!$B$21:$C$33,2,FALSE) -> 30 | E89: =VLOOKUP(C89,Employees!$A$5:$B$14,2,FALSE) -> 2 | F89: 8 | I89: =D89*E89*F89 -> 480
C90: Purchasing Agents | D90: =VLOOKUP(C90,Employees!$B$21:$C$33,2,FALSE) -> 23.08 | E90: =VLOOKUP(C90,Employees!$A$5:$B$14,2,FALSE) -> 2 | F90: 8 | I90: =D90*E90*F90 -> 369.28
C91: Shipper / Receivers | D91: =VLOOKUP(C91,Employees!$B$21:$C$33,2,FALSE) -> 26 | E91: =VLOOKUP(C91,Employees!$A$5:$B$14,2,FALSE) -> 2 | F91: 8 | I91: =D91*E91*F91 -> 416
C92: Human Resources | D92: =VLOOKUP(C92,Employees!$B$21:$C$33,2,FALSE) -> 21.54 | E92: =VLOOKUP(C92,Employees!$A$5:$B$14,2,FALSE) -> 3 | F92: 8 | I92: =D92*E92*F92 -> 516.96
C93: Production VP / Plant Manager | D93: =VLOOKUP(C93,Employees!$B$21:$C$33,2,FALSE) -> 30.77 | E93: =VLOOKUP(C93,Employees!$A$5:$B$14,2,FALSE) -> 1 | F93: 8 | I93: =D93*E93*F93 -> 246.16
I94: =SUM(I86:I93) -> 3372.4
C95: TrackR Share of Indirect Labour Costs Per Day | D95: 0.5
C97: Total InDirect Labour Cost Per Day | D97: =D95*I94 -> 1686.2
B99: Other Expenses
C100: Plant Operational Expenses (Electricity, Water, Insurance, etc) | D100: 42 | E100: per Hour
C101: for TrackR | D101: 24 | E101: Hours per Working Day
B103: Summary for 1 Day and Profit / Loss Calculations
C104: Net Income | D104: =D73 -> 1585.99
C105: Direct Labour | D105: =-D82 -> -2764.8
C106: Indirect Labout | D106: =-D97 -> -1686.2
C107: Other Expenses | D107: =-(D100*D101) -> -1008
C109: One Day Profit / Loss | D109: =SUM(D104:D108) -> -3873.01

Sheet Sunny Day
A1: As-Is Profit And loss
A3: Assumptions | C3: Issue | D3: Options # | E3: Description | H3: Chosen | I3: Notes and Sources of Knowledge
B4: 1 | C4: Is the Final Testing time included in the Assembly time (Calc Factor 1) for this model? | H4: No | I4: Directed by the Senior BA
C5: *** Final Testing is Done at the 4th Assembly Table *** | D5: 1 | E5: Yes
D6: 2 | E6: No
B8: 2 | C8: Should the production limit per day be built into this Calculation Model? | H8: No | I8: Directed by the Senior BA
C9: ** See point 1 in Additional Process Knowledge *** | D9: 1 | E9: Yes
D10: 2 | E10: No
B12: 3 | C12: Are shipping costs included in this model? | H12: No | I12: Shipping is Paid back by the TrackR Buyer
D13: 1 | E13: Yes
D14: 2 | E14: No
A16: Additional Process Knowledge
B17: 1 | C17: Current policy - Daily Limit of TrackR Production
C18: OHT will not build more TrackR's that it can sell in one day. In fact, it doesn't build a TRackR until it has an order for that TrackR.
C19: So, when enough TrackR's are built to meet orders, then production stops.
C20: Source - OHT Production VP - May 16
B22: 2 | C22: Current Policy - Picking of Components, and then Assembly
C23: Each Assembly worker - Lead Hand or not - walks and picks the needed components for one TrackR,
C24: and then, when an Assembly Table is available, steps to the assembly table
C25: and proceeds to perform all necessary actions and tests to asemble a Good TrackR.
C26: Source - OHT Production VP - May 16
B28: 3 | C28: All 3 Assembly Tables must be used continually until the daily limit is met
C29: So, often persons are standing still, with their picked components, waiting for an assembly table.
C30: Source - OHT Production VP - May 16
A33: Common Calculation Factors
B34: 1 | C34: Fast Time for one worker to assemble and test one TrackR | D34: ='T Assembly'!F69/60 -> 4.4583333 | E34: Minutes
B35: 2 | C35: Average Time for one worker to pick one set of TrackR components, for one version | D35: ='T Picking'!K43/60 -> 2.5560606 | E35: Minutes
B36: 3 | C36: Hours of shift per day | D36: 4 | E36: Hours
B37: 4 | C37: Number of Assembly Tables in Use | D37: 3 | E37: Tables
B38: 5 | C38: Number of Shifts Per Day | D38: 2 | E38: Shifts
B39: 6 | C39: Failure Rate of Final Test | D39: 0
B40: 7 | C40: Failure Rate of Heat Test | D40: 0
B41: 8 | C41: Marketing Cost per TrackR (income for the Marketing Group) | D41: 10
A43: TrackR Production - Profit and Loss Estimate Model
B45: Gross Income Per Average Day
C46: Productive Work Time per hour (1 - Maintenance Time) | D46: 1 | E46: Hours
C47: Hours shift per day | D47: =D36 -> 4 | E47: Hours
C49: TrackRs made per hour Per Table | D49: =D46/(D34/60) -> 13.457944 | E49: TrackRs per Hour
C50: TrackRs made per Table Per Shift | D50: =D49*D47 -> 53.831776 | E50: TrackRs per Shift
C51: ="TrackRs made by "&D37&" tables Per Shift" -> TrackRs made by 3 tables Per Shift | D51: =D50*D37 -> 161.49533 | E51: TrackR
C52: ="TrackRs per day in "&D38&" shifts" -> TrackRs per day in 2 shifts | D52: =D51*D38 -> 322.99065 | E52: TrackR
C53: Defective Rate (failing either the final or Heat tests) | D53: =D39+D40+D42 -> 0
C54: Good TrackRs built per day | D54: =D52*(1-D53) -> 322.99065 | E54: TrackR
C56: Gross Profit (Good TrackR's * WholeSale Price) per Day
C57: is not calculated, because of the need to calculate for 3 versions
D59: TrackR A | E59: TrackR B | F59: TrackR C
C60: Wholesale price of TrackR for 2019 Qtr 1 | D60: =GETPIVOTDATA("WholeSalePrice",WholeSale!$A$8,"ProductCode","Trackr A") -> 140 | E60: =GETPIVOTDATA("WholeSalePrice",WholeSale!$A$8,"ProductCode","Trackr B") -> 115 | F60: =GETPIVOTDATA("WholeSalePrice",WholeSale!$A$8,"ProductCode","Trackr C") -> 155
C61: Component Cost of One TrackR | D61: =Table3[[#Totals],[Max]] -> 104.11485 | E61: =Table4[[#Totals],[Max]] -> 99.91485 | F61: =Table5[[#Totals],[Max]] -> 109.36485
C62: Marketing Cost | D62: =D41 -> 10 | E62: =D62 -> 10 | F62: =E62 -> 10 | I62: 126 days in 6 months
C63: Daily TrackR Built for 2018 Qtr 4 and 2019 Qtr 1 | D63: =(GETPIVOTDATA("Quantity",DayProdn!$A$8,"ProductCode","Trackr A")+GETPIVOTDATA("Quantity",DayProdn!$D$8,"ProductCode","Trackr A"))/126 -> 65.785714 | E63: =(GETPIVOTDATA("Quantity",DayProdn!$A$8,"ProductCode","Trackr B")+GETPIVOTDATA("Quantity",DayProdn!$D$8,"ProductCode","Trackr B"))/126 -> 59.452381 | F63: =(GETPIVOTDATA("Quantity",DayProdn!$A$8,"ProductCode","Trackr C")+GETPIVOTDATA("Quantity",DayProdn!$D$8,"ProductCode","Trackr C"))/126 -> 55.18254
C64: Percentage of TrackR Version Built per Day | D64: =D63/SUM($D$63:$F$63) -> 0.36462411 | E64: =E63/SUM($D$63:$F$63) -> 0.32952096 | F64: =F63/SUM($D$63:$F$63) -> 0.30585492
C65: Profit Per Good TrackR | D65: =D60-(D61+D62) -> 25.88515 | E65: =E60-(E61+E62) -> 5.08515 | F65: =F60-(F61+F62) -> 35.63515
B67: Net Income Per Average Day
C68: Net Profit per TrackR Version for "Good TrackRs Built Per Day" | D68: =D65*D64*$D54 -> 3048.4988 | E68: =E65*E64*$D54 -> 541.22365 | F68: =F65*F64*$D54 -> 3520.3353
C69: ( Net Profit = Gross Profit - Component Costs - Marketing Costs )
C71: Less: Component Costs of Failed TRackR's that were built | D71: =D61*(D52-D54)*D64 -> 0 | E71: =E61*(D52-D54)*E64 -> 0 | F71: =F61*(D52-D54)*F64 -> 0
C73: Total Net Profit for Good TrackR's of 3 Versions per Day | D73: =SUM(D68:F68)-SUM(D71:F71) -> 7110.0577
B75: Direct Labour Costs Per Day | D75: Payrate | F75: Number of Staff
C76: Team Member | D76: =Employees!C22 -> 22 | E76: per hour | F76: 18
C77: Team Lead | D77: =Employees!C21 -> 26 | E77: per hour | F77: 0
C78: Maintenance | D78: =Employees!C23 -> 26 | E78: per hour | F78: =VLOOKUP(C78,Employees!$A$5:$B$14,2,FALSE) -> 6
C80: Payroll Burden | D80: 0.2
C82: Total Direct Labour Cost Per Day | D82: =(D76*F76+D77*F77+D78*F78)*D36*(1+D80) -> 2649.6
B84: InDirect Labour Costs Per Day - For both TrackR and Medical Imaging | I84: ** This should be hidden **
C85: Role | D85: Amount per hour | E85: Number of workers | F85: Hours per day | I85: Indirect labour expense for one day
C86: Team Lead | D86: 0 | E86: =VLOOKUP(C86,Employees!$A$5:$B$14,2,FALSE) -> 6 | F86: 8 | I86: =D86*E86*F86 -> 0
C87: Shift / Maintenance Manager | D87: =VLOOKUP(C87,Employees!$B$21:$C$33,2,FALSE) -> 30 | E87: =VLOOKUP(C87,Employees!$A$5:$B$14,2,FALSE) -> 3 | F87: 8 | I87: =D87*E87*F87 -> 720
C88: QC Staff | D88: =VLOOKUP(C88,Employees!$B$21:$C$33,2,FALSE) -> 26 | E88: =VLOOKUP(C88,Employees!$A$5:$B$14,2,FALSE) -> 3 | F88: 8 | I88: =D88*E88*F88 -> 624
C89: Product and Process Designers | D89: =VLOOKUP(C89,Employees!$B$21:$C$33,2,FALSE) -> 30 | E89: =VLOOKUP(C89,Employees!$A$5:$B$14,2,FALSE) -> 2 | F89: 8 | I89: =D89*E89*F89 -> 480
C90: Purchasing Agents | D90: =VLOOKUP(C90,Employees!$B$21:$C$33,2,FALSE) -> 23.08 | E90: =VLOOKUP(C90,Employees!$A$5:$B$14,2,FALSE) -> 2 | F90: 8 | I90: =D90*E90*F90 -> 369.28
C91: Shipper / Receivers | D91: =VLOOKUP(C91,Employees!$B$21:$C$33,2,FALSE) -> 26 | E91: =VLOOKUP(C91,Employees!$A$5:$B$14,2,FALSE) -> 2 | F91: 8 | I91: =D91*E91*F91 -> 416
C92: Human Resources | D92: =VLOOKUP(C92,Employees!$B$21:$C$33,2,FALSE) -> 21.54 | E92: =VLOOKUP(C92,Employees!$A$5:$B$14,2,FALSE) -> 3 | F92: 8 | I92: =D92*E92*F92 -> 516.96
C93: Production VP / Plant Manager | D93: =VLOOKUP(C93,Employees!$B$21:$C$33,2,FALSE) -> 30.77 | E93: =VLOOKUP(C93,Employees!$A$5:$B$14,2,FALSE) -> 1 | F93: 8 | I93: =D93*E93*F93 -> 246.16
I94: =SUM(I86:I93) -> 3372.4
C95: TrackR Share of Indirect Labour Costs Per Day | D95: 0.5
C97: Total InDirect Labour Cost Per Day | D97: =D95*I94 -> 1686.2
B99: Other Expenses
C100: Plant Operational Expenses (Electricity, Water, Insurance, etc) | D100: 42 | E100: per Hour
C101: for TrackR | D101: 24 | E101: Hours per Working Day
B103: Summary for 1 Day and Profit / Loss Calculations
C104: Net Income | D104: =D73 -> 7110.0577
C105: Direct Labour | D105: =-D82 -> -2649.6
C106: Indirect Labout | D106: =-D97 -> -1686.2
C107: Other Expenses | D107: =-(D100*D101) -> -1008
C109: One Day Profit / Loss | D109: =SUM(D104:D108) -> 1766.2577

Sheet Rainy Day
A1: As-Is Profit And loss
A3: Assumptions | C3: Issue | D3: Options # | E3: Description | H3: Chosen | I3: Notes and Sources of Knowledge
B4: 1 | C4: Is the Final Testing time included in the Assembly time (Calc Factor 1) for this model? | H4: No | I4: Directed by the Senior BA
C5: *** Final Testing is Done at the 4th Assembly Table *** | D5: 1 | E5: Yes
D6: 2 | E6: No
B8: 2 | C8: Should the production limit per day be built into this Calculation Model? | H8: No | I8: Directed by the Senior BA
C9: ** See point 1 in Additional Process Knowledge *** | D9: 1 | E9: Yes
D10: 2 | E10: No
B12: 3 | C12: Are shipping costs included in this model? | H12: No | I12: Shipping is Paid back by the TrackR Buyer
D13: 1 | E13: Yes
D14: 2 | E14: No
A16: Additional Process Knowledge
B17: 1 | C17: Current policy - Daily Limit of TrackR Production
C18: OHT will not build more TrackR's that it can sell in one day. In fact, it doesn't build a TRackR until it has an order for that TrackR.
C19: So, when enough TrackR's are built to meet orders, then production stops.
C20: Source - OHT Production VP - May 16
B22: 2 | C22: Current Policy - Picking of Components, and then Assembly
C23: Each Assembly worker - Lead Hand or not - walks and picks the needed components for one TrackR,
C24: and then, when an Assembly Table is available, steps to the assembly table
C25: and proceeds to perform all necessary actions and tests to asemble a Good TrackR.
C26: Source - OHT Production VP - May 16
B28: 3 | C28: All 3 Assembly Tables must be used continually until the daily limit is met
C29: So, often persons are standing still, with their picked components, waiting for an assembly table.
C30: Source - OHT Production VP - May 16
A33: Common Calculation Factors
B34: 1 | C34: Average Time for one worker to assemble and test one TrackR | D34: =(('A Assembly'!W69+'A Assembly'!F69)/2)/60 -> 7.3013946 | E34: Minutes
B35: 2 | C35: Average Time for one worker to pick one set of TrackR components, for one version | D35: =(('A Picking'!K43+'A Picking'!L43)/2)/60 -> 4.88795 | E35: Minutes
B36: 3 | C36: Hours of shift per day | D36: 4 | E36: Hours
B37: 4 | C37: Number of Assembly Tables in Use | D37: 3 | E37: Tables
B38: 5 | C38: Number of Shifts Per Day | D38: 2 | E38: Shifts
B39: 6 | C39: Failure Rate of Final Test | D39: ='A Assembly'!P67/100 -> 0.02
B40: 7 | C40: Failure Rate of Heat Test | D40: ='A Assembly'!P64/100 -> 0.095
B41: 8 | C41: Marketing Cost per TrackR (income for the Marketing Group) | D41: 10
A43: TrackR Production - Profit and Loss Estimate Model
B45: Gross Income Per Average Day
C46: Productive Work Time per hour (1 - Maintenance Time) | D46: 1 | E46: Hours
C47: Hours shift per day | D47: =D36 -> 4 | E47: Hours
C49: TrackRs made per hour Per Table | D49: =D46/(D34/60) -> 8.2176082 | E49: TrackRs per Hour
C50: TrackRs made per Table Per Shift | D50: =D49*D47 -> 32.870433 | E50: TrackRs per Shift
C51: ="TrackRs made by "&D37&" tables Per Shift" -> TrackRs made by 3 tables Per Shift | D51: =D50*D37 -> 98.611299 | E51: TrackR
C52: ="TrackRs per day in "&D38&" shifts" -> TrackRs per day in 2 shifts | D52: =D51*D38 -> 197.2226 | E52: TrackR
C53: Defective Rate (failing either the final or Heat tests) | D53: =D39+D40+D42 -> 0.115
C54: Good TrackRs built per day | D54: =D52*(1-D53) -> 174.542 | E54: TrackR
C56: Gross Profit (Good TrackR's * WholeSale Price) per Day
C57: is not calculated, because of the need to calculate for 3 versions
D59: TrackR A | E59: TrackR B | F59: TrackR C
C60: Wholesale price of TrackR for 2019 Qtr 1 | D60: =GETPIVOTDATA("WholeSalePrice",WholeSale!$A$8,"ProductCode","Trackr A") -> 140 | E60: =GETPIVOTDATA("WholeSalePrice",WholeSale!$A$8,"ProductCode","Trackr B") -> 115 | F60: =GETPIVOTDATA("WholeSalePrice",WholeSale!$A$8,"ProductCode","Trackr C") -> 155
C61: Component Cost of One TrackR | D61: =Table3[[#Totals],[Max]] -> 104.11485 | E61: =Table4[[#Totals],[Max]] -> 99.91485 | F61: =Table5[[#Totals],[Max]] -> 109.36485
C62: Marketing Cost | D62: =D41 -> 10 | E62: =D62 -> 10 | F62: =E62 -> 10 | I62: 126 days in 6 months
C63: Daily TrackR Built for 2018 Qtr 4 and 2019 Qtr 1 | D63: =(GETPIVOTDATA("Quantity",DayProdn!$A$8,"ProductCode","Trackr A")+GETPIVOTDATA("Quantity",DayProdn!$D$8,"ProductCode","Trackr A"))/126 -> 65.785714 | E63: =(GETPIVOTDATA("Quantity",DayProdn!$A$8,"ProductCode","Trackr B")+GETPIVOTDATA("Quantity",DayProdn!$D$8,"ProductCode","Trackr B"))/126 -> 59.452381 | F63: =(GETPIVOTDATA("Quantity",DayProdn!$A$8,"ProductCode","Trackr C")+GETPIVOTDATA("Quantity",DayProdn!$D$8,"ProductCode","Trackr C"))/126 -> 55.18254
C64: Percentage of TrackR Version Built per Day | D64: =D63/SUM($D$63:$F$63) -> 0.36462411 | E64: =E63/SUM($D$63:$F$63) -> 0.32952096 | F64: =F63/SUM($D$63:$F$63) -> 0.30585492
C65: Profit Per Good TrackR | D65: =D60-(D61+D62) -> 25.88515 | E65: =E60-(E61+E62) -> 5.08515 | F65: =F60-(F61+F62) -> 35.63515
B67: Net Income Per Average Day
C68: Net Profit per TrackR Version for "Good TrackRs Built Per Day" | D68: =D65*D64*$D54 -> 1647.3885 | E68: =E65*E64*$D54 -> 292.47366 | F68: =F65*F64*$D54 -> 1902.3657
C69: ( Net Profit = Gross Profit - Component Costs - Marketing Costs )
C71: Less: Component Costs of Failed TRackR's that were built | D71: =D61*(D52-D54)*D64 -> 861.01869 | E71: =E61*(D52-D54)*E64 -> 746.73688 | F71: =F61*(D52-D54)*F64 -> 758.66099
C73: Total Net Profit for Good TrackR's of 3 Versions per Day | D73: =SUM(D68:F68)-SUM(D71:F71) -> 1475.8113
B75: Direct Labour Costs Per Day | D75: Payrate | F75: Number of Staff
C76: Team Member | D76: =Employees!C22 -> 22 | E76: per hour | F76: 0
C77: Team Lead | D77: =Employees!C21 -> 26 | E77: per hour | F77: 18
C78: Maintenance | D78: =Employees!C23 -> 26 | E78: per hour | F78: =VLOOKUP(C78,Employees!$A$5:$B$14,2,FALSE) -> 6
C80: Payroll Burden | D80: 0.2
C82: Total Direct Labour Cost Per Day | D82: =(D76*F76+D77*F77+D78*F78)*D36*(1+D80) -> 2995.2
B84: InDirect Labour Costs Per Day - For both TrackR and Medical Imaging | I84: ** This should be hidden **
C85: Role | D85: Amount per hour | E85: Number of workers | F85: Hours per day | I85: Indirect labour expense for one day
C86: Team Lead | D86: 0 | E86: =VLOOKUP(C86,Employees!$A$5:$B$14,2,FALSE) -> 6 | F86: 8 | I86: =D86*E86*F86 -> 0
C87: Shift / Maintenance Manager | D87: =VLOOKUP(C87,Employees!$B$21:$C$33,2,FALSE) -> 30 | E87: =VLOOKUP(C87,Employees!$A$5:$B$14,2,FALSE) -> 3 | F87: 8 | I87: =D87*E87*F87 -> 720
C88: QC Staff | D88: =VLOOKUP(C88,Employees!$B$21:$C$33,2,FALSE) -> 26 | E88: =VLOOKUP(C88,Employees!$A$5:$B$14,2,FALSE) -> 3 | F88: 8 | I88: =D88*E88*F88 -> 624
C89: Product and Process Designers | D89: =VLOOKUP(C89,Employees!$B$21:$C$33,2,FALSE) -> 30 | E89: =VLOOKUP(C89,Employees!$A$5:$B$14,2,FALSE) -> 2 | F89: 8 | I89: =D89*E89*F89 -> 480
C90: Purchasing Agents | D90: =VLOOKUP(C90,Employees!$B$21:$C$33,2,FALSE) -> 23.08 | E90: =VLOOKUP(C90,Employees!$A$5:$B$14,2,FALSE) -> 2 | F90: 8 | I90: =D90*E90*F90 -> 369.28
C91: Shipper / Receivers | D91: =VLOOKUP(C91,Employees!$B$21:$C$33,2,FALSE) -> 26 | E91: =VLOOKUP(C91,Employees!$A$5:$B$14,2,FALSE) -> 2 | F91: 8 | I91: =D91*E91*F91 -> 416
C92: Human Resources | D92: =VLOOKUP(C92,Employees!$B$21:$C$33,2,FALSE) -> 21.54 | E92: =VLOOKUP(C92,Employees!$A$5:$B$14,2,FALSE) -> 3 | F92: 8 | I92: =D92*E92*F92 -> 516.96
C93: Production VP / Plant Manager | D93: =VLOOKUP(C93,Employees!$B$21:$C$33,2,FALSE) -> 30.77 | E93: =VLOOKUP(C93,Employees!$A$5:$B$14,2,FALSE) -> 1 | F93: 8 | I93: =D93*E93*F93 -> 246.16
I94: =SUM(I86:I93) -> 3372.4
C95: TrackR Share of Indirect Labour Costs Per Day | D95: 0.5
C97: Total InDirect Labour Cost Per Day | D97: =D95*I94 -> 1686.2
B99: Other Expenses
C100: Plant Operational Expenses (Electricity, Water, Insurance, etc) | D100: 42 | E100: per Hour
C101: for TrackR | D101: 24 | E101: Hours per Working Day
B103: Summary for 1 Day and Profit / Loss Calculations
C104: Net Income | D104: =D73 -> 1475.8113
C105: Direct Labour | D105: =-D82 -> -2995.2
C106: Indirect Labout | D106: =-D97 -> -1686.2
C107: Other Expenses | D107: =-(D100*D101) -> -1008
C109: One Day Profit / Loss | D109: =SUM(D104:D108) -> -4213.5887

Sheet Employees
A1: Attitudes towards Change | F1: Role | G1: Employee # | H1: Years Old | I1: Shift | J1: Attitude Code | K1: Comments
F2: Team Lead | G2: 616 | H2: 33 | I2: 1 | J2: 3 | L2: 3
A3: TrackR Prodn Staff as of Mar 22, 2019 | B3: Count | C3: Code | D3: of Attitudes toward Change as of Mar 24, 2019 | F3: Team Lead | G3: 629 | H3: 53 | I3: 1 | J3: 6 | L3: 6
F4: Team Lead | G4: 608 | H4: 26 | I4: 1 | J4: 4 | L4: 4
A5: Team Lead | B5: 6 | C5: 1 | D5: No Change Needed | F5: Team Lead | G5: 617 | H5: 39 | I5: 2 | J5: 4 | L5: 4
A6: Team Member | B6: 12 | C6: 2 | D6: Minor Tweaks / New Equipment Needed | F6: Team Lead | G6: 609 | H6: 32 | I6: 2 | J6: 3 | L6: 3
A7: Maintenance | B7: 6 | C7: 3 | D7: Training / Work Optimization Needed | F7: Team Lead | G7: 610 | H7: 49 | I7: 2 | J7: 6 | L7: 6
A8: Shift / Maintenance Manager | B8: 3 | C8: 4 | D8: Movement Changes Needed | F8: Team Member | G8: 623 | H8: 54 | I8: 1 | J8: 5 | L8: 5
A9: QC Staff | B9: 3 | C9: 5 | D9: Layout (and 4,3,2) Changes Needed | F9: Team Member | G9: 635 | H9: 32 | I9: 1 | J9: 3 | L9: 3
A10: Human Resources | B10: 3 | C10: 6 | D10: Total New facility needed | F10: Team Member | G10: 624 | H10: 35 | I10: 1 | J10: 4 | L10: 4
A11: Production VP / Plant Manager | B11: 1 | F11: Team Member | G11: 613 | H11: 44 | I11: 1 | J11: 3 | L11: 3
A12: Product and Process Designers | B12: 2 | F12: Team Member | G12: 636 | H12: 31 | I12: 1 | J12: 4 | L12: 4
A13: Purchasing Agents | B13: 2 | F13: Team Member | G13: 614 | H13: 52 | I13: 1 | J13: 2 | L13: 2
A14: Shipper / Receivers | B14: 2 | F14: Team Member | G14: 637 | H14: 42 | I14: 2 | J14: 4 | L14: 4
F15: Team Member | G15: 622 | H15: 46 | I15: 2 | J15: 5 | L15: 5
B16: =SUM(B5:B15) -> 40 | F16: Team Member | G16: 634 | H16: 35 | I16: 2 | J16: 3 | L16: 3
F17: Team Member | G17: 615 | H17: 41 | I17: 2 | J17: 6 | L17: 6
A18: Pay Rates without Company Taxes Burden | F18: Team Member | G18: 633 | H18: 25 | I18: 2 | J18: 3 | L18: 3
F19: Team Member | G19: 639 | H19: 31 | I19: 2 | J19: 4 | L19: 4
A20: Division | B20: Role | C20: Amount | D20: Per | F20: Team Maintenance | G20: 638 | H20: 43 | I20: 1 | J20: 2 | L20: 2
A21: TrackR | B21: Team Lead | C21: 26 | D21: per hour | F21: Team Maintenance | G21: 607 | H21: 43 | I21: 1 | J21: 1 | L21: 1
A22: TrackR | B22: Team Member | C22: 22 | D22: per hour | F22: Team Maintenance | G22: 631 | H22: 38 | I22: 1 | J22: 2 | L22: 2
A23: TrackR | B23: Team Maintenance | C23: 26 | D23: per hour | F23: Team Maintenance | G23: 618 | H23: 42 | I23: 2 | J23: 5 | L23: 5
A24: TrackR | B24: Shift / Maintenance Manager | C24: 30 | D24: per hour | F24: Team Maintenance | G24: 606 | H24: 41 | I24: 2 | J24: 4 | L24: 4
A25: TrackR | B25: QC Staff | C25: 26 | D25: per hour | F25: Team Maintenance | G25: 630 | H25: 29 | I25: 2 | J25: 1 | L25: 1
A26: CDL | B26: Product and Process Designers | C26: 30 | D26: per hour | F26: Shift / Maintenance Manager | G26: 611 | H26: 42 | I26: 1 | J26: 4 | L26: 4
F27: Shift / Maintenance Manager | G27: 605 | H27: 38 | I27: 2 | J27: 5 | L27: 5
A28: CDL | B28: Purchasing Agents | C28: 23.08 | D28: per hour | F28: Shift / Maintenance Manager | G28: 632 | H28: 28 | I28: as needed | J28: 2 | L28: 2
A29: CDL | B29: Shipper / Receivers | C29: 26 | D29: per hour | F29: Quality Control Tech | G29: 626 | H29: 41 | I29: 1 | J29: 3 | L29: 3
F30: Quality Control Tech | G30: 620 | H30: 38 | I30: 2 | J30: 2 | L30: 2
A31: CDL | B31: Human Resources | C31: 21.54 | D31: per hour | F31: Quality Control Tech | G31: 612 | H31: 32 | I31: as needed | J31: 4 | L31: 4
F32: Product and Process Designers | G32: 601 | H32: 25 | I32: Days | J32: 4 | L32: 4
A33: CDL | B33: Production VP / Plant Manager | C33: 30.77 | D33: per hour | F33: Product and Process Designers | G33: 602 | H33: 33 | I33: Days | J33: 2 | L33: 2
F34: Purchasing Agents | G34: 604 | H34: 33 | I34: Days | J34: 3 | L34: 3
F35: Purchasing Agents | G35: 619 | H35: 34 | I35: Days | J35: 3 | L35: 3
F36: Shipper / Receivers | G36: 627 | H36: 32 | I36: Days | J36: 2 | L36: 2
F37: Shipper / Receivers | G37: 603 | H37: 54 | I37: Days | J37: 5 | L37: 5

Sheet A Schedule
A1: As-Is 8 hour Three Table Schedule for 9 Assembly Workers | O1: ** Options - Different Worker Letters
A3: Assumptions | C3: Issue | H3: Options # | I3: Description | L3: Chosen | M3: Notes and Sources of Knowledge
B4: 1 | C4: What is the time that one worker spends assembling a TrackR? | L4: 5 | M4: minutes
H5: 1 | I5: 5 | J5: minutes
H6: 2 | I6: see assembly calculation
B8: 2 | C8: What is the time that one worker spends picking a TrackR? | L8: =I11 -> less than assembly time
H9: 1 | I9: 5 | J9: minutes
H10: 2 | I10: see assembly calculation
H11: 3 | I11: less than assembly time
B13: 3 | C13: The final test in Assembly is done at Table #4. Should this be in the model? | L13: 2 - No
H14: 1 | I14: Yes
H15: 2 | I15: No
A17: Additional Process Knowledge
B18: 1 | C18: The current policy is that every worker gets, at minimum, 10 minutes of break in every hour
B19: 2 | C19: The current policy is that every worker gets 30 minutes for a meal break somewhere in hours 4, 5 or 6
B20: 3 | C20: The current policy of 10 minute breaks every hour is to allow time for washroom, short snack, or relief from focused assembly work
D21: ** Is walking to pick more components not a break from focused assembly? **
A23: Common Calculation Factors
B24: 1 | C24: Time Interval for model below | H24: 5 | I24: minutes
B27: Table | C27: 1 | H27: 2 | L27: 3
B28: Hour | C28: Minute | D28: Assembling | E28: Picking | F28: Standby | H28: Assembling | I28: Picking | J28: Standby | L28: Assembling | M28: Picking | N28: Standby
B29: 1 | C29: 0 | D29: A | E29: B | F29: C | H29: D | I29: E | J29: F | L29: G | M29: H | N29: I
B30: =B29 -> 1 | C30: =C29+$H$24 -> 5 | D30: B | E30: A | F30: C | H30: E | I30: D | J30: F | L30: H | M30: G | N30: I
B31: =B30 -> 1 | C31: =C30+$H$24 -> 10 | D31: A | E31: B | F31: C | H31: D | I31: E | J31: F | L31: G | M31: H | N31: I
B32: =B31 -> 1 | C32: =C31+$H$24 -> 15 | D32: B | E32: C | F32: A | H32: E | I32: F | J32: D | L32: H | M32: I | N32: G
B33: =B32 -> 1 | C33: =C32+$H$24 -> 20 | D33: C | E33: B | F33: A | H33: F | I33: E | J33: D | L33: I | M33: H | N33: G
B34: =B33 -> 1 | C34: =C33+$H$24 -> 25 | D34: B | E34: A | F34: C | H34: E | I34: D | J34: F | L34: H | M34: G | N34: I
B35: =B34 -> 1 | C35: =C34+$H$24 -> 30 | D35: A | E35: B | F35: C | H35: D | I35: E | J35: F | L35: G | M35: H | N35: I
B36: =B35 -> 1 | C36: =C35+$H$24 -> 35 | D36: B | E36: A | F36: C | H36: E | I36: D | J36: F | L36: H | M36: G | N36: I
B37: =B36 -> 1 | C37: =C36+$H$24 -> 40 | D37: A | E37: C | F37: B | H37: D | I37: F | J37: E | L37: G | M37: I | N37: H
B38: =B37 -> 1 | C38: =C37+$H$24 -> 45 | D38: C | E38: A | F38: B | H38: F | I38: D | J38: E | L38: I | M38: G | N38: H
B39: =B38 -> 1 | C39: =C38+$H$24 -> 50 | D39: A | E39: B | F39: C | H39: D | I39: E | J39: F | L39: G | M39: H | N39: I
B40: =B39 -> 1 | C40: =C39+$H$24 -> 55 | D40: B | E40: A | F40: C | H40: E | I40: D | J40: F | L40: H | M40: G | N40: I
B41: =B40+1 -> 2 | C41: 0 | D41: C | E41: B | F41: A | H41: F | I41: E | J41: D | L41: I | M41: H | N41: G
B42: =B41 -> 2 | C42: =C41+$H$24 -> 5 | D42: B | E42: C | F42: A | H42: E | I42: F | J42: D | L42: H | M42: I | N42: G
B43: =B42 -> 2 | C43: =C42+$H$24 -> 10 | D43: C | E43: B | F43: A | H43: F | I43: E | J43: D | L43: I | M43: H | N43: G
B44: =B43 -> 2 | C44: =C43+$H$24 -> 15 | D44: B | E44: A | F44: C | H44: E | I44: D | J44: F | L44: H | M44: G | N44: I
B45: =B44 -> 2 | C45: =C44+$H$24 -> 20 | D45: A | E45: B | F45: C | H45: D | I45: E | J45: F | L45: G | M45: H | N45: I
B46: =B45 -> 2 | C46: =C45+$H$24 -> 25 | D46: B | E46: C | F46: A | H46: E | I46: F | J46: D | L46: H | M46: I | N46: G
B47: =B46 -> 2 | C47: 30 | D47: C | E47: B | F47: A | H47: F | I47: E | J47: D | L47: I | M47: H | N47: G
B48: =B47 -> 2 | C48: 35 | D48: B | E48: C | F48: A | H48: E | I48: F | J48: D | L48: H | M48: I | N48: G
B49: =B48 -> 2 | C49: 40 | D49: C | E49: A | F49: B | H49: F | I49: D | J49: E | L49: I | M49: G | N49: H
B50: =B49 -> 2 | C50: 45 | D50: A | E50: C | F50: B | H50: D | I50: F | J50: E | L50: G | M50: I | N50: H
B51: =B50 -> 2 | C51: 50 | D51: C | E51: B | F51: A | H51: F | I51: E | J51: D | L51: I | M51: H | N51: G
B52: =B51 -> 2 | C52: 55 | D52: B | E52: C | F52: A | H52: E | I52: F | J52: D | L52: H | M52: I | N52: G
B53: 3 | C53: 0 | D53: A | E53: C | F53: B | H53: D | I53: F | J53: E | L53: G | M53: I | N53: H
B54: 3 | C54: =C53+$H$24 -> 5 | D54: C | E54: A | F54: B | H54: F | I54: D | J54: E | L54: I | M54: G | N54: H
B55: 3 | C55: =C54+$H$24 -> 10 | D55: A | E55: C | F55: B | H55: D | I55: F | J55: E | L55: G | M55: I | N55: H
B56: 3 | C56: =C55+$H$24 -> 15 | D56: B | E56: A | F56: C | H56: E | I56: D | J56: F | L56: H | M56: G | N56: I
B57: 3 | C57: =C56+$H$24 -> 20 | D57: A | E57: B | F57: C | H57: D | I57: E | J57: F | L57: G | M57: H | N57: I
B58: 3 | C58: =C57+$H$24 -> 25 | D58: C | E58: A | F58: B | H58: F | I58: D | J58: E | L58: I | M58: G | N58: H
B59: 3 | C59: 30 | D59: A | E59: C | F59: B | H59: D | I59: F | J59: E | L59: G | M59: I | N59: H
B60: 3 | C60: 35 | D60: C | E60: A | F60: B | H60: F | I60: D | J60: E | L60: I | M60: G | N60: H
B61: 3 | C61: 40 | D61: B | E61: C | F61: A | H61: E | I61: F | J61: D | L61: H | M61: I | N61: G
B62: 3 | C62: 45 | D62: C | E62: B | F62: A | H62: F | I62: E | J62: D | L62: I | M62: H | N62: G
B63: 3 | C63: 50 | D63: A | E63: C | F63: B | H63: D | I63: F | J63: E | L63: G | M63: I | N63: H
B64: 3 | C64: 55 | D64: C | E64: A | F64: B | H64: F | I64: D | J64: E | L64: I | M64: G | N64: H
B65: 4 | C65: 0 | D65: C | E65: B | F65: A | H65: F | I65: E | J65: D | L65: I | M65: H | N65: G
B66: 4 | C66: =C65+$H$24 -> 5 | D66: B | E66: C | F66: A | H66: E | I66: F | J66: D | L66: H | M66: I | N66: G
B67: 4 | C67: =C66+$H$24 -> 10 | D67: C | E67: B | F67: A | H67: F | I67: E | J67: D | L67: I | M67: H | N67: G
B68: 4 | C68: =C67+$H$24 -> 15 | D68: B | E68: C | F68: A | H68: E | I68: F | J68: D | L68: H | M68: I | N68: G
B69: 4 | C69: =C68+$H$24 -> 20 | D69: C | E69: B | F69: A | H69: F | I69: E | J69: D | L69: I | M69: H | N69: G
B70: 4 | C70: =C69+$H$24 -> 25 | D70: B | E70: C | F70: A | H70: E | I70: F | J70: D | L70: H | M70: I | N70: G
B71: 4 | C71: 30 | D71: A | E71: B | F71: C | H71: D | I71: E | J71: F | L71: G | M71: H | N71: I
B72: 4 | C72: 35 | D72: B | E72: A | F72: C | H72: E | I72: D | J72: F | L72: H | M72: G | N72: I
B73: 4 | C73: 40 | D73: A | E73: C | F73: B | H73: D | I73: F | J73: E | L73: G | M73: I | N73: H
B74: 4 | C74: 45 | D74: C | E74: A | F74: B | H74: F | I74: D | J74: E | L74: I | M74: G | N74: H
B75: 4 | C75: 50 | D75: C | E75: B | F75: A | H75: F | I75: E | J75: D | L75: I | M75: H | N75: G
B76: 4 | C76: 55 | D76: B | E76: C | F76: A | H76: E | I76: F | J76: D | L76: H | M76: I | N76: G
B77: 5 | C77: 0 | D77: C | E77: A | F77: B | H77: F | I77: D | J77: E | L77: I | M77: G | N77: H
B78: 5 | C78: =C77+$H$24 -> 5 | D78: A | E78: C | F78: B | H78: D | I78: F | J78: E | L78: G | M78: I | N78: H
B79: 5 | C79: =C78+$H$24 -> 10 | D79: C | E79: A | F79: B | H79: F | I79: D | J79: E | L79: I | M79: G | N79: H
B80: 5 | C80: =C79+$H$24 -> 15 | D80: A | E80: C | F80: B | H80: D | I80: F | J80: E | L80: G | M80: I | N80: H
B81: 5 | C81: =C80+$H$24 -> 20 | D81: C | E81: A | F81: B | H81: F | I81: D | J81: E | L81: I | M81: G | N81: H
B82: 5 | C82: =C81+$H$24 -> 25 | D82: A | E82: C | F82: B | H82: D | I82: F | J82: E | L82: G | M82: I | N82: H
B83: 5 | C83: 30 | D83: C | E83: B | F83: A | H83: F | I83: E | J83: D | L83: I | M83: H | N83: G
B84: 5 | C84: 35 | D84: B | E84: C | F84: A | H84: E | I84: F | J84: D | L84: H | M84: I | N84: G
B85: 5 | C85: 40 | D85: B | E85: A | F85: C | H85: E | I85: D | J85: F | L85: H | M85: G | N85: I
B86: 5 | C86: 45 | D86: A | E86: B | F86: C | H86: D | I86: E | J86: F | L86: G | M86: H | N86: I
B87: 5 | C87: 50 | D87: C | E87: A | F87: B | H87: F | I87: D | J87: E | L87: I | M87: G | N87: H
B88: 5 | C88: 55 | D88: A | E88: C | F88: B | H88: D | I88: F | J88: E | L88: G | M88: I | N88: H
B89: 6 | C89: 0 | D89: A | E89: B | F89: C | H89: D | I89: E | J89: F | L89: G | M89: H | N89: I
B90: 6 | C90: =C89+$H$24 -> 5 | D90: B | E90: A | F90: C | H90: E | I90: D | J90: F | L90: H | M90: G | N90: I
B91: 6 | C91: =C90+$H$24 -> 10 | D91: A | E91: B | F91: C | H91: D | I91: E | J91: F | L91: G | M91: H | N91: I
B92: 6 | C92: =C91+$H$24 -> 15 | D92: B | E92: A | F92: C | H92: E | I92: D | J92: F | L92: H | M92: G | N92: I
B93: 6 | C93: =C92+$H$24 -> 20 | D93: A | E93: B | F93: C | H93: D | I93: E | J93: F | L93: G | M93: H | N93: I
B94: 6 | C94: =C93+$H$24 -> 25 | D94: B | E94: A | F94: C | H94: E | I94: D | J94: F | L94: H | M94: G | N94: I
B95: 6 | C95: 30 | D95: C | E95: B | F95: A | H95: F | I95: E | J95: D | L95: I | M95: H | N95: G
B96: 6 | C96: 35 | D96: B | E96: C | F96: A | H96: E | I96: F | J96: D | L96: H | M96: I | N96: G
B97: 6 | C97: 40 | D97: A | E97: C | F97: B | H97: D | I97: F | J97: E | L97: G | M97: I | N97: H
B98: 6 | C98: 45 | D98: C | E98: A | F98: B | H98: F | I98: D | J98: E | L98: I | M98: G | N98: H
B99: 6 | C99: 50 | D99: A | E99: B | F99: C | H99: D | I99: E | J99: F | L99: G | M99: H | N99: I
B100: 6 | C100: 55 | D100: B | E100: A | F100: C | H100: E | I100: D | J100: F | L100: H | M100: G | N100: I
B101: 7 | C101: 0 | D101: A | E101: B | F101: C | H101: D | I101: E | J101: F | L101: G | M101: H | N101: I
B102: 7 | C102: =C101+$H$24 -> 5 | D102: B | E102: A | F102: C | H102: E | I102: D | J102: F | L102: H | M102: G | N102: I
B103: 7 | C103: =C102+$H$24 -> 10 | D103: A | E103: B | F103: C | H103: D | I103: E | J103: F | L103: G | M103: H | N103: I
B104: 7 | C104: =C103+$H$24 -> 15 | D104: B | E104: C | F104: A | H104: E | I104: F | J104: D | L104: H | M104: I | N104: G
B105: 7 | C105: =C104+$H$24 -> 20 | D105: C | E105: B | F105: A | H105: F | I105: E | J105: D | L105: I | M105: H | N105: G
B106: 7 | C106: =C105+$H$24 -> 25 | D106: B | E106: A | F106: C | H106: E | I106: D | J106: F | L106: H | M106: G | N106: I
B107: 7 | C107: 30 | D107: A | E107: B | F107: C | H107: D | I107: E | J107: F | L107: G | M107: H | N107: I
...

Sheet T Schedule
A1: As-Is 8 hour Three Table Schedule for 9 Assembly Workers | O1: ** Options - Different Worker Letters
A3: Assumptions | C3: Issue | H3: Options # | I3: Description | L3: Chosen | M3: Notes and Sources of Knowledge
B4: 1 | C4: What is the time that one worker spends assembling a TrackR? | L4: 5 | M4: minutes
H5: 1 | I5: 5 | J5: minutes
H6: 2 | I6: see assembly calculation
B8: 2 | C8: What is the time that one worker spends picking a TrackR? | L8: =I11 -> less than assembly time
H9: 1 | I9: 5 | J9: minutes
H10: 2 | I10: see assembly calculation
H11: 3 | I11: less than assembly time
B13: 3 | C13: The final test in Assembly is done at Table #4. Should this be in the model? | L13: 2 - No
H14: 1 | I14: Yes
H15: 2 | I15: No
A17: Additional Process Knowledge
B18: 1 | C18: The current policy is that every worker gets, at minimum, 10 minutes of break in every hour
B19: 2 | C19: The current policy is that every worker gets 30 minutes for a meal break somewhere in hours 4, 5 or 6
B20: 3 | C20: The current policy of 10 minute breaks every hour is to allow time for washroom, short snack, or relief from focused assembly work
D21: ** Is walking to pick more components not a break from focused assembly? **
A23: Common Calculation Factors
B24: 1 | C24: Time Interval for model below | H24: 5 | I24: minutes
B27: Table | D27: 1 | H27: 2 | L27: 3 | P27: 4
B28: Hour | C28: Minute | D28: Assembling | E28: Picking | F28: Standby | H28: Assembling | I28: Picking | J28: Standby | L28: Assembling | M28: Picking | N28: Standby | P28: Testing/Packaging
B29: 0 | C29: 0 | D29: A | E29: C | F29: B | H29: D | I29: F | L29: G | M29: I | N29: H | P29: E
B30: 0 | C30: =C29+$H$24 -> 5 | D30: A | E30: C | H30: D | I30: F | J30: E | L30: G | M30: I | N30: H | P30: B
B31: 0 | C31: =C30+$H$24 -> 10 | D31: A | E31: C | F31: B | H31: D | I31: F | J31: E | L31: G | M31: I | P31: H
B32: 0 | C32: =C31+$H$24 -> 15 | D32: B | E32: C | F32: A | H32: E | I32: F | J32: D | L32: H | M32: I | P32: G
B33: 0 | C33: =C32+$H$24 -> 20 | D33: B | E33: C | F33: A | H33: E | I33: F | J33: D | L33: H | M33: I | P33: G
B34: 0 | C34: =C33+$H$24 -> 25 | D34: A | E34: C | F34: B | H34: D | I34: F | L34: G | M34: I | N34: H | P34: E
B35: 0 | C35: =C34+$H$24 -> 30 | D35: A | E35: B | F35: C | H35: D | I35: E | L35: G | M35: H | N35: I | P35: F
B36: 0 | C36: =C35+$H$24 -> 35 | D36: A | E36: B | F36: C | H36: D | I36: E | L36: G | M36: H | N36: I | P36: F
B37: 0 | C37: =C36+$H$24 -> 40 | D37: A | E37: C | F37: B | H37: D | I37: F | L37: H | M37: I | N37: G | P37: E
B38: 0 | C38: =C37+$H$24 -> 45 | D38: A | E38: C | F38: B | H38: D | I38: F | L38: H | M38: I | N38: G | P38: F
B39: 0 | C39: =C38+$H$24 -> 50 | D39: A | E39: C | H39: D | I39: E | J39: F | L39: G | M39: I | N39: H | P39: B
B40: 0 | C40: =C39+$H$24 -> 55 | D40: A | E40: C | F40: B | H40: D | I40: E | J40: F | L40: G | M40: I | P40: H
B41: 1 | C41: 0 | D41: B | E41: C | H41: E | I41: F | J41: D | L41: H | M41: I | N41: G | P41: A
B42: 1 | C42: =C41+$H$24 -> 5 | D42: B | E42: C | F42: A | H42: E | I42: F | J42: D | L42: H | M42: I | P42: G
B43: 1 | C43: =C42+$H$24 -> 10 | D43: B | E43: C | F43: A | H43: E | I43: F | L43: H | M43: I | N43: G | P43: G
B44: 1 | C44: =C43+$H$24 -> 15 | D44: A | E44: B | F44: C | H44: D | I44: F | J44: E | L44: G | M44: I | P44: H
B45: 1 | C45: =C44+$H$24 -> 20 | D45: A | E45: B | F45: C | H45: D | I45: F | J45: E | L45: G | M45: I | P45: H
B46: 1 | C46: =C45+$H$24 -> 25 | D46: B | E46: C | H46: E | I46: F | J46: D | L46: H | M46: I | N46: G | P46: A
B47: 1 | C47: 30 | D47: B | E47: A | H47: E | I47: D | J47: F | L47: H | M47: G | N47: I | P47: C
B48: 1 | C48: 35 | D48: B | E48: A | H48: E | I48: D | J48: F | L48: H | M48: G | N48: I | P48: C
B49: 1 | C49: 40 | D49: B | E49: C | F49: A | H49: E | I49: F | L49: H | M49: I | N49: G | P49: D
B50: 1 | C50: 45 | D50: B | E50: A | H50: E | I50: F | J50: D | L50: H | M50: I | N50: G | P50: C
B51: 1 | C51: 50 | D51: B | E51: C | F51: A | H51: E | I51: F | J51: D | L51: H | M51: I | P51: G
B52: 1 | C52: 55 | D52: B | E52: C | F52: A | H52: E | I52: F | L52: H | M52: I | N52: G | P52: D
B53: 2 | C53: 0 | D53: C | E53: A | F53: B | H53: F | I53: D | L53: I | M53: G | N53: H | P53: E
B54: 2 | C54: =C53+$H$24 -> 5 | D54: C | E54: A | F54: B | H54: F | I54: D | L54: I | M54: G | N54: H | P54: E
B55: 2 | C55: =C54+$H$24 -> 10 | D55: A | E55: B | F55: C | H55: D | I55: E | J55: F | L55: G | M55: H | P55: I
B56: 2 | C56: =C55+$H$24 -> 15 | D56: A | E56: B | F56: C | H56: D | I56: E | J56: F | L56: G | M56: H | P56: I
B57: 2 | C57: =C56+$H$24 -> 20 | D57: A | E57: B | F57: C | H57: D | I57: E | L57: G | M57: H | N57: I | P57: F
B58: 2 | C58: =C57+$H$24 -> 25 | D58: A | E58: C | H58: D | I58: E | J58: F | L58: G | M58: H | N58: I | P58: B
B59: 2 | C59: 30 | D59: A | E59: B | F59: C | H59: D | I59: E | J59: F | L59: G | M59: H | P59: I
B60: 2 | C60: 35 | D60: A | E60: B | F60: C | H60: D | I60: E | L60: G | M60: H | N60: I | P60: F
B61: 2 | C61: 40 | D61: C | E61: B | F61: A | H61: F | I61: E | J61: D | L61: I | M61: H | P61: G
B62: 2 | C62: 45 | D62: C | E62: B | F62: A | H62: F | I62: E | J62: D | L62: I | M62: H | P62: G
B63: 2 | C63: 50 | D63: C | E63: A | H63: F | I63: D | J63: E | L63: I | M63: G | N63: H | P63: B
B64: 2 | C64: 55 | D64: C | E64: A | H64: F | I64: D | J64: E | L64: I | M64: G | N64: H | P64: B
B65: 3 | C65: 0 | D65: A | E65: B | F65: C | H65: D | I65: E | J65: F | L65: G | M65: H | P65: I
B66: 3 | C66: =C65+$H$24 -> 5 | D66: A | E66: B | F66: C | H66: D | I66: E | L66: G | M66: H | N66: I | P66: F
B67: 3 | C67: =C66+$H$24 -> 10 | D67: B | E67: C | F67: A | H67: E | I67: F | J67: D | L67: H | M67: I | P67: G
B68: 3 | C68: =C67+$H$24 -> 15 | D68: B | E68: C | F68: A | H68: E | I68: F | L68: H | M68: I | N68: G | P68: D
B69: 3 | C69: =C68+$H$24 -> 20 | D69: B | E69: C | H69: E | I69: F | J69: D | L69: H | M69: I | N69: G | P69: A
B70: 3 | C70: =C69+$H$24 -> 25 | D70: B | E70: C | F70: A | H70: E | I70: F | J70: D | L70: H | M70: I | P70: G
B71: 3 | C71: 30 | D71: B | E71: A | F71: C | H71: E | I71: F | L71: H | M71: I | N71: G | P71: D
B72: 3 | C72: 35 | D72: B | E72: A | F72: C | H72: E | I72: F | J72: D | L72: H | M72: I | P72: G
B73: 3 | C73: 40 | D73: A | E73: B | H73: D | I73: F | J73: E | L73: G | M73: I | N73: H | P73: C
B74: 3 | C74: 45 | D74: A | E74: C | H74: D | I74: F | J74: E | L74: G | M74: I | N74: H | P74: B
B75: 3 | C75: 50 | D75: A | E75: B | H75: D | I75: E | J75: F | L75: G | M75: H | N75: I | P75: C
B76: 3 | C76: 55 | D76: A | E76: B | H76: D | I76: E | J76: F | L76: G | M76: H | N76: I | P76: C
B77: 4 | C77: 0 | D77: B | E77: A | F77: C | H77: E | I77: D | L77: H | M77: G | N77: I | P77: F
B78: 4 | C78: =C77+$H$24 -> 5 | D78: B | E78: A | F78: C | H78: E | I78: D | J78: F | L78: H | M78: G | P78: I
B79: 4 | C79: =C78+$H$24 -> 10 | D79: A | E79: C | F79: B | H79: D | I79: F | L79: G | M79: I | N79: H | P79: E
B80: 4 | C80: =C79+$H$24 -> 15 | D80: A | E80: C | F80: B | H80: D | I80: F | L80: G | M80: I | N80: H | P80: E
B81: 4 | C81: =C80+$H$24 -> 20 | D81: A | E81: C | H81: D | I81: F | J81: E | L81: G | M81: I | N81: H | P81: B
B82: 4 | C82: =C81+$H$24 -> 25 | D82: A | E82: C | F82: B | H82: D | I82: F | J82: E | L82: G | M82: I | P82: H
B83: 4 | C83: 30 | D83: A | E83: B | H83: D | I83: F | L83: G | M83: I | N83: H | P83: C
B84: 4 | C84: 35 | D84: A | E84: B | F84: C | H84: D | I84: F | L84: G | M84: I | P84: E
B85: 4 | C85: 40 | D85: B | E85: A | H85: E | I85: D | J85: F | L85: H | M85: G | N85: I | P85: C
B86: 4 | C86: 45 | D86: B | E86: A | H86: E | I86: D | J86: F | L86: H | M86: G | N86: I | P86: C
B87: 4 | C87: 50 | D87: C | F87: A | H87: E | I87: F | J87: D | L87: H | M87: I | N87: G | P87: B
B88: 4 | C88: 55 | D88: C | E88: B | F88: A | H88: E | I88: D | L88: H | M88: I | N88: G | P88: F
A126: Summary: | D126: =D28 -> Assembling | E126: =E28 -> Picking | F126: =F28 -> Standby | H126: =H28 -> Assembling | I126: =I28 -> Picking | J126: =J28 -> Standby | L126: =L28 -> Assembling | M126: =M28 -> Picking | N126: =N28 -> Standby
C127: A | D127: =COUNTIF(D$29:D$124,$C127) -> 30 | E127: =COUNTIF(E$29:E$124,$C127) -> 13 | F127: =COUNTIF(F$29:F$124,$C127) -> 14 | G127: D | H127: =COUNTIF(H$29:H$124,$G127) -> 30 | I127: =COUNTIF(I$29:I$124,$G127) -> 11 | J127: =COUNTIF(J$29:J$124,$G127) -> 14 | K127: G | L127: =COUNTIF(L$29:L$124,$K127) -> 28 | M127: =COUNTIF(M$29:M$124,$K127) -> 10 | N127: =COUNTIF(N$29:N$124,$K127) -> 13
C128: B | D128: =COUNTIF(D$29:D$124,$C128) -> 22 | E128: =COUNTIF(E$29:E$124,$C128) -> 19 | F128: =COUNTIF(F$29:F$124,$C128) -> 11 | G128: E | H128: =COUNTIF(H$29:H$124,$G128) -> 24 | I128: =COUNTIF(I$29:I$124,$G128) -> 16 | J128: =COUNTIF(J$29:J$124,$G128) -> 10 | K128: H | L128: =COUNTIF(L$29:L$124,$K128) -> 26 | M128: =COUNTIF(M$29:M$124,$K128) -> 14 | N128: =COUNTIF(N$29:N$124,$K128) -> 14
C129: C | D129: =COUNTIF(D$29:D$124,$C129) -> 8 | E129: =COUNTIF(E$29:E$124,$C129) -> 27 | F129: =COUNTIF(F$29:F$124,$C129) -> 16 | G129: F | H129: =COUNTIF(H$29:H$124,$G129) -> 6 | I129: =COUNTIF(I$29:I$124,$G129) -> 33 | J129: =COUNTIF(J$29:J$124,$G129) -> 14 | K129: I | L129: =COUNTIF(L$29:L$124,$K129) -> 6 | M129: =COUNTIF(M$29:M$124,$K129) -> 36 | N129: =COUNTIF(N$29:N$124,$K129) -> 13
A131: Time Analysis in Total Hours
D132: Productive | E132: Standby | H132: Productive | I132: Standby | L132: Productive | M132: Standby
C133: A | D133: =(D127+E127)*5/60 -> 3.5833333 | E133: =F127*5/60 -> 1.1666667 | G133: D | H133: =(H127+I127)*5/60 -> 3.4166667 | I133: =J127*5/60 -> 1.1666667 | K133: G | L133: =(L127+M127)*5/60 -> 3.1666667 | M133: =N127*5/60 -> 1.0833333
C134: B | D134: =(D128+E128)*5/60 -> 3.4166667 | E134: =F128*5/60 -> 0.91666667 | G134: E | H134: =(H128+I128)*5/60 -> 3.3333333 | I134: =J128*5/60 -> 0.83333333 | K134: H | L134: =(L128+M128)*5/60 -> 3.3333333 | M134: =N128*5/60 -> 1.1666667
C135: C | D135: =(D129+E129)*5/60 -> 2.9166667 | E135: =F129*5/60 -> 1.3333333 | G135: F | H135: =(H129+I129)*5/60 -> 3.25 | I135: =J129*5/60 -> 1.1666667 | K135: I | L135: =(L129+M129)*5/60 -> 3.5 | M135: =N129*5/60 -> 1.0833333
A137: Time Analysis in Percentages
D138: Productive | E138: Standby | H138: Productive | I138: Standby | L138: Productive | M138: Standby
C139: A | D139: =D133/SUM(D133+E133) -> 0.75438596 | E139: =E133/SUM(E133+D133) -> 0.24561404 | G139: D | H139: =H133/SUM(H133+I133) -> 0.74545455 | I139: =I133/SUM(I133+H133) -> 0.25454545 | K139: G | L139: =L133/SUM(L133+M133) -> 0.74509804 | M139: =M133/SUM(M133+L133) -> 0.25490196
C140: B | D140: =D134/SUM(D134+E134) -> 0.78846154 | E140: =E134/SUM(E134+D134) -> 0.21153846 | G140: E | H140: =H134/SUM(H134+I134) -> 0.8 | I140: =I134/SUM(I134+H134) -> 0.2 | K140: H | L140: =L134/SUM(L134+M134) -> 0.74074074 | M140: =M134/SUM(M134+L134) -> 0.25925926
C141: C | D141: =D135/SUM(D135+E135) -> 0.68627451 | E141: =E135/SUM(E135+D135) -> 0.31372549 | G141: F | H141: =H135/SUM(H135+I135) -> 0.73584906 | I141: =I135/SUM(I135+H135) -> 0.26415094 | K141: I | L141: =L135/SUM(L135+M135) -> 0.76363636 | M141: =M135/SUM(M135+L135) -> 0.23636364

Sheet WholeSale
A1: From the Senior BA: Get data from TrackR Data Generation
B2: of the Wholesale Price of TrackR's for 2019 Q1 for All Versions
B3: This wholesale price per TrackR is the Production Facillity's income!
A5: SalesYear | B5: 2019
A6: SalesQtr | B6: 1
A8: Row Labels | B8: Sum of WholeSalePrice
A9: Trackr A | B9: 140
A10: Trackr B | B10: 115
A11: Trackr C | B11: 155
A12: Grand Total | B12: 410

Sheet DayProdn
A1: From the Senior BA: Get data from TrackR Data Generation
B2: of the Daily Production for Each TrackR Version for 2018 Q4 and 2019 Q1
A5: BuildYear | B5: 2018 | D5: BuildYear | E5: 2019
A6: BuildQtr | B6: 4 | D6: BuildQtr | E6: 1
A8: Row Labels | B8: Sum of Quantity | D8: Row Labels | E8: Sum of Quantity
A9: Trackr A | B9: 4355 | D9: Trackr A | E9: 3934
A10: Trackr B | B10: 3944 | D10: Trackr B | E10: 3547
A11: Trackr C | B11: 3152 | D11: Trackr C | E11: 3801
A12: Grand Total | B12: 11451 | D12: Grand Total | E12: 11282

Sheet VerAvgProdn
A1: From the Senior BA: Looking for Pivot Table here
B2: of the Average Daily Production for Each TrackR Version for 2018 Q4 and 2019 Q1
A4: BuildYear | B4: 2018 | E4: BuildYear | F4: 2019
A5: BuildQtr | B5: 4 | E5: BuildQtr | F5: 1
A7: Row Labels | B7: Average of Quantity | E7: Row Labels | F7: Average of Quantity
A8: Trackr A | B8: 46.329787 | C8: =GETPIVOTDATA("Quantity",$A$7,"ProductCode","Trackr A") /GETPIVOTDATA("Quantity",$A$7) -> 1.0883515 | E8: Trackr A | F8: 53.890411 | G8: =GETPIVOTDATA("Quantity",$E$7,"ProductCode","Trackr A") /GETPIVOTDATA("Quantity",$E$7) -> 1.1320712
A9: Trackr B | B9: 42.869565 | C9: =GETPIVOTDATA("Quantity",$A$7,"ProductCode","Trackr B") /GETPIVOTDATA("Quantity",$A$7) -> 1.007066 | E9: Trackr B | F9: 46.064935 | G9: =GETPIVOTDATA("Quantity",$E$7,"ProductCode","Trackr B") /GETPIVOTDATA("Quantity",$E$7) -> 0.96768211
A10: Trackr C | B10: 37.975904 | C10: =GETPIVOTDATA("Quantity",$A$7,"ProductCode","Trackr C") /GETPIVOTDATA("Quantity",$A$7) -> 0.89210707 | E10: Trackr C | F10: 43.689655 | G10: =GETPIVOTDATA("Quantity",$E$7,"ProductCode","Trackr C") /GETPIVOTDATA("Quantity",$E$7) -> 0.91778481
A11: Grand Total | B11: 42.568773 | E11: Grand Total | F11: 47.603376
A14: Product Code | B14: Daily Average Production
A15: TrackR A | B15: =C8+G8 -> 2.2204227
A16: TrackR B | B16: =C9+G9 -> 1.9747481
A17: TrackR C | B17: =C10+G10 -> 1.8098919

Sheet POs
A1: Manufacturer | B1: ITEM # | C1: DESCRIPTION | D1: QTY | E1: UNIT PRICE | F1: TOTAL | G1: Date Of Order | H1: PO # | I1: REQUISITIONER | J1: SHIP VIA | K1: F.O.B. | L1: SHIPPING TERMS
A2: Samsung | B2: SS98AA1S | C2: 18mm x 29mm OLED screen *REFURB | D2: 12467 | E2: 26.43 | F2: =D2*E2 -> 329502.81 | G2: 42009 | H2: 1236479 | I2: T. Abhir | J2: Canada Post | K2: AB12649 | L2: C.O.D.
A3: Samsung | B3: SS89BB2S | C3: 89mm x 49mm LED screen | D3: 2346 | E3: 49.44 | F3: =D3*E3 -> 115986.24 | G3: 42009 | H3: 1236479 | I3: T. Abhir | J3: Canada Post | K3: AB12649 | L3: C.O.D.
A4: Samsung | B4: SG32VD3G | C4: 22mm x 43mm PDP screen | D4: 23499 | E4: 22.19 | F4: =D4*E4 -> 521442.81 | G4: 42009 | H4: 1236479 | I4: T. Abhir | J4: Canada Post | K4: AB12649 | L4: C.O.D.
A5: Samsung | B5: SS98AAIS | C5: 18mm x 29mm OLED screen | D5: 43647 | E5: 38.15 | F5: =D5*E5 -> 1665133.1 | G5: 42009 | H5: 1236479 | I5: T. Abhir | J5: Canada Post | K5: AB12649 | L5: C.O.D.
A6: Samsung | B6: SD43QCR4 | C6: 43mm x 89mm LCD screen | D6: 1243 | E6: 52.13 | F6: =D6*E6 -> 64797.59 | G6: 42009 | H6: 1236479 | I6: T. Abhir | J6: Canada Post | K6: AB12649 | L6: C.O.D.
A7: ST Microelectronics | B7: HG213213-221 | C7: 3-axis analogue gyroscope XT35 | D7: 2349 | E7: 0.89 | F7: =D7*E7 -> 2090.61 | G7: 42009 | H7: 1236479 | I7: T. Abhir | J7: FEDEX | K7: AB12649 | L7: C.O.D.
A8: ST Microelectronics | B8: HG213123-221 | C8: 3-axis digital gyroscope XT98 | D8: 32798 | E8: 0.57 | F8: =D8*E8 -> 18694.86 | G8: 42009 | H8: 1236479 | I8: T. Abhir | J8: FEDEX | K8: AB12649 | L8: C.O.D.
A9: ST Microelectronics | B9: HG231123-221 | C9: 3-axis digital accelerometer XT89 | D9: 12649 | E9: 0.98 | F9: =D9*E9 -> 12396.02 | G9: 42009 | H9: 1236479 | I9: T. Abhir | J9: FEDEX | K9: AB12649 | L9: C.O.D.
A10: ST Microelectronics | B10: STMA12133 | C10: 2-axis digital accelerometer | D10: 6494 | E10: 0.45 | F10: =D10*E10 -> 2922.3 | G10: 42009 | H10: 1236479 | I10: T. Abhir | J10: FEDEX | K10: AB12649 | L10: C.O.D.
A11: ST Microelectronics | B11: STMA11233 | C11: 2-axis analogue accelerometer | D11: 46795 | E11: 0.31 | F11: =D11*E11 -> 14506.45 | G11: 42009 | H11: 1236479 | I11: T. Abhir | J11: FEDEX | K11: AB12649 | L11: C.O.D.
A12: ST Microelectronics | B12: STMA111233 | C12: 2-axis analogue acceleraX89$g | D12: 234 | E12: 0.95 | F12: =D12*E12 -> 222.3 | G12: 42009 | H12: 1236479 | I12: T. Abhir | J12: FEDEX | K12: AB12649 | L12: C.O.D.
A13: American Vanadium | B13: SVLV25 | C13: Slimflex Lithium-Vanadium printed battery | D13: 4731 | E13: 12.21 | F13: =D13*E13 -> 57765.51 | G13: 42009 | H13: 332232 | I13: T. Abhir | J13: Purolator | K13: AB2232 | L13: C.O.D.
... A20: Banda Bracelets (HK) Ltd. | B20: LS1128 | C20: Gold expansion strap | D20: 14990 | E20: 10 | F20: =D20*E20 -> 149900 | G20: 42009 | H20: 1236479 | I20: T. Abhir | J20: Canada Post | K20: AB12649 | L20: C.O.D.
A21: Banda Bracelets (HK) Ltd. | F21: =D21*E21 -> 0 | G21: 42009 | H21: 1236479 | I21: T. Abhir | J21: Canada Post | K21: AB12649 | L21: C.O.D.
A22: Banda Bracelets (HK) Ltd. | B22: KK425 | C22: Economy TrackR Packaging | D22: 23560 | E22: 2 | F22: =D22*E22 -> 47120 | G22: 42009 | H22: 1236479 | I22: T. Abhir | J22: Canada Post | K22: AB12649 | L22: C.O.D.
A23: Banda Bracelets (HK) Ltd. | B23: KK433 | C23: Standard TrackR packaging | D23: 26660 | E23: 3 | F23: =D23*E23 -> 79980 | G23: 42009 | H23: 1236479 | I23: T. Abhir | J23: Canada Post | K23: AB12649 | L23: C.O.D.
A24: Banda Bracelets (HK) Ltd. | B24: KK438 | C24: DeLuxe TrackR packaging | D24: 19820 | E24: 4 | F24: =D24*E24 -> 79280 | G24: 42009 | H24: 1236479 | I24: T. Abhir | J24: Canada Post | K24: AB12649 | L24: C.O.D.
A25: BlueGiga | B25: BLE112 | C25: Bluetooth 4.0 low energy chipset | D25: 32146 | E25: 2 | F25: =D25*E25 -> 64292 | G25: 42009 | H25: 1236479 | I25: T. Abhir | J25: PUROLATOR | K25: AB12649 | L25: C.O.D.
A26: Qualcomm | B26: BD2099733AAB | C26: Micro Bluetooth transmitter | D26: 13249 | E26: 4.32 | F26: =D26*E26 -> 57235.68 | G26: 42009 | H26: 15348679 | I26: T. Abhir | J26: Purolator | K26: AB2468 | L26: C.O.D.
A27: Qualcomm | B27: BD209111131BB | C27: Micro-transmitter for 3G communication | D27: 1123 | E27: 0.89 | F27: =D27*E27 -> 999.47 | G27: 42009 | H27: 15348679 | I27: T. Abhir | J27: Purolator | K27: AB2468 | L27: C.O.D.
A28: Qualcomm | B28: BD21111132BD | C28: PCB housing | D28: 46579 | E28: 17.42 | F28: =D28*E28 -> 811406.18 | G28: 42009 | H28: 15348679 | I28: T. Abhir | J28: Purolator | K28: AB2468 | L28: C.O.D.
A29: Qualcomm | B29: BD2098733AAB | C29: Secure housing for orientation equipment | D29: 62197 | E29: 4.15 | F29: =D29*E29 -> 258117.55 | G29: 42009 | H29: 15348679 | I29: T. Abhir | J29: Purolator | K29: AB2468 | L29: C.O.D.
A30: Qualcomm | B30: QC0334542BGD | C30: Snapdragon 800 | D30: 3246 | E30: 29.76 | F30: =D30*E30 -> 96600.96 | G30: 42009 | H30: 15348679 | I30: T. Abhir | J30: Purolator | K30: AB2468 | L30: C.O.D.
A31: Qualcomm | B31: BD348279555AC | C31: Micro-transmitter for X7 LTE modem | D31: 1436 | E31: 2.49 | F31: =D31*E31 -> 3575.64 | G31: 42009 | H31: 15348679 | I31: T. Abhir | J31: Purolator | K31: AB2468 | L31: C.O.D.
A32: Qualcomm | B32: BD20911131BB | C32: Micro-transmitter for LTE communication | D32: 43795 | E32: 1.88 | F32: =D32*E32 -> 82334.6 | G32: 42009 | H32: 15348679 | I32: T. Abhir | J32: Purolator | K32: AB2468 | L32: C.O.D.
A33: Sandisk | B33: SDMALBB3033G | C33: 2GB FLASH NAND | D33: 43121 | E33: 4 | F33: =D33*E33 -> 172484 | G33: 42009 | H33: 1236479 | I33: T. Abhir | J33: PUROLATOR | K33: AB12649 | L33: C.O.D.
A34: Mitchell's Plastics | B34: MPC432119-2 | C34: Vulcanized Rubber casing | D34: 15423 | E34: =(7.34*0.9) -> 6.606 | F34: =D34*E34 -> 101884.34 | G34: 42009 | H34: 332232 | I34: T. Abhir | J34: Purolator | K34: AB2232 | L34: C.O.D.
A35: Mitchell's Plastics | B35: MPC44422 | C35: Rigid plastic pins | D35: =D34*2 -> 30846 | E35: =(0.09*0.9) -> 0.081 | F35: =D35*E35 -> 2498.526 | G35: 42009 | H35: 332232 | I35: T. Abhir | J35: Purolator | K35: AB2232 | L35: C.O.D.
A36: Foxconn | B36: Packing Foam | D36: 1 | E36: 0.05 | F36: 0.05$ | G36: 42350 | H36: A423232
A37: Foxconn | B37: Packing Slip | D37: 1 | E37: 0.05 | F37: 0.05$ | G37: 42350 | H37: A423232
A38: Foxconn | B38: Packaging | D38: 712 | E38: 0.1 | F38: 71.2$ | G38: 42350 | H38: A423232
A39: Foxconn | B39: FnOFI-OM212 | D39: 845 | E39: 9.12 | F39: 7.706.40 $ | G39: 42350 | H39: A423232
A40: Foxconn | B40: FnOFI-GM1212 | D40: 223 | E40: 44.12 | F40: 9.838.76 $ | G40: 42350 | H40: A423232
A41: Foxconn | B41: PnOFI-GN1242 | D41: 915 | E41: 21.73 | F41: 19.882.95 $ | G41: 42350 | H41: A423232
A42: Foxconn | B42: FnOFI-GN1212 | C42: Main printed circuit board (PCB) | D42: 1455 | E42: 14.99 | F42: 21.810.45 $ | G42: 42350 | H42: A423232
A43: Foxconn | B43: FnO0FI-GN7212 | D43: 2078 | E43: 56.78 | F43: 117.988.84 $ | G43: 42350 | H43: A423232
A44: Foxconn | B44: VnOFI-GN7212 | D44: 212 | E44: 81.01 | F44: 17.174.12$ | G44: 42350 | H44: A423232
A45: Foxconn | B45: FnOFI-GN1213 | D45: 1 | E45: 37.78 | F45: 37.78$ | G45: 42350 | H45: A423232
A46: Foxconn | B46: Misc [Mystery] Packaging Materials | D46: 200 | E46: 1 | F46: 200$ | G46: 42350 | H46: A423232

Sheet Shelving Inventory list
A1: Part Number | B1: Row | C1: Bay | D1: Fixed Location
A2: BLE112 | B2: 1 | C2: A | D2: Yes
A3: KXQ91CZD9HD | B3: 1 | C3: B | D3: Yes
A4: TJT88COB2WC | B4: 1 | C4: C | D4: Yes
A5: UIH36QWQ4HW | B5: 1 | C5: D | D5: No
A6: SFLV25 | B6: 2 | C6: A | D6: Yes
A7: XWC78UDC5SC | B7: 2 | C7: B | D7: No
A8: QTB96PHQ5WB | B8: 2 | C8: C | D8: Yes
A9: NMI74BKG4GE | B9: 2 | C9: D | D9: Yes
A10: AVG29VUB7SL | B10: 3 | C10: A | D10: No
A11: VEA77BAF2MB | B11: 3 | C11: B | D11: No
A12: SDMALBB3033G | B12: 3 | C12: C | D12: Yes
A13: GBN66GUJ8EZ | B13: 3 | C13: D | D13: Yes
... A72: KK438 | B72: 13 | C72: D | D72: Yes
